Workbook

Sheet boitiers actifs
A1: Name | B1: Gateway | C1: Boitier | D1: License Plate | E1: VIN | F1: Driver | G1: Vehicle Type | H1: Gross Vehicle Weight | I1: Weight Unit | J1: Tags | K1: Site | L1: Odometer (km) | M1: Engine Hours | N1: Camera | O1: Camera Serial | P1: Multicam | Q1: Multicam Serial | R1: Battery | S1: Power State | T1: Install Photos | U1: Device Calibration Status | V1: Last Connected | W1: Last Location | X1: Wifi SSID | Y1: Wifi Up | Z1: Wifi IP | AA1: Wifi Access Point Data Usage (MB) | AB1: Cell Operator | AC1: Cell Up | AD1: Ethernet IP | AE1: Cable SKU | AF1: Ethernet Up | AG1: Vehicle Regulation Mode
A2: DW-773-YG | B2: VG54-EU | C2: m | D2: DW-773-YG | E2: VF640J567FB002628 | F2: n/a | G2: Truck | H2: 16000 | I2: KG | J2: TG CENTRE EST | K2: =VLOOKUP(J2, correspondance!A:B, 2, FALSE) -> TG CENTRE EST | L2: 592571.2 | M2: 11541 | N2: n/a | O2: n/a | P2: n/a | Q2: n/a | R2: n/a | S2: n/a | T2: n/a | U2: Calibrated | V2: 14 avr. 2026 10:01 | W2: D 37, Planchez, Bourgogne-Franche-Comté, 58230 | X2: n/a | Y2: n/a | Z2: n/a | AA2: 0 | AB2: F SFR | AC2: true | AD2: n/a | AE2: CBL-VG-CFMS | AF2: n/a | AG2: Regulated
A3: FR-281-MN | B3: VG54-EU | C3: GGMW-NMZ-NT6 | D3: FR-281-MN | E3: VF620J86XLB007983 | F3: n/a | G3: Truck | H3: 19000 | I3: KG | J3: TG La Roche sur Yon (PF) | K3: =VLOOKUP(J3, correspondance!A:B, 2, FALSE) -> TG La Roche sur Yon (PF) | L3: 341211.2 | M3: 9569 | N3: n/a | O3: n/a | P3: n/a | Q3: n/a | R3: n/a | S3: n/a | T3: n/a | U3: Calibrated | V3: 14 avr. 2026 10:01 | W3: Impasse des Ajoncs, La Roche-sur-Yon, Pays de la Loire, 85000 | X3: n/a | Y3: n/a | Z3: n/a | AA3: 0 | AB3: F SFR | AC3: true | AD3: n/a | AE3: CBL-VG-CHGV | AF3: n/a | AG3: Regulated
A4: FT-601-CN | B4: VG54-EU | C4: G4YX-EK6-Z7R | D4: FT-601-CN | E4: VF620J861LB007967 | F4: n/a | G4: Truck | H4: 19000 | I4: KG | J4: TG La Roche sur Yon (PF) | K4: =VLOOKUP(J4, correspondance!A:B, 2, FALSE) -> TG La Roche sur Yon (PF) | L4: 299910.7 | M4: 9088 | N4: n/a | O4: n/a | P4: n/a | Q4: n/a | R4: n/a | S4: n/a | T4: n/a | U4: Calibrated | V4: 14 avr. 2026 10:01 | W4: Boulevard de Port Gentil, Thouars, Nouvelle-Aquitaine, 79100 | X4: n/a | Y4: n/a | Z4: n/a | AA4: 0 | AB4: F SFR | AC4: true | AD4: n/a | AE4: CBL-VG-CHGV | AF4: n/a | AG4: Regulated
A5: GR-695-TJ | B5: VG54-EU | C5: GU3X-UGS-9YV | D5: n/a | E5: ZCFCP35A50D736039 | F5: n/a | J5: Site Bonneville | K5: =VLOOKUP(J5, correspondance!A:B, 2, FALSE) -> Site Bonneville | L5: 113342.3 | M5: 1930 | N5: n/a | O5: n/a | P5: n/a | Q5: n/a | R5: n/a | S5: n/a | T5: n/a | U5: Calibrated | V5: 14 avr. 2026 10:01 | W5: Route de Sallanches, Demi-Quartier, Auvergne-Rhône-Alpes, 74120 | X5: n/a | Y5: n/a | Z5: n/a | AA5: 0 | AB5: F SFR | AC5: true | AD5: n/a | AE5: CBL-VG-COBDII-Y0 | AF5: n/a | AG5: Regulated
A6: GM-743-ST | B6: VG54-EU | C6: GR58-DA4-PVN | D6: GM-743-ST | E6: VF640J565NB019779 | F6: n/a | G6: Truck | H6: 10000 | I6: KG | J6: TG IDF VALENTON | K6: =VLOOKUP(J6, correspondance!A:B, 2, FALSE) -> TG IDF VALENTON | L6: 70386.9 | M6: 3442 | N6: n/a | O6: n/a | P6: n/a | Q6: n/a | R6: n/a | S6: n/a | T6: n/a | U6: Calibrated | V6: 14 avr. 2026 10:01 | W6: Rue de Schomberg, Paris, Île-de-France, 75004 | X6: n/a | Y6: n/a | Z6: n/a | AA6: 0 | AB6: F SFR | AC6: true | AD6: n/a | AE6: CBL-VG-CHGV | AF6: n/a | AG6: Regulated
A7: GM-757-SV | B7: VG54-EU | C7: GWKS-B4Z-AV2 | D7: GM-757-SV | E7: VF620J961NB000566 | F7: n/a | G7: Truck | H7: 16776 | I7: KG | J7: TG IDF VALENTON | K7: =VLOOKUP(J7, correspondance!A:B, 2, FALSE) -> TG IDF VALENTON | L7: 30947.7 | M7: 2396 | N7: n/a | O7: n/a | P7: n/a | Q7: n/a | R7: n/a | S7: n/a | T7: n/a | U7: Calibrated | V7: 14 avr. 2026 10:01 | W7: 14 Rue Ferme de la Tour, Valenton, Île-de-France, 94460 | X7: n/a | Y7: n/a | Z7: n/a | AA7: 0 | AB7: F SFR | AC7: true | AD7: n/a | AE7: CBL-VG-CHGV | AF7: n/a | AG7: Regulated
A8: FT-966-XF | B8: VG54-EU | C8: GECZ-HHA-E3F | D8: FT-966-XF | E8: VF620J861LB008231 | F8: n/a | G8: Truck | H8: 16000 | I8: KG | J8: TG IDF VALENTON | K8: =VLOOKUP(J8, correspondance!A:B, 2, FALSE) -> TG IDF VALENTON | L8: 167192.0 | M8: 11883 | N8: n/a | O8: n/a | P8: n/a | Q8: n/a | R8: n/a | S8: n/a | T8: n/a | U8: Calibrated | V8: 14 avr. 2026 10:01 | W8: 14 Rue Ferme de la Tour, Valenton, Île-de-France, 94460 | X8: n/a | Y8: n/a | Z8: n/a | AA8: 0 | AB8: F SFR | AC8: true | AD8: n/a | AE8: CBL-VG-CHGV | AF8: n/a | AG8: Regulated
A9: EJ-847-PS | B9: VG54-EU | C9: GZAK-5WG-488 | D9: EJ-847-PS | E9: ZCFCD35A40D578513 | F9: n/a | G9: Truck | H9: 3500 | I9: KG | J9: TG IDF VALENTON | K9: =VLOOKUP(J9, correspondance!A:B, 2, FALSE) -> TG IDF VALENTON | L9: 366128.4 | M9: 7298 | N9: n/a | O9: n/a | P9: n/a | Q9: n/a | R9: n/a | S9: n/a | T9: n/a | U9: Calibrated | V9: 14 avr. 2026 10:01 | W9: Boulevard Périphérique Extérieur, Paris, Île-de-France, 75014 | X9: n/a | Y9: n/a | Z9: n/a | AA9: 0 | AB9: F SFR | AC9: true | AD9: n/a | AE9: CBL-VG-COBDII-Y0 | AF9: n/a | AG9: Regulated
A10: EA-206-DW | B10: VG54-EU | C10: GDSE-UXJ-C7X | D10: EA-206-DW | E10: VF640J562GB003610 | F10: n/a | G10: Truck | H10: 16000 | I10: KG | J10: TG Rennes (PF) | K10: =VLOOKUP(J10, correspondance!A:B, 2, FALSE) -> TG Rennes (PF) | L10: 388728.9 | M10: 8304 | N10: n/a | O10: n/a | P10: n/a | Q10: n/a | R10: n/a | S10: n/a | T10: n/a | U10: Calibrated | V10: 14 avr. 2026 10:01 | W10: Caulnes, Bretagne, 22350 | X10: n/a | Y10: n/a | Z10: n/a | AA10: 0 | AB10: F SFR | AC10: true | AD10: n/a | AE10: CBL-VG-CHGV | AF10: n/a | AG10: Regulated
A11: FC-613-XX | B11: VG54-EU | C11: GMK3-VUC-3E4 | D11: FC-613-XX | E11: VF620J860KB005786 | F11: n/a | G11: Truck | H11: 16000 | I11: KG | J11: TG Ouest | K11: =VLOOKUP(J11, correspondance!A:B, 2, FALSE) -> TG Ouest | L11: 334087.3 | M11: 10688 | N11: n/a | O11: n/a | P11: n/a | Q11: n/a | R11: n/a | S11: n/a | T11: n/a | U11: Calibrated | V11: 14 avr. 2026 10:01 | W11: 13 Promenade du Bout du Monde, Angers, Pays de la Loire, 49100 | X11: n/a | Y11: n/a | Z11: n/a | AA11: 0 | AB11: F SFR | AC11: true | AD11: n/a | AE11: CBL-VG-CHGV | AF11: n/a | AG11: Regulated
A12: GH-033-QX | B12: VG54-EU | C12: GYFP-PJJ-FJF | D12: GH-033-QX | E12: VF611A367ND038308 | F12: n/a | G12: Truck | H12: 19000 | I12: KG | J12: TG Ouest | K12: =VLOOKUP(J12, correspondance!A:B, 2, FALSE) -> TG Ouest | L12: 278333.1 | M12: 3912 | N12: n/a | O12: n/a | P12: n/a | Q12: n/a | R12: n/a | S12: n/a | T12: n/a | U12: Calibrated | V12: 14 avr. 2026 10:01 | W12: Rue Véga, Carquefou, Pays de la Loire, 44470 | X12: n/a | Y12: n/a | Z12: n/a | AA12: 0 | AB12: F SFR | AC12: true | AD12: n/a | AE12: CBL-VG-CHGV | AF12: n/a | AG12: Regulated
A13: FA-902-XZ | B13: VG54-EU | C13: GMCU-T8J-A9U | D13: FA-902-XZ | E13: XLRAEL2700L475280 | F13: n/a | G13: Truck | H13: 15500 | I13: KG | J13: TG Ouest | K13: =VLOOKUP(J13, correspondance!A:B, 2, FALSE) -> TG Ouest | L13: 375445.3 | M13: 9461 | N13: n/a | O13: n/a | P13: n/a | Q13: n/a | R13: n/a | S13: n/a | T13: n/a | U13: Calibrated | V13: 14 avr. 2026 10:01 | W13: Angers, Pays de la Loire, 49035 | X13: n/a | Y13: n/a | Z13: n/a | AA13: 0 | AB13: F SFR | AC13: true | AD13: n/a | AE13: CBL-VG-CFMS | AF13: n/a | AG13: Regulated
A14: GH-931-QW | B14: VG54-EU | C14: GYHU-FUP-SY9 | D14: GH-931-QW | E14: VF611A365ND038307 | F14: n/a | G14: Truck | H14: 19000 | I14: KG | J14: TG Ouest | K14: =VLOOKUP(J14, correspondance!A:B, 2, FALSE) -> TG Ouest | L14: 283091.8 | M14: 4238 | N14: n/a | O14: n/a | P14: n/a | Q14: n/a | R14: n/a | S14: n/a | T14: n/a | U14: Calibrated | V14: 14 avr. 2026 10:01 | W14: Rue Véga, Carquefou, Pays de la Loire, 44470 | X14: n/a | Y14: n/a | Z14: n/a | AA14: 0 | AB14: F SFR | AC14: true | AD14: n/a | AE14: CBL-VG-CHGV | AF14: n/a | AG14: Regulated
A15: ER-911-TW | B15: VG54-EU | C15: GGWD-5M4-6UZ | D15: ER-911-TW | E15: VF640J566HB007659 | F15: n/a | G15: Truck | H15: 16000 | I15: KG | J15: TG Rennes (PF) | K15: =VLOOKUP(J15, correspondance!A:B, 2, FALSE) -> TG Rennes (PF) | L15: 395812.3 | M15: 8684 | N15: n/a | O15: n/a | P15: n/a | Q15: n/a | R15: n/a | S15: n/a | T15: n/a | U15: Calibrated | V15: 14 avr. 2026 10:01 | W15: 13ter Place des Lices, Rennes, Bretagne, 35000 | X15: n/a | Y15: n/a | Z15: n/a | AA15: 0 | AB15: F SFR | AC15: true | AD15: n/a | AE15: CBL-VG-CHGV | AF15: n/a | AG15: Regulated
A16: DX-992-LX | B16: VG54-EU | C16: GA6Y-ACC-ZGN | D16: DX-992-LX | E16: YV2T0X1A2FZ103749 | F16: n/a | G16: Truck | H16: 16000 | I16: KG | J16: TG St Brieuc (PF) | K16: =VLOOKUP(J16, correspondance!A:B, 2, FALSE) -> TG St Brieuc (PF) | L16: 482584.4 | M16: 10496 | N16: n/a | O16: n/a | P16: n/a | Q16: n/a | R16: n/a | S16: n/a | T16: n/a | U16: Calibrated | V16: 14 avr. 2026 10:01 | W16: N 24, Ploërmel, Bretagne, 56800 | X16: n/a | Y16: n/a | Z16: n/a | AA16: 0 | AB16: F SFR | AC16: true | AD16: n/a | AE16: CBL-VG-CHGV | AF16: n/a | AG16: Regulated
A17: GS-381-DM | B17: VG54-EU | C17: GVEY-USU-EYR | D17: GS-381-DM | E17: VF620J868PB012198 | F17: n/a | G17: Truck | H17: 19000 | I17: KG | J17: B100, TG Ouest | K17: =VLOOKUP(J17, correspondance!A:B, 2, FALSE) -> TG Ouest | L17: 126868.6 | M17: 3207 | N17: n/a | O17: n/a | P17: n/a | Q17: n/a | R17: n/a | S17: n/a | T17: n/a | U17: Calibrated | V17: 14 avr. 2026 10:01 | W17: 11 Rue Lieutenant-Colonel Dubois, Vezin-le-Coquet, Bretagne, 35132 | X17: n/a | Y17: n/a | Z17: n/a | AA17: 0 | AB17: F SFR | AC17: true | AD17: n/a | AE17: CBL-VG-CHGV | AF17: n/a | AG17: Regulated
... A119: HB-986-WN | B119: VG54-EU | C119: GNK2-PDC-NCY | D119: HB-986-WN | E119: VF611A362SD055870 | F119: n/a | G119: Truck | H119: 44000 | I119: KG | J119: TG CENTRE EST | K119: =VLOOKUP(J119, correspondance!A:B, 2, FALSE) -> TG CENTRE EST | L119: 125145.7 | M119: 2033 | N119: n/a | O119: n/a | P119: n/a | Q119: n/a | R119: n/a | S119: n/a | T119: n/a | U119: Calibrated | V119: 14 avr. 2026 10:01 | W119: Chemin des Petits Rocs, Avermes, Auvergne-Rhône-Alpes, 03000 | X119: n/a | Y119: n/a | Z119: n/a | AA119: 0 | AB119: F SFR | AC119: true | AD119: n/a | AE119: CBL-VG-CHGV | AF119: n/a | AG119: Regulated
A120: DW-586-QW | B120: VG54-EU | C120: GGB2-M5J-SJH | D120: DW-586-QW | E120: VF620J866TB016048 | F120: n/a | G120: Truck | H120: 19000 | I120: KG | J120: TG CENTRE EST | K120: =VLOOKUP(J120, correspondance!A:B, 2, FALSE) -> TG CENTRE EST | L120: 1411.9 | M120: 27 | N120: n/a | O120: n/a | P120: n/a | Q120: n/a | R120: n/a | S120: n/a | T120: n/a | U120: Calibrated | V120: 14 avr. 2026 10:01 | W120: 2 Place des Roches, Lormes, Bourgogne-Franche-Comté, 58140 | X120: n/a | Y120: n/a | Z120: n/a | AA120: 0 | AB120: F SFR | AC120: true | AD120: n/a | AF120: n/a | AG120: Regulated
A121: FQ-744-SP | B121: VG54-EU | C121: GC8K-U9P-GU7 | D121: FQ-744-SP | E121: VF611A364LD025478 | F121: n/a | G121: Truck | H121: 40000 | I121: KG | J121: TG CENTRE EST | K121: =VLOOKUP(J121, correspondance!A:B, 2, FALSE) -> TG CENTRE EST | L121: 675957.9 | M121: 10954 | N121: n/a | O121: n/a | P121: n/a | Q121: n/a | R121: n/a | S121: n/a | T121: n/a | U121: Calibrated | V121: 14 avr. 2026 10:01 | W121: Rue Jacques Cœur, Yzeure, Auvergne-Rhône-Alpes, 03400 | X121: n/a | Y121: n/a | Z121: n/a | AA121: 0 | AB121: F SFR | AC121: true | AD121: n/a | AE121: CBL-VG-CHGV | AF121: n/a | AG121: Regulated
A122: GR-695-TJ | B122: VG54-EU | C122: GN93-7NK-JKH | D122: GR-695-TJ | E122: ZCFCP35A50D736039 | F122: n/a | G122: Truck | H122: 3500 | I122: KG | J122: Site Bonneville | K122: =VLOOKUP(J122, correspondance!A:B, 2, FALSE) -> Site Bonneville | L122: 113342.3 | M122: 1930 | N122: n/a | O122: n/a | P122: n/a | Q122: n/a | R122: n/a | S122: n/a | T122: n/a | U122: Calibrated | V122: 14 avr. 2026 10:01 | W122: Route de Sallanches, Demi-Quartier, Auvergne-Rhône-Alpes, 74120 | X122: n/a | Y122: n/a | Z122: n/a | AA122: 0 | AB122: F SFR | AC122: true | AD122: n/a | AE122: CBL-VG-COBDII-Y0 | AF122: n/a | AG122: Regulated
A123: DR-208-FB | B123: VG54-EU | C123: G5AT-K89-5RA | D123: DR-208-FB | E123: VF620J864FB000788 | F123: n/a | G123: Truck | H123: 19000 | I123: KG | J123: TG CENTRE EST | K123: =VLOOKUP(J123, correspondance!A:B, 2, FALSE) -> TG CENTRE EST | L123: 716557.0 | M123: 13595 | N123: n/a | O123: n/a | P123: n/a | Q123: n/a | R123: n/a | S123: n/a | T123: n/a | U123: Calibrated | V123: 10 avr. 2026 17:15 | W123: D 707, Avermes, Auvergne-Rhône-Alpes, 03000 | X123: n/a | Y123: n/a | Z123: n/a | AA123: 0 | AB123: F SFR | AC123: true | AD123: n/a | AE123: CBL-VG-CFMS | AF123: n/a | AG123: Regulated
A124: EQ-533-MQ | B124: VG54-EU | C124: GYGM-VD2-X5E | D124: EQ-533-MQ | E124: VF611A368TD062596 | F124: n/a | G124: Truck | H124: 19000 | I124: KG | J124: TG CENTRE EST | K124: =VLOOKUP(J124, correspondance!A:B, 2, FALSE) -> TG CENTRE EST | L124: 1243.3 | M124: 22 | N124: n/a | O124: n/a | P124: n/a | Q124: n/a | R124: n/a | S124: n/a | T124: n/a | U124: Calibrated | V124: 14 avr. 2026 10:01 | W124: D 951, Saint-Aignan-des-Noyers, Centre-Val de Loire, 18600 | X124: n/a | Y124: n/a | Z124: n/a | AA124: 0 | AB124: F SFR | AC124: true | AD124: n/a | AE124: CBL-VG-CHGV | AF124: n/a | AG124: Regulated
A125: GY-968-QC | B125: VG54-EU | C125: G3R5-YDE-7UN | D125: GY-968-QC | E125: VF620J867RB012938 | F125: n/a | G125: Truck | H125: 16000 | I125: KG | J125: TG CENTRE EST | K125: =VLOOKUP(J125, correspondance!A:B, 2, FALSE) -> TG CENTRE EST | L125: 117692.1 | M125: 2290 | N125: n/a | O125: n/a | P125: n/a | Q125: n/a | R125: n/a | S125: n/a | T125: n/a | U125: Calibrated | V125: 14 avr. 2026 10:01 | W125: Avenue de Chazeuil, Varennes-sur-Allier, Auvergne-Rhône-Alpes, 03150 | X125: n/a | Y125: n/a | Z125: n/a | AA125: 0 | AB125: F SFR | AC125: true | AD125: n/a | AE125: CBL-VG-CHGV | AF125: n/a | AG125: Regulated
A126: DW-935-QW | B126: VG54-EU | C126: G5KU-FZC-EEC | D126: DW-935-QW | E126: VF620J868TB016049 | F126: n/a | G126: Truck | H126: 19000 | I126: KG | J126: TG CENTRE EST | K126: =VLOOKUP(J126, correspondance!A:B, 2, FALSE) -> TG CENTRE EST | L126: 2810.4 | M126: 55 | N126: n/a | O126: n/a | P126: n/a | Q126: n/a | R126: n/a | S126: n/a | T126: n/a | U126: Calibrated | V126: 14 avr. 2026 10:01 | W126: Rue du Courtioux, Marcillat-en-Combraille, Auvergne-Rhône-Alpes, 03420 | X126: n/a | Y126: n/a | Z126: n/a | AA126: 0 | AB126: F SFR | AC126: true | AD126: n/a | AE126: CBL-VG-CHGV | AF126: n/a | AG126: Regulated
A127: CC-024-RY | B127: VG54-EU | C127: GPR4-BUW-US5 | D127: CC-024-RY | E127: VF624GPA000057362 | F127: n/a | G127: Truck | H127: 19000 | I127: KG | J127: TG CENTRE OUEST | K127: =VLOOKUP(J127, correspondance!A:B, 2, FALSE) -> TG CENTRE OUEST | L127: 1457279.0 | M127: n/a | N127: n/a | O127: n/a | P127: n/a | Q127: n/a | R127: n/a | S127: n/a | T127: n/a | U127: Calibrated | V127: 14 avr. 2026 10:01 | W127: TRANSGOURMET CENTRE OUEST | X127: n/a | Y127: n/a | Z127: n/a | AA127: 0 | AB127: F SFR | AC127: true | AD127: n/a | AE127: CBL-VG-CHGV | AF127: n/a | AG127: Regulated
A128: GX-919-WX | B128: VG54-EU | C128: G8WH-GZ2-974 | D128: GX-919-WX | E128: VF620J164RB001647 | F128: n/a | G128: Truck | H128: 19000 | I128: KG | J128: TG CENTRE OUEST | K128: =VLOOKUP(J128, correspondance!A:B, 2, FALSE) -> TG CENTRE OUEST | L128: 162669.8 | M128: 2294 | N128: n/a | O128: n/a | P128: n/a | Q128: n/a | R128: n/a | S128: n/a | T128: n/a | U128: Calibrated | V128: 14 avr. 2026 10:01 | W128: TRANSGOURMET CENTRE OUEST | X128: n/a | Y128: n/a | Z128: n/a | AA128: 0 | AB128: F SFR | AC128: true | AD128: n/a | AE128: CBL-VG-CHGV | AF128: n/a | AG128: Regulated
A129: GR-794-YF | B129: VG54-EU | C129: GV3S-WZE-PGM | D129: GR-794-YF | E129: VF611A365RD046753 | F129: n/a | G129: Truck | H129: 19000 | I129: KG | J129: TG CENTRE OUEST | K129: =VLOOKUP(J129, correspondance!A:B, 2, FALSE) -> TG CENTRE OUEST | L129: 403807.3 | M129: 5948 | N129: n/a | O129: n/a | P129: n/a | Q129: n/a | R129: n/a | S129: n/a | T129: n/a | U129: Calibrated | V129: 14 avr. 2026 10:01 | W129: TRANSGOURMET CENTRE OUEST | X129: n/a | Y129: n/a | Z129: n/a | AA129: 0 | AB129: F SFR | AC129: true | AD129: n/a | AE129: CBL-VG-CHGV | AF129: n/a | AG129: Regulated
A130: HB-141-VX | B130: VG54-EU | C130: G9AU-FEG-352 | D130: HB-141-VX | E130: VF620J860SB014438 | F130: MICHALAK Michael | G130: Truck | H130: 19000 | I130: KG | J130: TG COULOMMIERS | K130: =VLOOKUP(J130, correspondance!A:B, 2, FALSE) -> TG COULOMMIERS | L130: 35491.7 | M130: 1500 | N130: n/a | O130: n/a | P130: n/a | Q130: n/a | R130: n/a | S130: n/a | T130: n/a | U130: Calibrated | V130: 14 avr. 2026 10:01 | W130: D 402, Beautheil-Saints, Île-de-France, 77120 | X130: n/a | Y130: n/a | Z130: n/a | AA130: 0 | AB130: F SFR | AC130: true | AD130: n/a | AE130: CBL-VG-CHGV | AF130: n/a | AG130: Regulated
A131: HB-491-NW | B131: VG54-EU | C131: GSFX-XMZ-C49 | D131: HB-491-NW | E131: VF620J860SB014410 | F131: n/a | G131: Truck | H131: 19000 | I131: KG | J131: TG COULOMMIERS | K131: =VLOOKUP(J131, correspondance!A:B, 2, FALSE) -> TG COULOMMIERS | L131: 51783.5 | M131: 2145 | N131: n/a | O131: n/a | P131: n/a | Q131: n/a | R131: n/a | S131: n/a | T131: n/a | U131: Calibrated | V131: 14 avr. 2026 10:01 | W131: Rue du Jariel, Coulommiers, Île-de-France, 77120 | X131: n/a | Y131: n/a | Z131: n/a | AA131: 0 | AB131: F SFR | AC131: true | AD131: n/a | AE131: CBL-VG-CHGV | AF131: n/a | AG131: Regulated
A132: DX-989-DN | B132: VG54-EU | C132: GRJR-CEU-MMF | D132: DX-989-DN | E132: VF620J862FB001390 | F132: n/a | G132: Truck | H132: 19000 | I132: KG | J132: TG COULOMMIERS | K132: =VLOOKUP(J132, correspondance!A:B, 2, FALSE) -> TG COULOMMIERS | L132: 507794.3 | M132: 12085 | N132: n/a | O132: n/a | P132: n/a | Q132: n/a | R132: n/a | S132: n/a | T132: n/a | U132: Calibrated | V132: 14 avr. 2026 10:01 | W132: D 402, Beautheil-Saints, Île-de-France, 77120 | X132: n/a | Y132: n/a | Z132: n/a | AA132: 0 | AB132: F SFR | AC132: true | AD132: n/a | AE132: CBL-VG-CHGV | AF132: n/a | AG132: Regulated
... A169: GP-949-BQ | B169: VG54-EU | C169: GBY2-STX-DPY | D169: GP-949-BQ | E169: VF620J861PB011359 | F169: n/a | G169: Truck | H169: 19000 | I169: KG | J169: Site Bonneville | K169: =VLOOKUP(J169, correspondance!A:B, 2, FALSE) -> Site Bonneville | L169: 165885.6 | M169: 4339 | N169: n/a | O169: n/a | P169: n/a | Q169: n/a | R169: n/a | S169: n/a | T169: n/a | U169: Calibrated | V169: 14 avr. 2026 10:01 | W169: Centre Commercial le Warrens, Sallanches, Auvergne-Rhône-Alpes, 74700 | X169: n/a | Y169: n/a | Z169: n/a | AA169: 0 | AB169: F SFR | AC169: true | AD169: n/a | AE169: CBL-VG-CHGV | AF169: n/a | AG169: Regulated
A170: GT-494-NY | B170: VG55-EU | C170: GGMF-GRK-ZUG | D170: GT-494-NY | E170: VF1VAE00070169427 | F170: n/a | G170: Truck | J170: TGFL-DELTA LOGISTIQUE | K170: =VLOOKUP(J170, correspondance!A:B, 2, FALSE) -> TGFL-DELTA LOGISTIQUE | L170: 486.0 | M170: n/a | N170: n/a | O170: n/a | P170: n/a | Q170: n/a | R170: n/a | S170: n/a | T170: n/a | U170: Calibrated | V170: 14 avr. 2026 10:01 | W170: Avenue Charles Lindbergh, Rungis, Île-de-France, 94150 | X170: n/a | Y170: n/a | Z170: n/a | AA170: 0 | AB170: Orange F | AC170: true | AD170: n/a | AE170: CBL-VG-COBDII-Y0 | AF170: n/a | AG170: Regulated
A171: GN-240-VQ | B171: VG55-EU | C171: GFPW-3PW-5YA | D171: GN-240-VQ | E171: VF1VAE00070169427 | F171: n/a | G171: Truck | J171: TGFL-DELTA LOGISTIQUE | K171: =VLOOKUP(J171, correspondance!A:B, 2, FALSE) -> TGFL-DELTA LOGISTIQUE | L171: 31601.0 | M171: n/a | N171: n/a | O171: n/a | P171: n/a | Q171: n/a | R171: n/a | S171: n/a | T171: n/a | U171: Calibrated | V171: 14 avr. 2026 10:01 | W171: 21 Avenue d'Auvergne, Chevilly-Larue, Île-de-France, 94550 | X171: n/a | Y171: n/a | Z171: n/a | AA171: 0 | AB171: Orange F | AC171: true | AD171: n/a | AE171: CBL-VG-COBDII-Y0 | AF171: n/a | AG171: Regulated
A172: Boitier téléchargement tachys CARQUEFOU | B172: VG54-EU | C172: GR2A-VPG-46X | D172: Z boitier téléchgt | F172: n/a | G172: Automatic | J172: TG OUEST | K172: =VLOOKUP(J172, correspondance!A:B, 2, FALSE) -> TG Ouest | L172: n/a | M172: n/a | N172: n/a | O172: n/a | P172: n/a | Q172: n/a | R172: n/a | S172: n/a | T172: n/a | U172: Not Calibrated | V172: 14 avr. 2026 10:01 | W172: Avenue Syrma, Carquefou, Pays de la Loire, 44470 | X172: n/a | Y172: n/a | Z172: n/a | AA172: 0 | AB172: F SFR | AC172: true | AD172: n/a | AE172: CBL-VG-CPWR | AF172: n/a | AG172: Regulated
A173: GG9S-4BS-FN4 | B173: VG54-EU | C173: GG9S-4BS-FN4 | D173: n/a | F173: n/a | K173: =VLOOKUP(J173, correspondance!A:B, 2, FALSE) -> #N/A | L173: n/a | M173: n/a | N173: n/a | O173: n/a | P173: n/a | Q173: n/a | R173: n/a | S173: n/a | T173: n/a | U173: Not Calibrated | V173: n/a | W173: Location unknown | X173: n/a | Y173: n/a | Z173: n/a | AA173: 0 | AB173: n/a | AC173: n/a | AD173: n/a | AF173: n/a | AG173: Regulated
A174: GUSX-HV8-ZMT | B174: VG54-EU | C174: GUSX-HV8-ZMT | D174: n/a | F174: n/a | K174: =VLOOKUP(J174, correspondance!A:B, 2, FALSE) -> #N/A | L174: n/a | M174: n/a | N174: n/a | O174: n/a | P174: n/a | Q174: n/a | R174: n/a | S174: n/a | T174: n/a | U174: Not Calibrated | V174: n/a | W174: Location unknown | X174: n/a | Y174: n/a | Z174: n/a | AA174: 0 | AB174: n/a | AC174: n/a | AD174: n/a | AF174: n/a | AG174: Regulated
A175: G2WW-KVA-NYS | B175: VG54-EU | C175: G2WW-KVA-NYS | D175: n/a | F175: n/a | K175: =VLOOKUP(J175, correspondance!A:B, 2, FALSE) -> #N/A | L175: n/a | M175: n/a | N175: n/a | O175: n/a | P175: n/a | Q175: n/a | R175: n/a | S175: n/a | T175: n/a | U175: Not Calibrated | V175: n/a | W175: Location unknown | X175: n/a | Y175: n/a | Z175: n/a | AA175: 0 | AB175: n/a | AC175: n/a | AD175: n/a | AF175: n/a | AG175: Regulated
A176: G2KH-3SN-YVA | B176: VG54-EU | C176: G2KH-3SN-YVA | D176: n/a | F176: n/a | K176: =VLOOKUP(J176, correspondance!A:B, 2, FALSE) -> #N/A | L176: n/a | M176: n/a | N176: n/a | O176: n/a | P176: n/a | Q176: n/a | R176: n/a | S176: n/a | T176: n/a | U176: Not Calibrated | V176: n/a | W176: Location unknown | X176: n/a | Y176: n/a | Z176: n/a | AA176: 0 | AB176: n/a | AC176: n/a | AD176: n/a | AF176: n/a | AG176: Regulated
A177: G4XR-8ZH-KV9 | B177: VG54-EU | C177: G4XR-8ZH-KV9 | D177: n/a | F177: n/a | K177: =VLOOKUP(J177, correspondance!A:B, 2, FALSE) -> #N/A | L177: n/a | M177: n/a | N177: n/a | O177: n/a | P177: n/a | Q177: n/a | R177: n/a | S177: n/a | T177: n/a | U177: Not Calibrated | V177: n/a | W177: Location unknown | X177: n/a | Y177: n/a | Z177: n/a | AA177: 0 | AB177: n/a | AC177: n/a | AD177: n/a | AF177: n/a | AG177: Regulated
A178: GW-033-NK | B178: VG54-EU | C178: GJGT-N5T-6NJ | D178: GW-033-NK | E178: VF620J863RB012905 | F178: n/a | G178: Truck | H178: 16000 | I178: KG | J178: TG BOURGOGNE | K178: =VLOOKUP(J178, correspondance!A:B, 2, FALSE) -> TG BOURGOGNE | L178: 119189.8 | M178: 2798 | N178: n/a | O178: n/a | P178: n/a | Q178: n/a | R178: n/a | S178: n/a | T178: n/a | U178: Calibrated | V178: 14 avr. 2026 10:01 | W178: Fauverney, Bourgogne-Franche-Comté, 21110 | X178: n/a | Y178: n/a | Z178: n/a | AA178: 0 | AB178: F SFR | AC178: true | AD178: n/a | AE178: CBL-VG-CHGV | AF178: n/a | AG178: Regulated
A179: EF-717-TL | B179: VG54-EU | C179: GK56-RFY-XXA | D179: EF-717-TL | E179: YV2X9J0A3GB779868 | F179: n/a | G179: Truck | H179: 19000 | I179: KG | J179: TG BOURGOGNE | K179: =VLOOKUP(J179, correspondance!A:B, 2, FALSE) -> TG BOURGOGNE | L179: 464207.4 | M179: 9237 | N179: n/a | O179: n/a | P179: n/a | Q179: n/a | R179: n/a | S179: n/a | T179: n/a | U179: Calibrated | V179: 14 avr. 2026 10:01 | W179: Route des Microtechniques, Avoudrey, Bourgogne-Franche-Comté, 25690 | X179: n/a | Y179: n/a | Z179: n/a | AA179: 0 | AB179: F SFR | AC179: true | AD179: n/a | AE179: CBL-VG-CHGV | AF179: n/a | AG179: Regulated
A180: EF-900-EB | B180: VG54-EU | C180: GTJS-C6N-H78 | D180: EF-900-EB | E180: YV2X9J0A5GB780021 | F180: n/a | G180: Truck | H180: 19000 | I180: KG | J180: TG BOURGOGNE | K180: =VLOOKUP(J180, correspondance!A:B, 2, FALSE) -> TG BOURGOGNE | L180: 451712.4 | M180: 9705 | N180: n/a | O180: n/a | P180: n/a | Q180: n/a | R180: n/a | S180: n/a | T180: n/a | U180: Calibrated | V180: 14 avr. 2026 10:01 | W180: D 70, Renève, Bourgogne-Franche-Comté, 21310 | X180: n/a | Y180: n/a | Z180: n/a | AA180: 0 | AB180: F SFR | AC180: true | AD180: n/a | AE180: CBL-VG-CHGV | AF180: n/a | AG180: Regulated
A181: GTV2-6CB-DBH | B181: VG54-EU | C181: GTV2-6CB-DBH | D181: n/a | F181: n/a | K181: =VLOOKUP(J181, correspondance!A:B, 2, FALSE) -> #N/A | L181: n/a | M181: n/a | N181: n/a | O181: n/a | P181: n/a | Q181: n/a | R181: n/a | S181: n/a | T181: n/a | U181: Not Calibrated | V181: n/a | W181: Location unknown | X181: n/a | Y181: n/a | Z181: n/a | AA181: 0 | AB181: n/a | AC181: n/a | AD181: n/a | AF181: n/a | AG181: Regulated
A182: FS-857-GL | B182: VG54-EU | C182: G9K4-YTX-PRZ | D182: FS-857-GL | E182: VF620J86XLB007966 | F182: n/a | G182: Truck | H182: 16000 | I182: KG | J182: TG BOURGOGNE | K182: =VLOOKUP(J182, correspondance!A:B, 2, FALSE) -> TG BOURGOGNE | L182: 269767.9 | M182: 8032 | N182: n/a | O182: n/a | P182: n/a | Q182: n/a | R182: n/a | S182: n/a | T182: n/a | U182: Calibrated | V182: 14 avr. 2026 10:01 | W182: 20 Rue Jean-Baptiste-Victor Proudhon, Besançon, Bourgogne-Franche-Comté, 25000 | X182: n/a | Y182: n/a | Z182: n/a | AA182: 0 | AB182: F SFR | AC182: true | AD182: n/a | AE182: CBL-VG-CHGV | AF182: n/a | AG182: Regulated
A183: FS-194-SE | B183: VG54-EU | C183: GCPC-MJR-RTK | D183: FS-194-SE | E183: VF620J864LB008028 | F183: n/a | G183: Truck | H183: 16000 | I183: KG | J183: TG BOURGOGNE | K183: =VLOOKUP(J183, correspondance!A:B, 2, FALSE) -> TG BOURGOGNE | L183: 249932.8 | M183: 8300 | N183: n/a | O183: n/a | P183: n/a | Q183: n/a | R183: n/a | S183: n/a | T183: n/a | U183: Calibrated | V183: 14 avr. 2026 10:01 | W183: 116 Rue des Bordes, Louhans, Bourgogne-Franche-Comté, 71500 | X183: n/a | Y183: n/a | Z183: n/a | AA183: 0 | AB183: F SFR | AC183: true | AD183: n/a | AE183: CBL-VG-CHGV | AF183: n/a | AG183: Regulated
A184: EQ-144-FM | B184: VG54-EU | C184: GUAY-HSD-KCV | D184: EQ-144-FM | E184: VF620J865HB003816 | F184: n/a | G184: Truck | H184: 19000 | I184: KG | J184: TG BOURGOGNE | K184: =VLOOKUP(J184, correspondance!A:B, 2, FALSE) -> TG BOURGOGNE | L184: 383351.8 | M184: 11310 | N184: n/a | O184: n/a | P184: n/a | Q184: n/a | R184: n/a | S184: n/a | T184: n/a | U184: Calibrated | V184: 14 avr. 2026 10:01 | W184: Accès Piéton à l'Aire d'Autoroute de Marchaux, Marchaux-Chaudefontaine, Bourgogne-Franche-Comté, 25640 | X184: n/a | Y184: n/a | Z184: n/a | AA184: 0 | AB184: F SFR | AC184: true | AD184: n/a | AE184: CBL-VG-CHGV | AF184: n/a | AG184: Regulated
A185: EQ-467-KN | B185: VG54-EU | C185: GRHX-X7Y-8KC | D185: EQ-467-KN | E185: VF620J869HB003771 | F185: n/a | G185: Truck | H185: 19000 | I185: KG | J185: TG BOURGOGNE | K185: =VLOOKUP(J185, correspondance!A:B, 2, FALSE) -> TG BOURGOGNE | L185: 480814.3 | M185: 8927 | N185: n/a | O185: n/a | P185: n/a | Q185: n/a | R185: n/a | S185: n/a | T185: n/a | U185: Calibrated | V185: 14 avr. 2026 10:01 | W185: Quai de Verdun, Tournus, Bourgogne-Franche-Comté, 71700 | X185: n/a | Y185: n/a | Z185: n/a | AA185: 0 | AB185: F SFR | AC185: true | AD185: n/a | AE185: CBL-VG-CHGV | AF185: n/a | AG185: Regulated
A186: EQ-079-FM | B186: VG54-EU | C186: GARW-AHH-MAM | D186: EQ-079-FM | E186: VF620J864HB003659 | F186: n/a | G186: Truck | H186: 19000 | I186: KG | J186: TG BOURGOGNE | K186: =VLOOKUP(J186, correspondance!A:B, 2, FALSE) -> TG BOURGOGNE | L186: 366895.4 | M186: 10369 | N186: n/a | O186: n/a | P186: n/a | Q186: n/a | R186: n/a | S186: n/a | T186: n/a | U186: Calibrated | V186: 14 avr. 2026 10:01 | W186: 1 Rue Camille Desmoulins, Auxerre, Bourgogne-Franche-Comté, 89000 | X186: n/a | Y186: n/a | Z186: n/a | AA186: 0 | AB186: F SFR | AC186: true | AD186: n/a | AE186: CBL-VG-CHGV | AF186: n/a | AG186: Regulated
A187: EF-839-XN | B187: VG54-EU | C187: GXWR-PUR-AK8 | D187: EF-839-XN | E187: VF640J562GB004983 | F187: n/a | G187: Truck | H187: 16000 | I187: KG | J187: TG BOURGOGNE | K187: =VLOOKUP(J187, correspondance!A:B, 2, FALSE) -> TG BOURGOGNE | L187: 432663.5 | M187: 8891 | N187: n/a | O187: n/a | P187: n/a | Q187: n/a | R187: n/a | S187: n/a | T187: n/a | U187: Calibrated | V187: 14 avr. 2026 10:01 | W187: 29 Avenue de Lahr, Dole, Bourgogne-Franche-Comté, 39100 | X187: n/a | Y187: n/a | Z187: n/a | AA187: 0 | AB187: F SFR | AC187: true | AD187: n/a | AE187: CBL-VG-CHGV | AF187: n/a | AG187: Regulated
A188: EP-959-HK | B188: VG54-EU | C188: G83C-97D-CEZ | D188: EP-959-HK | E188: VF620J867HB003560 | F188: n/a | G188: Truck | H188: 19000 | I188: KG | J188: TG BOURGOGNE | K188: =VLOOKUP(J188, correspondance!A:B, 2, FALSE) -> TG BOURGOGNE | L188: 414477.5 | M188: 11270 | N188: n/a | O188: n/a | P188: n/a | Q188: n/a | R188: n/a | S188: n/a | T188: n/a | U188: Calibrated | V188: 14 avr. 2026 10:01 | W188: Chemin Vert, Chagny, Bourgogne-Franche-Comté, 71150 | X188: n/a | Y188: n/a | Z188: n/a | AA188: 0 | AB188: F SFR | AC188: true | AD188: n/a | AE188: CBL-VG-CHGV | AF188: n/a | AG188: Regulated
A189: FS-190-FH | B189: VG54-EU | C189: GV33-Y3U-3AM | D189: FS-190-FH | E189: VF620J865LB007972 | F189: n/a | G189: Truck | H189: 16000 | I189: KG | J189: TG BOURGOGNE | K189: =VLOOKUP(J189, correspondance!A:B, 2, FALSE) -> TG BOURGOGNE | L189: 224404.3 | M189: 7460 | N189: n/a | O189: n/a | P189: n/a | Q189: n/a | R189: n/a | S189: n/a | T189: n/a | U189: Calibrated | V189: 14 avr. 2026 10:01 | W189: Autoroute du Soleil, Levernois, Bourgogne-Franche-Comté, 21200 | X189: n/a | Y189: n/a | Z189: n/a | AA189: 0 | AB189: F SFR | AC189: true | AD189: n/a | AE189: CBL-VG-CHGV | AF189: n/a | AG189: Regulated
A190: ER-826-GA | B190: VG54-EU | C190: GG32-GZT-ZDJ | D190: ER-826-GA | E190: VF620J86XHB003715 | F190: n/a | G190: Truck | H190: 19000 | I190: KG | J190: TG BOURGOGNE | K190: =VLOOKUP(J190, correspondance!A:B, 2, FALSE) -> TG BOURGOGNE | L190: 358393.2 | M190: 11170 | N190: n/a | O190: n/a | P190: n/a | Q190: n/a | R190: n/a | S190: n/a | T190: n/a | U190: Calibrated | V190: 14 avr. 2026 10:01 | W190: Route de Dijon, Aiserey, Bourgogne-Franche-Comté, 21110 | X190: n/a | Y190: n/a | Z190: n/a | AA190: 0 | AB190: F SFR | AC190: true | AD190: n/a | AE190: CBL-VG-CHGV | AF190: n/a | AG190: Regulated
A191: HF-648-NK | B191: VG54-EU | C191: GW8D-Y7H-94F | D191: HF-648-NK | E191: VF620J862SB015428 | F191: n/a | G191: Truck | H191: 16000 | I191: KG | J191: TG BOURGOGNE | K191: =VLOOKUP(J191, correspondance!A:B, 2, FALSE) -> TG BOURGOGNE | L191: 20934.0 | M191: 478 | N191: n/a | O191: n/a | P191: n/a | Q191: n/a | R191: n/a | S191: n/a | T191: n/a | U191: Calibrated | V191: 14 avr. 2026 10:01 | W191: 15 Rue Pierre Déchanet, Pontarlier, Bourgogne-Franche-Comté, 25300 | X191: n/a | Y191: n/a | Z191: n/a | AA191: 0 | AB191: F SFR | AC191: true | AD191: n/a | AE191: CBL-VG-CHGV | AF191: n/a | AG191: Regulated
A192: ER-883-YV | B192: VG54-EU | C192: GBTN-64Z-T6B | D192: ER-883-YV | E192: VF640J565HB007619 | F192: TRABELSI Akim | G192: Truck | H192: 16000 | I192: KG | J192: TG BOURGOGNE | K192: =VLOOKUP(J192, correspondance!A:B, 2, FALSE) -> TG BOURGOGNE | L192: 448283.0 | M192: 8706 | N192: n/a | O192: n/a | P192: n/a | Q192: n/a | R192: n/a | S192: n/a | T192: n/a | U192: Calibrated | V192: 23 mars 2026 10:38 | W192: Levernois, Bourgogne-Franche-Comté, 21200 | X192: n/a | Y192: n/a | Z192: n/a | AA192: 0 | AB192: F SFR | AC192: true | AD192: n/a | AE192: CBL-VG-CHGV | AF192: n/a | AG192: Regulated
A193: FR-573-VV | B193: VG54-EU | C193: GHJW-45S-3KB | D193: FR-573-VV | E193: VF620J864LB007963 | F193: n/a | G193: Truck | H193: 16000 | I193: KG | J193: TG ALSACE | K193: =VLOOKUP(J193, correspondance!A:B, 2, FALSE) -> TG ALSACE | L193: 405332.8 | M193: 7295 | N193: n/a | O193: n/a | P193: n/a | Q193: n/a | R193: n/a | S193: n/a | T193: n/a | U193: Calibrated | V193: 14 avr. 2026 10:01 | W193: Rue de la Vaugine, Pusey, Bourgogne-Franche-Comté, 70000 | X193: n/a | Y193: n/a | Z193: n/a | AA193: 0 | AB193: F SFR | AC193: true | AD193: n/a | AE193: CBL-VG-CHGV | AF193: n/a | AG193: Regulated
... A204: EZ-285-NC | B204: VG54-EU | C204: GPNN-X5A-VHF | D204: EZ-285-NC | E204: YV2T0U1A3JZ120275 | F204: n/a | G204: Truck | H204: 13300 | I204: KG | J204: TG ALSACE | K204: =VLOOKUP(J204, correspondance!A:B, 2, FALSE) -> TG ALSACE | L204: 237828.1 | M204: 6496 | N204: n/a | O204: n/a | P204: n/a | Q204: n/a | R204: n/a | S204: n/a | T204: n/a | U204: Calibrated | V204: 14 avr. 2026 10:01 | W204: 23 Place du Marché, Obernai, Grand Est, 67210 | X204: n/a | Y204: n/a | Z204: n/a | AA204: 0 | AB204: F SFR | AC204: true | AD204: n/a | AE204: CBL-VG-CHGV | AF204: n/a | AG204: Regulated
A205: EY-638-HK | B205: VG54-EU | C205: G5R9-GZ7-UV9 | D205: EY-638-HK | E205: ZCFC270D50D608715 | F205: n/a | G205: Truck | H205: 7500 | I205: KG | J205: TG ALSACE | K205: =VLOOKUP(J205, correspondance!A:B, 2, FALSE) -> TG ALSACE | L205: n/a | M205: n/a | N205: n/a | O205: n/a | P205: n/a | Q205: n/a | R205: n/a | S205: n/a | T205: n/a | U205: Not Calibrated | V205: n/a | W205: Location unknown | X205: n/a | Y205: n/a | Z205: n/a | AA205: 0 | AB205: n/a | AC205: n/a | AD205: n/a | AF205: n/a | AG205: Regulated
A206: GX-894-LA | B206: VG54-EU | C206: G57M-2NN-PHM | D206: GX-894-LA | E206: VF620J863RB012919 | F206: n/a | G206: Truck | H206: 16000 | I206: KG | J206: TG ALSACE | K206: =VLOOKUP(J206, correspondance!A:B, 2, FALSE) -> TG ALSACE | L206: 98818.9 | M206: 2028 | N206: n/a | O206: n/a | P206: n/a | Q206: n/a | R206: n/a | S206: n/a | T206: n/a | U206: Calibrated | V206: 14 avr. 2026 10:01 | W206: Kintzheim, Grand Est, 67600 | X206: n/a | Y206: n/a | Z206: n/a | AA206: 0 | AB206: F SFR | AC206: true | AD206: n/a | AE206: CBL-VG-CHGV | AF206: n/a | AG206: Regulated
A207: EZ-292-NC | B207: VG54-EU | C207: GTRY-9CK-GE8 | D207: EZ-292-NC | E207: YV2T0U1A0JZ120377 | F207: n/a | G207: Truck | H207: 14000 | I207: KG | J207: TG ALSACE | K207: =VLOOKUP(J207, correspondance!A:B, 2, FALSE) -> TG ALSACE | L207: 406572.6 | M207: 8478 | N207: n/a | O207: n/a | P207: n/a | Q207: n/a | R207: n/a | S207: n/a | T207: n/a | U207: Calibrated | V207: 14 avr. 2026 10:01 | W207: Chemin de Halage, Vogelgrun, Grand Est, 68600 | X207: n/a | Y207: n/a | Z207: n/a | AA207: 0 | AB207: F SFR | AC207: true | AD207: n/a | AE207: CBL-VG-CHGV | AF207: n/a | AG207: Regulated
A208: FA-078-ZF | B208: VG54-EU | C208: G2KR-HFN-VGH | D208: FA-078-ZF | E208: YV2T0W1A8JZ120462 | F208: n/a | G208: Truck | H208: 16000 | I208: KG | J208: TG ALSACE | K208: =VLOOKUP(J208, correspondance!A:B, 2, FALSE) -> TG ALSACE | L208: 454585.6 | M208: 8936 | N208: n/a | O208: n/a | P208: n/a | Q208: n/a | R208: n/a | S208: n/a | T208: n/a | U208: Calibrated | V208: 14 avr. 2026 10:01 | W208: Reichstett, Grand Est, 67116 | X208: n/a | Y208: n/a | Z208: n/a | AA208: 0 | AB208: F SFR | AC208: true | AD208: n/a | AE208: CBL-VG-CHGV | AF208: n/a | AG208: Regulated
A209: FA-096-YF | B209: VG54-EU | C209: GKF6-FP3-98K | D209: FA-096-YF | E209: YV2T0W1A3JZ120465 | F209: n/a | G209: Truck | H209: 16000 | I209: KG | J209: TG ALSACE | K209: =VLOOKUP(J209, correspondance!A:B, 2, FALSE) -> TG ALSACE | L209: 394640.0 | M209: 9088 | N209: n/a | O209: n/a | P209: n/a | Q209: n/a | R209: n/a | S209: n/a | T209: n/a | U209: Calibrated | V209: 14 avr. 2026 10:01 | W209: Autoroute des Cigognes, Réguisheim, Grand Est, 68890 | X209: n/a | Y209: n/a | Z209: n/a | AA209: 0 | AB209: F SFR | AC209: true | AD209: n/a | AE209: CBL-VG-CHGV | AF209: n/a | AG209: Regulated
A210: FA-187-HQ | B210: VG54-EU | C210: GWWR-HAE-MPA | D210: FA-187-HQ | E210: YV2T0U1A2JZ120378 | F210: n/a | G210: Truck | H210: 14000 | I210: KG | J210: TG ALSACE | K210: =VLOOKUP(J210, correspondance!A:B, 2, FALSE) -> TG ALSACE | L210: 251360.5 | M210: 6922 | N210: n/a | O210: n/a | P210: n/a | Q210: n/a | R210: n/a | S210: n/a | T210: n/a | U210: Calibrated | V210: 14 avr. 2026 10:01 | W210: 4 Place de la Réunion, Mulhouse, Grand Est, 68100 | X210: n/a | Y210: n/a | Z210: n/a | AA210: 0 | AB210: F SFR | AC210: true | AD210: n/a | AE210: CBL-VG-CHGV | AF210: n/a | AG210: Regulated
A211: FA-960-MT | B211: VG54-EU | C211: GZ4S-EA7-DXZ | D211: FA-960-MT | E211: ZCFC470A405235242 | F211: n/a | G211: Truck | H211: 1 | I211: KG | J211: TG ALSACE | K211: =VLOOKUP(J211, correspondance!A:B, 2, FALSE) -> TG ALSACE | L211: n/a | M211: n/a | N211: n/a | O211: n/a | P211: n/a | Q211: n/a | R211: n/a | S211: n/a | T211: n/a | U211: Not Calibrated | V211: n/a | W211: Location unknown | X211: n/a | Y211: n/a | Z211: n/a | AA211: 0 | AB211: n/a | AC211: n/a | AD211: n/a | AF211: n/a | AG211: Regulated
A212: FB-051-BN | B212: VG54-EU | C212: GEB4-8SC-U3H | D212: FB-051-BN | E212: YV2T0W1A4JZ120457 | F212: n/a | G212: Truck | H212: 16000 | I212: KG | J212: TG ALSACE | K212: =VLOOKUP(J212, correspondance!A:B, 2, FALSE) -> TG ALSACE | L212: 315420.0 | M212: 7212 | N212: n/a | O212: n/a | P212: n/a | Q212: n/a | R212: n/a | S212: n/a | T212: n/a | U212: Calibrated | V212: 14 avr. 2026 10:01 | W212: 17 Rue des Trois Frontières, Illzach, Grand Est, 68110 | X212: n/a | Y212: n/a | Z212: n/a | AA212: 0 | AB212: F SFR | AC212: true | AD212: n/a | AE212: CBL-VG-CHGV | AF212: n/a | AG212: Regulated
A213: FT-998-CC | B213: VG54-EU | C213: GNFY-D8V-8DF | D213: FT-998-CC | E213: VF620J867LB008038 | F213: n/a | G213: Truck | H213: 16000 | I213: KG | J213: TG ALSACE | K213: =VLOOKUP(J213, correspondance!A:B, 2, FALSE) -> TG ALSACE | L213: 354929.9 | M213: 6848 | N213: n/a | O213: n/a | P213: n/a | Q213: n/a | R213: n/a | S213: n/a | T213: n/a | U213: Calibrated | V213: 14 avr. 2026 10:01 | W213: 17 Rue Edmond Lenne, Sochaux, Bourgogne-Franche-Comté, 25600 | X213: n/a | Y213: n/a | Z213: n/a | AA213: 0 | AB213: F SFR | AC213: true | AD213: n/a | AE213: CBL-VG-CHGV | AF213: n/a | AG213: Regulated
A214: FT-084-CD | B214: VG54-EU | C214: GJTB-H34-7C6 | D214: FT-084-CD | E214: VF620J866LB007981 | F214: n/a | G214: Truck | H214: 16000 | I214: KG | J214: TG ALSACE | K214: =VLOOKUP(J214, correspondance!A:B, 2, FALSE) -> TG ALSACE | L214: 325307.8 | M214: 3598 | N214: n/a | O214: n/a | P214: n/a | Q214: n/a | R214: n/a | S214: n/a | T214: n/a | U214: Calibrated | V214: 14 avr. 2026 10:01 | W214: D 417, Stosswihr, Grand Est, 68140 | X214: n/a | Y214: n/a | Z214: n/a | AA214: 0 | AB214: F SFR | AC214: true | AD214: n/a | AE214: CBL-VG-CHGV | AF214: n/a | AG214: Regulated
A215: GP-445-MS | B215: VG54-EU | C215: G9EA-4U8-B2C | D215: GP-445-MS | E215: VF640J563PB020366 | F215: n/a | G215: Truck | H215: 13000 | I215: KG | J215: TG ALSACE | K215: =VLOOKUP(J215, correspondance!A:B, 2, FALSE) -> TG ALSACE | L215: 103401.9 | M215: 2399 | N215: n/a | O215: n/a | P215: n/a | Q215: n/a | R215: n/a | S215: n/a | T215: n/a | U215: Calibrated | V215: 14 avr. 2026 10:01 | W215: Rue Jules Verne, Mulhouse, Grand Est, 68200 | X215: n/a | Y215: n/a | Z215: n/a | AA215: 0 | AB215: F SFR | AC215: true | AD215: n/a | AE215: CBL-VG-CHGV | AF215: n/a | AG215: Regulated
A216: GP-212-MS | B216: VG54-EU | C216: G7GC-UTP-6ZM | D216: GP-212-MS | E216: VF640J561PB020592 | F216: n/a | G216: Truck | H216: 13000 | I216: KG | J216: TG ALSACE | K216: =VLOOKUP(J216, correspondance!A:B, 2, FALSE) -> TG ALSACE | L216: 172609.2 | M216: 3599 | N216: n/a | O216: n/a | P216: n/a | Q216: n/a | R216: n/a | S216: n/a | T216: n/a | U216: Calibrated | V216: 14 avr. 2026 10:01 | W216: D 73, Bouxwiller, Grand Est, 67330 | X216: n/a | Y216: n/a | Z216: n/a | AA216: 0 | AB216: F SFR | AC216: true | AD216: n/a | AE216: CBL-VG-CHGV | AF216: n/a | AG216: Regulated
A217: FR-057-PW | B217: VG54-EU | C217: GCPU-SH7-X66 | D217: FR-057-PW | E217: VF620J86XLB008017 | F217: n/a | G217: Truck | H217: 16000 | I217: KG | J217: TG ALSACE | K217: =VLOOKUP(J217, correspondance!A:B, 2, FALSE) -> TG ALSACE | L217: 246758.6 | M217: 5714 | N217: n/a | O217: n/a | P217: n/a | Q217: n/a | R217: n/a | S217: n/a | T217: n/a | U217: Calibrated | V217: 14 avr. 2026 10:01 | W217: D 1066, Ranspach, Grand Est, 68550 | X217: n/a | Y217: n/a | Z217: n/a | AA217: 0 | AB217: F SFR | AC217: true | AD217: n/a | AE217: CBL-VG-CHGV | AF217: n/a | AG217: Regulated
A218: DK-846-AJ | B218: VG54-EU | C218: GK7R-Y7E-KUC | D218: DK-846-AJ | E218: VF640J866EB000251 | F218: n/a | G218: Truck | H218: 16000 | I218: KG | J218: TG ALSACE | K218: =VLOOKUP(J218, correspondance!A:B, 2, FALSE) -> TG ALSACE | L218: 507841.8 | M218: 11341 | N218: n/a | O218: n/a | P218: n/a | Q218: n/a | R218: n/a | S218: n/a | T218: n/a | U218: Calibrated | V218: 14 avr. 2026 10:01 | W218: Rue du Haut-Kœnigsbourg, Guémar, Grand Est, 68970 | X218: n/a | Y218: n/a | Z218: n/a | AA218: 0 | AB218: F SFR | AC218: true | AD218: n/a | AE218: CBL-VG-CHGV | AF218: n/a | AG218: Regulated
A219: EZ-760-NG | B219: VG54-EU | C219: GMMF-UYT-4RG | D219: EZ-760-NG | E219: YV2T0U1A4JZ120365 | F219: n/a | G219: Truck | H219: 14000 | I219: KG | J219: TG ALSACE | K219: =VLOOKUP(J219, correspondance!A:B, 2, FALSE) -> TG ALSACE | L219: 255378.4 | M219: 6198 | N219: n/a | O219: n/a | P219: n/a | Q219: n/a | R219: n/a | S219: n/a | T219: n/a | U219: Calibrated | V219: 14 avr. 2026 10:01 | W219: 17 Route de Saverne, Stutzheim-Offenheim, Grand Est, 67370 | X219: n/a | Y219: n/a | Z219: n/a | AA219: 0 | AB219: F SFR | AC219: true | AD219: n/a | AE219: CBL-VG-CHGV | AF219: n/a | AG219: Regulated
A220: FB-987-GN | B220: VG54-EU | C220: G7H3-TU4-PBJ | D220: FB-987-GN | E220: YV2T0W1A6JZ120475 | F220: n/a | G220: Truck | H220: 16000 | I220: KG | J220: TG ALSACE | K220: =VLOOKUP(J220, correspondance!A:B, 2, FALSE) -> TG ALSACE | L220: 431286.1 | M220: 9746 | N220: n/a | O220: n/a | P220: n/a | Q220: n/a | R220: n/a | S220: n/a | T220: n/a | U220: Calibrated | V220: 14 avr. 2026 10:01 | W220: 7 Faubourg de Montbéliard, Belfort, Bourgogne-Franche-Comté, 90000 | X220: n/a | Y220: n/a | Z220: n/a | AA220: 0 | AB220: F SFR | AC220: true | AD220: n/a | AE220: CBL-VG-CHGV | AF220: n/a | AG220: Regulated
A221: DJ-375-ZW | B221: VG54-EU | C221: GS6P-8UE-67C | D221: DJ-375-ZW | E221: VF640J56XEB000466 | F221: n/a | G221: Truck | H221: 16000 | I221: KG | J221: TG ALSACE | K221: =VLOOKUP(J221, correspondance!A:B, 2, FALSE) -> TG ALSACE | L221: 519006.5 | M221: 11360 | N221: n/a | O221: n/a | P221: n/a | Q221: n/a | R221: n/a | S221: n/a | T221: n/a | U221: Calibrated | V221: 14 avr. 2026 10:01 | W221: Route d'Illhaeusern, Guémar, Grand Est, 68970 | X221: n/a | Y221: n/a | Z221: n/a | AA221: 0 | AB221: F SFR | AC221: true | AD221: n/a | AE221: CBL-VG-CHGV | AF221: n/a | AG221: Regulated
A222: DJ-351-ZW | B222: VG54-EU | C222: GHKW-7K3-BGE | D222: DJ-351-ZW | E222: VF640J569EB000457 | F222: n/a | G222: Truck | H222: 16000 | I222: KG | J222: TG LORRAINE | K222: =VLOOKUP(J222, correspondance!A:B, 2, FALSE) -> TG LORRAINE | L222: 454912.0 | M222: 13272 | N222: n/a | O222: n/a | P222: n/a | Q222: n/a | R222: n/a | S222: n/a | T222: n/a | U222: Calibrated | V222: 14 avr. 2026 10:01 | W222: A 33, Fléville-devant-Nancy, Grand Est, 54710 | X222: n/a | Y222: n/a | Z222: n/a | AA222: 0 | AB222: F SFR | AC222: true | AD222: n/a | AE222: CBL-VG-CHGV | AF222: n/a | AG222: Regulated
A223: GS-251-GR | B223: VG54-EU | C223: GW3G-9BH-FN8 | D223: GS-251-GR | E223: ZCFA81MF502740142 | F223: n/a | G223: Truck | H223: 16000 | I223: KG | J223: TG MIDI PYRENEES | K223: =VLOOKUP(J223, correspondance!A:B, 2, FALSE) -> TG MIDI PYRENEES | L223: 88431.9 | M223: 2931 | N223: n/a | O223: n/a | P223: n/a | Q223: n/a | R223: n/a | S223: n/a | T223: n/a | U223: Calibrated | V223: 14 avr. 2026 10:01 | W223: 19 Rue de l'Arc-en-Ciel, Toulouse, Occitanie, 31300 | X223: n/a | Y223: n/a | Z223: n/a | AA223: 0 | AB223: F SFR | AC223: true | AD223: n/a | AE223: CBL-VG-CFMS | AF223: n/a | AG223: Regulated
... A251: GL-243-SY | B251: VG54-EU | C251: GY6D-MXP-2TH | D251: GL-243-SY | E251: VF620J967NB000555 | F251: NAULET Regis | G251: Truck | H251: 16000 | I251: KG | J251: TG RHONE | K251: =VLOOKUP(J251, correspondance!A:B, 2, FALSE) -> TG RHONE | L251: 119639.1 | M251: 3772 | N251: n/a | O251: n/a | P251: n/a | Q251: n/a | R251: n/a | S251: n/a | T251: n/a | U251: Calibrated | V251: 14 avr. 2026 10:01 | W251: Rue Marcel Mérieux, Corbas, Auvergne-Rhône-Alpes, 69960 | X251: n/a | Y251: n/a | Z251: n/a | AA251: 0 | AB251: Orange F | AC251: true | AD251: n/a | AE251: CBL-VG-CHGV | AF251: n/a | AG251: Regulated
A252: HG-031-GE | B252: VG54-EU | C252: G4EX-AJF-HUN | D252: HG-031-GE | E252: ZCFCS72A605601480 | F252: n/a | G252: Truck | J252: TG RHONE | K252: =VLOOKUP(J252, correspondance!A:B, 2, FALSE) -> TG RHONE | L252: 2634.1 | M252: 147 | N252: n/a | O252: n/a | P252: n/a | Q252: n/a | R252: n/a | S252: n/a | T252: n/a | U252: Calibrated | V252: 14 avr. 2026 10:01 | W252: 118 Rue Challemel-Lacour, Lyon, Auvergne-Rhône-Alpes, 69007 | X252: n/a | Y252: n/a | Z252: n/a | AA252: 0 | AB252: Orange F | AC252: true | AD252: n/a | AF252: n/a | AG252: Regulated
A253: GL-251-NS | B253: VG54-EU | C253: GNZN-46U-DB2 | D253: GL-251-NS | E253: VF620J969NB000556 | F253: QUATTROCIOCCHI Yannick | G253: Truck | H253: 16776 | I253: KG | J253: TG RHONE | K253: =VLOOKUP(J253, correspondance!A:B, 2, FALSE) -> TG RHONE | L253: 123698.6 | M253: 4757 | N253: n/a | O253: n/a | P253: n/a | Q253: n/a | R253: n/a | S253: n/a | T253: n/a | U253: Calibrated | V253: 14 avr. 2026 10:01 | W253: Rue des Aqueducs, Craponne, Auvergne-Rhône-Alpes, 69290 | X253: n/a | Y253: n/a | Z253: n/a | AA253: 0 | AB253: Orange F | AC253: true | AD253: n/a | AE253: CBL-VG-CHGV | AF253: n/a | AG253: Regulated
A254: EE-579-AM | B254: VG54-EU | C254: GPPD-7D5-6HX | D254: EE-579-AM | E254: VF6WTAG40G2453582 | F254: BRUNAT Didier leon antoine | G254: Truck | H254: 7500 | I254: KG | J254: TG RHONE | K254: =VLOOKUP(J254, correspondance!A:B, 2, FALSE) -> TG RHONE | L254: n/a | M254: n/a | N254: n/a | O254: n/a | P254: n/a | Q254: n/a | R254: n/a | S254: n/a | T254: n/a | U254: Calibrated | V254: 14 avr. 2026 10:01 | W254: A 42, Saint-Maurice-de-Beynost, Auvergne-Rhône-Alpes, 01700 | X254: n/a | Y254: n/a | Z254: n/a | AA254: 0 | AB254: Orange F | AC254: true | AD254: n/a | AE254: CBL-VG-CHGV | AF254: n/a | AG254: Regulated
A255: GM-658-FP | B255: VG54-EU | C255: GPBH-E4P-GTJ | D255: GM-658-FP | E255: VF620J96XNB000551 | F255: FANJAT Guillaume | G255: Truck | H255: 16000 | I255: KG | J255: TG RHONE | K255: =VLOOKUP(J255, correspondance!A:B, 2, FALSE) -> TG RHONE | L255: 152075.0 | M255: 4610 | N255: n/a | O255: n/a | P255: n/a | Q255: n/a | R255: n/a | S255: n/a | T255: n/a | U255: Calibrated | V255: 14 avr. 2026 10:01 | W255: Route de Brailles, Vézeronce-Curtin, Auvergne-Rhône-Alpes, 38510 | X255: n/a | Y255: n/a | Z255: n/a | AA255: 0 | AB255: Orange F | AC255: true | AD255: n/a | AE255: CBL-VG-CHGV | AF255: n/a | AG255: Regulated
A256: GK-279-CS | B256: VG54-EU | C256: G4CE-ZZD-4WM | D256: GK-279-CS | E256: VF620J968NB000547 | F256: HENAULT Pierre | G256: Truck | H256: 16000 | I256: KG | J256: TG RHONE | K256: =VLOOKUP(J256, correspondance!A:B, 2, FALSE) -> TG RHONE | L256: 138928.4 | M256: 5153 | N256: n/a | O256: n/a | P256: n/a | Q256: n/a | R256: n/a | S256: n/a | T256: n/a | U256: Calibrated | V256: 14 avr. 2026 10:01 | W256: Rue de Bonnel, Lyon, Auvergne-Rhône-Alpes, 69003 | X256: n/a | Y256: n/a | Z256: n/a | AA256: 0 | AB256: Orange F | AC256: true | AD256: n/a | AE256: CBL-VG-CHGV | AF256: n/a | AG256: Regulated
A257: GK-188-GL | B257: VG54-EU | C257: GDMW-PYR-3NW | D257: GK-188-GL | E257: VF620J962NB000561 | F257: POCHOPIEN Herve | G257: Truck | H257: 16000 | I257: KG | J257: TG RHONE | K257: =VLOOKUP(J257, correspondance!A:B, 2, FALSE) -> TG RHONE | L257: 104811.6 | M257: 3942 | N257: n/a | O257: n/a | P257: n/a | Q257: n/a | R257: n/a | S257: n/a | T257: n/a | U257: Calibrated | V257: 14 avr. 2026 10:01 | W257: D 522, Bourgoin-Jallieu, Auvergne-Rhône-Alpes, 38300 | X257: n/a | Y257: n/a | Z257: n/a | AA257: 0 | AB257: Orange F | AC257: true | AD257: n/a | AE257: CBL-VG-CHGV | AF257: n/a | AG257: Regulated
A258: GJ-534-DC | B258: VG54-EU | C258: GWDU-U9Z-9E2 | D258: GJ-534-DC | E258: VF620J963NB000536 | F258: DE LARICHAUDY Alexandre | G258: Truck | H258: 19000 | I258: KG | J258: TG RHONE | K258: =VLOOKUP(J258, correspondance!A:B, 2, FALSE) -> TG RHONE | L258: 201624.9 | M258: 4912 | N258: n/a | O258: n/a | P258: n/a | Q258: n/a | R258: n/a | S258: n/a | T258: n/a | U258: Calibrated | V258: 14 avr. 2026 10:01 | W258: A 43, Saint-Didier-de-la-Tour, Auvergne-Rhône-Alpes, 38110 | X258: n/a | Y258: n/a | Z258: n/a | AA258: 0 | AB258: Orange F | AC258: true | AD258: n/a | AE258: CBL-VG-CHGV | AF258: n/a | AG258: Regulated
A259: GJ-501-ZZ | B259: VG54-EU | C259: G6VU-U2M-5WG | D259: GJ-501-ZZ | E259: VF640J568NB018755 | F259: n/a | G259: Truck | H259: 10000 | I259: KG | J259: TG RHONE | K259: =VLOOKUP(J259, correspondance!A:B, 2, FALSE) -> TG RHONE | L259: 109874.8 | M259: 2927 | N259: n/a | O259: n/a | P259: n/a | Q259: n/a | R259: n/a | S259: n/a | T259: n/a | U259: Calibrated | V259: 14 avr. 2026 10:01 | W259: Rue du Ponant, Donzère, Auvergne-Rhône-Alpes, 26290 | X259: n/a | Y259: n/a | Z259: n/a | AA259: 0 | AB259: Orange F | AC259: true | AD259: n/a | AE259: CBL-VG-CHGV | AF259: n/a | AG259: Regulated
A260: GM-916-CE | B260: VG54-EU | C260: GVG5-4XT-JD5 | D260: GM-916-CE | E260: VF620J964NB000559 | F260: n/a | G260: Truck | H260: 16776 | I260: KG | J260: TG RHONE | K260: =VLOOKUP(J260, correspondance!A:B, 2, FALSE) -> TG RHONE | L260: 126271.9 | M260: 4869 | N260: n/a | O260: n/a | P260: n/a | Q260: n/a | R260: n/a | S260: n/a | T260: n/a | U260: Calibrated | V260: 14 avr. 2026 10:01 | W260: Route de Langonand, Sorbiers, Auvergne-Rhône-Alpes, 42400 | X260: n/a | Y260: n/a | Z260: n/a | AA260: 0 | AB260: Orange F | AC260: true | AD260: n/a | AE260: CBL-VG-CHGV | AF260: n/a | AG260: Regulated
A261: FB-989-TF | B261: VG54-EU | C261: GX6T-EVH-9JV | D261: FB-989-TF | E261: XLRAEL2700L476374 | F261: n/a | G261: Truck | H261: 15500 | I261: KG | J261: TG RHONE | K261: =VLOOKUP(J261, correspondance!A:B, 2, FALSE) -> TG RHONE | L261: 316692.9 | M261: 8881 | N261: n/a | O261: n/a | P261: n/a | Q261: n/a | R261: n/a | S261: n/a | T261: n/a | U261: Calibrated | V261: 14 avr. 2026 10:01 | W261: D 30, Vérin, Auvergne-Rhône-Alpes, 42410 | X261: n/a | Y261: n/a | Z261: n/a | AA261: 0 | AB261: Orange F | AC261: true | AD261: n/a | AE261: CBL-VG-CFMS | AF261: n/a | AG261: Regulated
A262: GR-004-WR | B262: VG54-EU | C262: GJ8S-GSP-XU6 | D262: GR-004-WR | E262: ZCFCP35A20D736029 | F262: RAVET Lucas Jean-Louis | G262: Truck | H262: 3500 | I262: KG | J262: TG RHONE | K262: =VLOOKUP(J262, correspondance!A:B, 2, FALSE) -> TG RHONE | L262: 92471.8 | M262: 4822 | N262: n/a | O262: n/a | P262: n/a | Q262: n/a | R262: n/a | S262: n/a | T262: n/a | U262: Calibrated | V262: 14 avr. 2026 10:01 | W262: D 338, Bagnols, Auvergne-Rhône-Alpes, 69620 | X262: n/a | Y262: n/a | Z262: n/a | AA262: 0 | AB262: Orange F | AC262: true | AD262: n/a | AE262: CBL-VG-COBDII-Y0 | AF262: n/a | AG262: Regulated
A263: GV-649-WL | B263: VG54-EU | C263: GSSF-9VP-233 | D263: GV-649-WL | E263: VF620J966RB000777 | F263: DHONT Anthony | G263: Truck | H263: 16000 | I263: KG | J263: TG RHONE | K263: =VLOOKUP(J263, correspondance!A:B, 2, FALSE) -> TG RHONE | L263: 84372.5 | M263: 3074 | N263: n/a | O263: n/a | P263: n/a | Q263: n/a | R263: n/a | S263: n/a | T263: n/a | U263: Calibrated | V263: 14 avr. 2026 10:01 | W263: D 45, Cordelle, Auvergne-Rhône-Alpes, 42123 | X263: n/a | Y263: n/a | Z263: n/a | AA263: 0 | AB263: Orange F | AC263: true | AD263: n/a | AE263: CBL-VG-CHGV | AF263: n/a | AG263: Regulated
A264: DQ-836-GN | B264: VG54-EU | C264: GBBD-2BV-TAT | D264: DQ-836-GN | E264: YV2V0Y1A5FZ101895 | F264: HUET JO | G264: Truck | H264: 19000 | I264: KG | J264: TG RHONE | K264: =VLOOKUP(J264, correspondance!A:B, 2, FALSE) -> TG RHONE | L264: 394551.3 | M264: 9972 | N264: n/a | O264: n/a | P264: n/a | Q264: n/a | R264: n/a | S264: n/a | T264: n/a | U264: Calibrated | V264: 14 avr. 2026 10:01 | W264: Rue Albert Londres, Échirolles, Auvergne-Rhône-Alpes, 38130 | X264: n/a | Y264: n/a | Z264: n/a | AA264: 0 | AB264: Orange F | AC264: true | AD264: n/a | AE264: CBL-VG-CHGV | AF264: n/a | AG264: Regulated
... A271: EQ-116-NS | B271: VG54-EU | C271: GFCV-9BB-8EG | D271: EQ-116-NS | E271: VF620J863HB003765 | F271: n/a | G271: Truck | H271: 19000 | I271: KG | J271: EUR Schiltigheim LIV | K271: =VLOOKUP(J271, correspondance!A:B, 2, FALSE) -> EUR Schiltigheim LIV | L271: 404733.7 | M271: 6478 | N271: n/a | O271: n/a | P271: n/a | Q271: n/a | R271: n/a | S271: n/a | T271: n/a | U271: Calibrated | V271: 14 avr. 2026 10:01 | W271: Route de Hausbergen, Schiltigheim, Grand Est, 67300 | X271: n/a | Y271: n/a | Z271: n/a | AA271: 0 | AB271: F SFR | AC271: true | AD271: n/a | AE271: CBL-VG-CHGV | AF271: n/a | AG271: Regulated
A272: DT-944-DQ | B272: VG54-EU | C272: GNVY-7JG-X8P | D272: DT-944-DQ | E272: VF6VFE4S652921538 | F272: BLONDE Jean-Philippe | G272: Truck | H272: 3500 | I272: KG | J272: EUR Schiltigheim LIV | K272: =VLOOKUP(J272, correspondance!A:B, 2, FALSE) -> EUR Schiltigheim LIV | L272: n/a | M272: n/a | N272: n/a | O272: n/a | P272: n/a | Q272: n/a | R272: n/a | S272: n/a | T272: n/a | U272: Not Calibrated | V272: n/a | W272: Location unknown | X272: n/a | Y272: n/a | Z272: n/a | AA272: 0 | AB272: n/a | AC272: n/a | AD272: n/a | AF272: n/a | AG272: Regulated
A273: G4XU-598-325 | B273: VG54-EU | C273: G4XU-598-325 | D273: n/a | F273: n/a | K273: =VLOOKUP(J273, correspondance!A:B, 2, FALSE) -> #N/A | L273: n/a | M273: n/a | N273: n/a | O273: n/a | P273: n/a | Q273: n/a | R273: n/a | S273: n/a | T273: n/a | U273: Not Calibrated | V273: n/a | W273: Location unknown | X273: n/a | Y273: n/a | Z273: n/a | AA273: 0 | AB273: n/a | AC273: n/a | AD273: n/a | AF273: n/a | AG273: Regulated
A274: GK-662-MR | B274: VG54-EU | C274: GZ4N-DYR-FWW | D274: GK-662-MR | E274: VF620J86XNB010577 | F274: SZYMANSKI Jean-Philippe | G274: Truck | H274: 19000 | I274: KG | J274: EUR Schiltigheim LIV | K274: =VLOOKUP(J274, correspondance!A:B, 2, FALSE) -> EUR Schiltigheim LIV | L274: 202006.9 | M274: 3976 | N274: n/a | O274: n/a | P274: n/a | Q274: n/a | R274: n/a | S274: n/a | T274: n/a | U274: Calibrated | V274: 14 avr. 2026 10:01 | W274: 43 Rue du Général Hirschauer, Saint-Avold, Grand Est, 57500 | X274: n/a | Y274: n/a | Z274: n/a | AA274: 0 | AB274: F SFR | AC274: true | AD274: n/a | AE274: CBL-VG-CHGV | AF274: n/a | AG274: Regulated
A275: GT-686-JG | B275: VG54-EU | C275: G4BY-TC8-RHR | D275: GT-686-JG | E275: WMA06KZZ2RM941535 | F275: n/a | G275: Truck | H275: 19000 | I275: KG | J275: EUR Schiltigheim LIV | K275: =VLOOKUP(J275, correspondance!A:B, 2, FALSE) -> EUR Schiltigheim LIV | L275: 357997.6 | M275: 5593 | N275: n/a | O275: n/a | P275: n/a | Q275: n/a | R275: n/a | S275: n/a | T275: n/a | U275: Calibrated | V275: 14 avr. 2026 10:01 | W275: N 4, Dombasle-sur-Meurthe, Grand Est, 54110 | X275: n/a | Y275: n/a | Z275: n/a | AA275: 0 | AB275: F SFR | AC275: true | AD275: n/a | AE275: CBL-VG-CHGV | AF275: n/a | AG275: Regulated
A276: EJ-188-VA | B276: VG54-EU | C276: G7RU-E5M-Y5E | D276: EJ-188-VA | E276: VF6WTAG40G2455026 | F276: n/a | G276: Truck | H276: 7500 | I276: KG | J276: EUR Schiltigheim LIV | K276: =VLOOKUP(J276, correspondance!A:B, 2, FALSE) -> EUR Schiltigheim LIV | L276: n/a | M276: n/a | N276: n/a | O276: n/a | P276: n/a | Q276: n/a | R276: n/a | S276: n/a | T276: n/a | U276: Calibrated | V276: 9 mars 2026 08:50 | W276: 101 Route de Hausbergen, Schiltigheim, Grand Est, 67012 | X276: n/a | Y276: n/a | Z276: n/a | AA276: 0 | AB276: F SFR | AC276: true | AD276: n/a | AE276: CBL-VG-CHGV | AF276: n/a | AG276: Regulated
A277: EB-220-CY | B277: VG54-EU | C277: GYG9-ZKP-H42 | D277: EB-220-CY | E277: VF6VFE4S654058175 | F277: WOLFF Pascal | G277: Truck | H277: 3500 | I277: KG | J277: EUR Schiltigheim LIV | K277: =VLOOKUP(J277, correspondance!A:B, 2, FALSE) -> EUR Schiltigheim LIV | L277: 186242.0 | M277: n/a | N277: n/a | O277: n/a | P277: n/a | Q277: n/a | R277: n/a | S277: n/a | T277: n/a | U277: Calibrated | V277: 14 avr. 2026 10:01 | W277: Rue de l'Artisanat, Fegersheim, Grand Est, 67640 | X277: n/a | Y277: n/a | Z277: n/a | AA277: 0 | AB277: F SFR | AC277: true | AD277: n/a | AE277: CBL-VG-COBDII-Y0 | AF277: n/a | AG277: Regulated
A278: ES-521-JG | B278: VG54-EU | C278: GAJH-SM8-8JW | D278: ES-521-JG | E278: VF640J560HB007091 | F278: KEMEUGNE LIENOU Emmanuel Victor | G278: Truck | H278: 13300 | I278: KG | J278: EUR Schiltigheim LIV | K278: =VLOOKUP(J278, correspondance!A:B, 2, FALSE) -> EUR Schiltigheim LIV | L278: 196917.4 | M278: 5297 | N278: n/a | O278: n/a | P278: n/a | Q278: n/a | R278: n/a | S278: n/a | T278: n/a | U278: Calibrated | V278: 14 avr. 2026 10:01 | W278: Rue des Francs-Bourgeois, Strasbourg, Grand Est, 67003 | X278: n/a | Y278: n/a | Z278: n/a | AA278: 0 | AB278: F SFR | AC278: true | AD278: n/a | AE278: CBL-VG-CHGV | AF278: n/a | AG278: Regulated
A279: GM-532-SK | B279: VG54-EU | C279: G7S7-W2Z-72B | D279: GM-532-SK | E279: VF620J968NB000564 | F279: DROUET Julien | G279: Truck | H279: 16776 | I279: KG | J279: EUR Schiltigheim LIV | K279: =VLOOKUP(J279, correspondance!A:B, 2, FALSE) -> EUR Schiltigheim LIV | L279: 47607.7 | M279: 2210 | N279: n/a | O279: n/a | P279: n/a | Q279: n/a | R279: n/a | S279: n/a | T279: n/a | U279: Calibrated | V279: 14 avr. 2026 10:01 | W279: Accès livraisons, Strasbourg, Grand Est, 67027 | X279: n/a | Y279: n/a | Z279: n/a | AA279: 0 | AB279: F SFR | AC279: true | AD279: n/a | AE279: CBL-VG-CHGV | AF279: n/a | AG279: Regulated
A280: DV-285-AF | B280: VG54-EU | C280: G53M-74A-TDH | D280: DV-285-AF | E280: YV2T0X1A9FZ103294 | F280: n/a | G280: Truck | H280: 16000 | I280: KG | J280: EUR Schiltigheim LIV | K280: =VLOOKUP(J280, correspondance!A:B, 2, FALSE) -> EUR Schiltigheim LIV | L280: 408063.3 | M280: 8760 | N280: n/a | O280: n/a | P280: n/a | Q280: n/a | R280: n/a | S280: n/a | T280: n/a | U280: Calibrated | V280: 14 avr. 2026 10:01 | W280: Autoroute de l’Est, Eckartswiller, Grand Est, 67700 | X280: n/a | Y280: n/a | Z280: n/a | AA280: 0 | AB280: F SFR | AC280: true | AD280: n/a | AE280: CBL-VG-CHGV | AF280: n/a | AG280: Regulated
...

Sheet correspondance
A1: tag | B1: site
A2: TG CENTRE EST | B2: TG CENTRE EST
A3: TG La Roche sur Yon (PF) | B3: TG La Roche sur Yon (PF)
A4: Site Bonneville | B4: Site Bonneville
A5: TG IDF VALENTON | B5: TG IDF VALENTON
A6: TG Rennes (PF) | B6: TG Rennes (PF)
A7: TG Ouest | B7: TG Ouest
A8: TG St Brieuc (PF) | B8: TG St Brieuc (PF)
A9: B100, TG Ouest | B9: TG Ouest
A10: TG Caen (PF) | B10: TG Caen (PF)
A11: TG Laval (PF) | B11: TG Laval (PF)
A12: TG Quimper (PF) | B12: TG Quimper (PF)
... A53: TG IDF - Valenton, TG IDF VALENTON | B53: TG IDF VALENTON

Sheet Commandes
A1: Commandes de boitiers 2024-2026
A3: Date | B3: Numéro de commande | C3: Type de produit | D3: Boitier ID | E3: Quantité | F3: Immatriculation | G3: Transgourmet
A4: 45320 | B4: S-1477736 | C4: HW-VG54-EU | D4: G2VD-P2R-XFY | E4: 1 | F4: =IFERROR(IF(LEN(_xlfn.XLOOKUP(D4, 'Parc Samsara'!B:B, 'Parc Samsara'!A:A)) >9, "Non équipé", _xlfn.XLOOKUP(D4, 'Parc Samsara'!B:B, 'Parc Samsara'!A:A)), "Non équipé") -> GF-361-NP | G4: oui
A5: 45320 | B5: S-1477736 | C5: HW-VG54-EU | D5: G96Z-EEG-4MH | E5: 1 | F5: =IFERROR(IF(LEN(_xlfn.XLOOKUP(D5, 'Parc Samsara'!B:B, 'Parc Samsara'!A:A)) >9, "Non équipé", _xlfn.XLOOKUP(D5, 'Parc Samsara'!B:B, 'Parc Samsara'!A:A)), "Non équipé") -> Non équipé | G5: oui
A6: 45320 | B6: S-1477736 | C6: HW-VG54-EU | D6: GEEC-3FB-ZNB | E6: 1 | F6: =IFERROR(IF(LEN(_xlfn.XLOOKUP(D6, 'Parc Samsara'!B:B, 'Parc Samsara'!A:A)) >9, "Non équipé", _xlfn.XLOOKUP(D6, 'Parc Samsara'!B:B, 'Parc Samsara'!A:A)), "Non équipé") -> Non équipé | G6: oui
A7: 45320 | B7: S-1477736 | C7: HW-VG54-EU | D7: GG42-MAR-WA6 | E7: 1 | F7: =IFERROR(IF(LEN(_xlfn.XLOOKUP(D7, 'Parc Samsara'!B:B, 'Parc Samsara'!A:A)) >9, "Non équipé", _xlfn.XLOOKUP(D7, 'Parc Samsara'!B:B, 'Parc Samsara'!A:A)), "Non équipé") -> GL-123-JV | G7: oui
A8: 45320 | B8: S-1477736 | C8: HW-VG54-EU | D8: G4NR-YWZ-KJG | E8: 1 | F8: =IFERROR(IF(LEN(_xlfn.XLOOKUP(D8, 'Parc Samsara'!B:B, 'Parc Samsara'!A:A)) >9, "Non équipé", _xlfn.XLOOKUP(D8, 'Parc Samsara'!B:B, 'Parc Samsara'!A:A)), "Non équipé") -> EZ-274-HC | G8: oui
A9: 45320 | B9: S-1477736 | C9: HW-VG54-EU | D9: GN9P-NBY-M3M | E9: 1 | F9: =IFERROR(IF(LEN(_xlfn.XLOOKUP(D9, 'Parc Samsara'!B:B, 'Parc Samsara'!A:A)) >9, "Non équipé", _xlfn.XLOOKUP(D9, 'Parc Samsara'!B:B, 'Parc Samsara'!A:A)), "Non équipé") -> FT-699-DD | G9: oui
A10: 45320 | B10: S-1477736 | C10: HW-VG54-EU | D10: G6RF-DT5-DMX | E10: 1 | F10: =IFERROR(IF(LEN(_xlfn.XLOOKUP(D10, 'Parc Samsara'!B:B, 'Parc Samsara'!A:A)) >9, "Non équipé", _xlfn.XLOOKUP(D10, 'Parc Samsara'!B:B, 'Parc Samsara'!A:A)), "Non équipé") -> GX-465-SM | G10: oui
A11: 45320 | B11: S-1477736 | C11: HW-VG54-EU | D11: GXGX-5CR-4SX | E11: 1 | F11: =IFERROR(IF(LEN(_xlfn.XLOOKUP(D11, 'Parc Samsara'!B:B, 'Parc Samsara'!A:A)) >9, "Non équipé", _xlfn.XLOOKUP(D11, 'Parc Samsara'!B:B, 'Parc Samsara'!A:A)), "Non équipé") -> EA-702-LC | G11: oui | J11: NB boitiers commandé : | K11: =SUM(E:E) -> 880
A12: 45320 | B12: S-1477736 | C12: HW-VG54-EU | D12: GNZX-TPN-H3F | E12: 1 | F12: =IFERROR(IF(LEN(_xlfn.XLOOKUP(D12, 'Parc Samsara'!B:B, 'Parc Samsara'!A:A)) >9, "Non équipé", _xlfn.XLOOKUP(D12, 'Parc Samsara'!B:B, 'Parc Samsara'!A:A)), "Non équipé") -> FA-734-DL | G12: oui
A13: 45320 | B13: S-1477736 | C13: HW-VG54-EU | D13: GW4B-G4D-EX7 | E13: 1 | F13: =IFERROR(IF(LEN(_xlfn.XLOOKUP(D13, 'Parc Samsara'!B:B, 'Parc Samsara'!A:A)) >9, "Non équipé", _xlfn.XLOOKUP(D13, 'Parc Samsara'!B:B, 'Parc Samsara'!A:A)), "Non équipé") -> HJ-008-RZ | G13: oui
A14: 45320 | B14: S-1477736 | C14: HW-VG54-EU | D14: GWXD-959-9N9 | E14: 1 | F14: =IFERROR(IF(LEN(_xlfn.XLOOKUP(D14, 'Parc Samsara'!B:B, 'Parc Samsara'!A:A)) >9, "Non équipé", _xlfn.XLOOKUP(D14, 'Parc Samsara'!B:B, 'Parc Samsara'!A:A)), "Non équipé") -> FZ-659-XT | G14: oui | I14: Nombre de boitiers commandé non utilisé | L14: Nombre de boitiers par site
A15: 45320 | B15: S-1477736 | C15: HW-VG54-EU | D15: GKWD-W8V-RDZ | E15: 1 | F15: =IFERROR(IF(LEN(_xlfn.XLOOKUP(D15, 'Parc Samsara'!B:B, 'Parc Samsara'!A:A)) >9, "Non équipé", _xlfn.XLOOKUP(D15, 'Parc Samsara'!B:B, 'Parc Samsara'!A:A)), "Non équipé") -> GK-960-SQ | G15: oui
A16: 45320 | B16: S-1477736 | C16: HW-VG54-EU | D16: GA9K-7CZ-VR8 | E16: 1 | F16: =IFERROR(IF(LEN(_xlfn.XLOOKUP(D16, 'Parc Samsara'!B:B, 'Parc Samsara'!A:A)) >9, "Non équipé", _xlfn.XLOOKUP(D16, 'Parc Samsara'!B:B, 'Parc Samsara'!A:A)), "Non équipé") -> GJ-484-DE | G16: oui
A17: 45320 | B17: S-1477736 | C17: HW-VG54-EU | D17: GKRC-UKC-63Y | E17: 1 | F17: =IFERROR(IF(LEN(_xlfn.XLOOKUP(D17, 'Parc Samsara'!B:B, 'Parc Samsara'!A:A)) >9, "Non équipé", _xlfn.XLOOKUP(D17, 'Parc Samsara'!B:B, 'Parc Samsara'!A:A)), "Non équipé") -> ED-972-WP | G17: oui | I17: Immatriculation | J17: (Plusieurs éléments) | L17: Site | M17: Nombre de Boitier
A18: 45320 | B18: S-1477736 | C18: HW-VG54-EU | D18: G6FA-F93-M9Y | E18: 1 | F18: =IFERROR(IF(LEN(_xlfn.XLOOKUP(D18, 'Parc Samsara'!B:B, 'Parc Samsara'!A:A)) >9, "Non équipé", _xlfn.XLOOKUP(D18, 'Parc Samsara'!B:B, 'Parc Samsara'!A:A)), "Non équipé") -> FA-868-EE | G18: oui | L18: EUR Schiltigheim LIV | M18: 14
A19: 45320 | B19: S-1477736 | C19: HW-VG54-EU | D19: GAPW-56Z-T79 | E19: 1 | F19: =IFERROR(IF(LEN(_xlfn.XLOOKUP(D19, 'Parc Samsara'!B:B, 'Parc Samsara'!A:A)) >9, "Non équipé", _xlfn.XLOOKUP(D19, 'Parc Samsara'!B:B, 'Parc Samsara'!A:A)), "Non équipé") -> FA-720-DK | G19: oui | I19: Type de boitier | J19: Nombre de boitiers commandé non utilisé (samsara) | L19: PF Mouguerre | M19: 12
A20: 45320 | B20: S-1477736 | C20: HW-VG54-EU | D20: GGFJ-5G5-EB6 | E20: 1 | F20: =IFERROR(IF(LEN(_xlfn.XLOOKUP(D20, 'Parc Samsara'!B:B, 'Parc Samsara'!A:A)) >9, "Non équipé", _xlfn.XLOOKUP(D20, 'Parc Samsara'!B:B, 'Parc Samsara'!A:A)), "Non équipé") -> GZ-474-VB | G20: oui | I20: HW-VG54-EU | J20: 71 | L20: Site Bonneville | M20: 21
A21: 45320 | B21: S-1477736 | C21: HW-VG54-EU | D21: GKGS-96F-U57 | E21: 1 | F21: =IFERROR(IF(LEN(_xlfn.XLOOKUP(D21, 'Parc Samsara'!B:B, 'Parc Samsara'!A:A)) >9, "Non équipé", _xlfn.XLOOKUP(D21, 'Parc Samsara'!B:B, 'Parc Samsara'!A:A)), "Non équipé") -> ES-687-GK | G21: oui | I21: HW-VG55-EU | J21: 27 | L21: Site Laplace | M21: 8
A22: 45320 | B22: S-1477736 | C22: HW-VG54-EU | D22: GCK8-V2P-TDR | E22: 1 | F22: =IFERROR(IF(LEN(_xlfn.XLOOKUP(D22, 'Parc Samsara'!B:B, 'Parc Samsara'!A:A)) >9, "Non équipé", _xlfn.XLOOKUP(D22, 'Parc Samsara'!B:B, 'Parc Samsara'!A:A)), "Non équipé") -> GL-792-AC | G22: oui | I22: Total général | J22: 98 | L22: Site St Loubes | M22: 43
A23: 45320 | B23: S-1477736 | C23: HW-VG54-EU | D23: GGXT-5U5-HGJ | E23: 1 | F23: =IFERROR(IF(LEN(_xlfn.XLOOKUP(D23, 'Parc Samsara'!B:B, 'Parc Samsara'!A:A)) >9, "Non équipé", _xlfn.XLOOKUP(D23, 'Parc Samsara'!B:B, 'Parc Samsara'!A:A)), "Non équipé") -> GL-169-ZR | G23: oui | L23: TG ALPES | M23: 4
A24: 45320 | B24: S-1477736 | C24: HW-VG54-EU | D24: GT9V-PF5-224 | E24: 1 | F24: =IFERROR(IF(LEN(_xlfn.XLOOKUP(D24, 'Parc Samsara'!B:B, 'Parc Samsara'!A:A)) >9, "Non équipé", _xlfn.XLOOKUP(D24, 'Parc Samsara'!B:B, 'Parc Samsara'!A:A)), "Non équipé") -> HJ-710-ZK | G24: oui | L24: TG ALSACE | M24: 37
A25: 45320 | B25: S-1477736 | C25: HW-VG54-EU | D25: GRRX-9GK-W4S | E25: 1 | F25: =IFERROR(IF(LEN(_xlfn.XLOOKUP(D25, 'Parc Samsara'!B:B, 'Parc Samsara'!A:A)) >9, "Non équipé", _xlfn.XLOOKUP(D25, 'Parc Samsara'!B:B, 'Parc Samsara'!A:A)), "Non équipé") -> FT-906-HJ | G25: oui | L25: TG Arques | M25: 27
A26: 45320 | B26: S-1477736 | C26: HW-VG54-EU | D26: GSSH-F8T-KN5 | E26: 1 | F26: =IFERROR(IF(LEN(_xlfn.XLOOKUP(D26, 'Parc Samsara'!B:B, 'Parc Samsara'!A:A)) >9, "Non équipé", _xlfn.XLOOKUP(D26, 'Parc Samsara'!B:B, 'Parc Samsara'!A:A)), "Non équipé") -> GM-081-HH | G26: oui | L26: TG BOURGOGNE | M26: 25
A27: 45320 | B27: S-1477736 | C27: HW-VG54-EU | D27: G6XA-RSS-PXK | E27: 1 | F27: =IFERROR(IF(LEN(_xlfn.XLOOKUP(D27, 'Parc Samsara'!B:B, 'Parc Samsara'!A:A)) >9, "Non équipé", _xlfn.XLOOKUP(D27, 'Parc Samsara'!B:B, 'Parc Samsara'!A:A)), "Non équipé") -> GX-443-JW | G27: oui | L27: TG Caen (PF) | M27: 11
A28: 45320 | B28: S-1477736 | C28: HW-VG54-EU | D28: G9RZ-6H9-FDG | E28: 1 | F28: =IFERROR(IF(LEN(_xlfn.XLOOKUP(D28, 'Parc Samsara'!B:B, 'Parc Samsara'!A:A)) >9, "Non équipé", _xlfn.XLOOKUP(D28, 'Parc Samsara'!B:B, 'Parc Samsara'!A:A)), "Non équipé") -> GS-442-FA | G28: oui | L28: TG CENTRE EST | M28: 26
A29: 45320 | B29: S-1477736 | C29: HW-VG54-EU | D29: GFRH-J8Y-8WJ | E29: 1 | F29: =IFERROR(IF(LEN(_xlfn.XLOOKUP(D29, 'Parc Samsara'!B:B, 'Parc Samsara'!A:A)) >9, "Non équipé", _xlfn.XLOOKUP(D29, 'Parc Samsara'!B:B, 'Parc Samsara'!A:A)), "Non équipé") -> ES-754-HM | G29: oui | L29: TG CENTRE OUEST | M29: 52
A30: 45320 | B30: S-1477736 | C30: HW-VG54-EU | D30: GE3A-XXG-599 | E30: 1 | F30: =IFERROR(IF(LEN(_xlfn.XLOOKUP(D30, 'Parc Samsara'!B:B, 'Parc Samsara'!A:A)) >9, "Non équipé", _xlfn.XLOOKUP(D30, 'Parc Samsara'!B:B, 'Parc Samsara'!A:A)), "Non équipé") -> Non équipé | G30: oui | L30: TG COULOMMIERS | M30: 8
A31: 45320 | B31: S-1477736 | C31: HW-VG54-EU | D31: G3DW-XH2-YYC | E31: 1 | F31: =IFERROR(IF(LEN(_xlfn.XLOOKUP(D31, 'Parc Samsara'!B:B, 'Parc Samsara'!A:A)) >9, "Non équipé", _xlfn.XLOOKUP(D31, 'Parc Samsara'!B:B, 'Parc Samsara'!A:A)), "Non équipé") -> GX-430-GY | G31: oui | L31: TG Gouzeaucourt (PF) | M31: 8
A32: 45320 | B32: S-1477736 | C32: HW-VG54-EU | D32: GXJ5-RZT-MC2 | E32: 1 | F32: =IFERROR(IF(LEN(_xlfn.XLOOKUP(D32, 'Parc Samsara'!B:B, 'Parc Samsara'!A:A)) >9, "Non équipé", _xlfn.XLOOKUP(D32, 'Parc Samsara'!B:B, 'Parc Samsara'!A:A)), "Non équipé") -> GR-635-ZR | G32: oui | L32: TG IDF VALENTON | M32: 107
A33: 45320 | B33: S-1477736 | C33: HW-VG54-EU | D33: GMGG-A3M-CZ3 | E33: 1 | F33: =IFERROR(IF(LEN(_xlfn.XLOOKUP(D33, 'Parc Samsara'!B:B, 'Parc Samsara'!A:A)) >9, "Non équipé", _xlfn.XLOOKUP(D33, 'Parc Samsara'!B:B, 'Parc Samsara'!A:A)), "Non équipé") -> FA-585-FF | G33: oui | L33: TG IDF WISSOUS | M33: 13
A34: 45320 | B34: S-1477736 | C34: HW-VG54-EU | D34: GS92-G9U-XF2 | E34: 1 | F34: =IFERROR(IF(LEN(_xlfn.XLOOKUP(D34, 'Parc Samsara'!B:B, 'Parc Samsara'!A:A)) >9, "Non équipé", _xlfn.XLOOKUP(D34, 'Parc Samsara'!B:B, 'Parc Samsara'!A:A)), "Non équipé") -> GX-648-RZ | G34: oui | L34: TG La Roche sur Yon (PF) | M34: 5
... A55: 45320 | B55: S-1477736 | C55: HW-VG54-EU | D55: GRZY-PWF-BG9 | E55: 1 | F55: =IFERROR(IF(LEN(_xlfn.XLOOKUP(D55, 'Parc Samsara'!B:B, 'Parc Samsara'!A:A)) >9, "Non équipé", _xlfn.XLOOKUP(D55, 'Parc Samsara'!B:B, 'Parc Samsara'!A:A)), "Non équipé") -> HC-607-XV | G55: oui | L55: Total général | M55: 793
A56: 45320 | B56: S-1477736 | C56: HW-VG54-EU | D56: GPTR-HUR-PDP | E56: 1 | F56: =IFERROR(IF(LEN(_xlfn.XLOOKUP(D56, 'Parc Samsara'!B:B, 'Parc Samsara'!A:A)) >9, "Non équipé", _xlfn.XLOOKUP(D56, 'Parc Samsara'!B:B, 'Parc Samsara'!A:A)), "Non équipé") -> GR-232-ZS | G56: oui
A57: 45320 | B57: S-1477736 | C57: HW-VG54-EU | D57: GRRJ-HS2-UXY | E57: 1 | F57: =IFERROR(IF(LEN(_xlfn.XLOOKUP(D57, 'Parc Samsara'!B:B, 'Parc Samsara'!A:A)) >9, "Non équipé", _xlfn.XLOOKUP(D57, 'Parc Samsara'!B:B, 'Parc Samsara'!A:A)), "Non équipé") -> FA-205-EE | G57: oui
A58: 45320 | B58: S-1477736 | C58: HW-VG54-EU | D58: GHGD-PRE-VVM | E58: 1 | F58: =IFERROR(IF(LEN(_xlfn.XLOOKUP(D58, 'Parc Samsara'!B:B, 'Parc Samsara'!A:A)) >9, "Non équipé", _xlfn.XLOOKUP(D58, 'Parc Samsara'!B:B, 'Parc Samsara'!A:A)), "Non équipé") -> GZ-830-DZ | G58: oui
A59: 45320 | B59: S-1477736 | C59: HW-VG54-EU | D59: GWJF-W8B-XDU | E59: 1 | F59: =IFERROR(IF(LEN(_xlfn.XLOOKUP(D59, 'Parc Samsara'!B:B, 'Parc Samsara'!A:A)) >9, "Non équipé", _xlfn.XLOOKUP(D59, 'Parc Samsara'!B:B, 'Parc Samsara'!A:A)), "Non équipé") -> Non équipé | G59: oui
A60: 45320 | B60: S-1477736 | C60: HW-VG54-EU | D60: GT2U-5DX-3GS | E60: 1 | F60: =IFERROR(IF(LEN(_xlfn.XLOOKUP(D60, 'Parc Samsara'!B:B, 'Parc Samsara'!A:A)) >9, "Non équipé", _xlfn.XLOOKUP(D60, 'Parc Samsara'!B:B, 'Parc Samsara'!A:A)), "Non équipé") -> GL-643-QX | G60: oui
A61: 45320 | B61: S-1477736 | C61: HW-VG54-EU | D61: GXC6-M5Y-Z9V | E61: 1 | F61: =IFERROR(IF(LEN(_xlfn.XLOOKUP(D61, 'Parc Samsara'!B:B, 'Parc Samsara'!A:A)) >9, "Non équipé", _xlfn.XLOOKUP(D61, 'Parc Samsara'!B:B, 'Parc Samsara'!A:A)), "Non équipé") -> HA-887-GC | G61: oui
A62: 45320 | B62: S-1477736 | C62: HW-VG54-EU | D62: GNB4-WBN-T6E | E62: 1 | F62: =IFERROR(IF(LEN(_xlfn.XLOOKUP(D62, 'Parc Samsara'!B:B, 'Parc Samsara'!A:A)) >9, "Non équipé", _xlfn.XLOOKUP(D62, 'Parc Samsara'!B:B, 'Parc Samsara'!A:A)), "Non équipé") -> DY-273-RQ | G62: oui
A63: 45320 | B63: S-1477736 | C63: HW-VG54-EU | D63: GHEW-D2J-B2C | E63: 1 | F63: =IFERROR(IF(LEN(_xlfn.XLOOKUP(D63, 'Parc Samsara'!B:B, 'Parc Samsara'!A:A)) >9, "Non équipé", _xlfn.XLOOKUP(D63, 'Parc Samsara'!B:B, 'Parc Samsara'!A:A)), "Non équipé") -> GZ-447-SF | G63: oui
A64: 45320 | B64: S-1477736 | C64: HW-VG54-EU | D64: GJTX-UFD-773 | E64: 1 | F64: =IFERROR(IF(LEN(_xlfn.XLOOKUP(D64, 'Parc Samsara'!B:B, 'Parc Samsara'!A:A)) >9, "Non équipé", _xlfn.XLOOKUP(D64, 'Parc Samsara'!B:B, 'Parc Samsara'!A:A)), "Non équipé") -> GY-712-JL | G64: oui
A65: 45320 | B65: S-1477736 | C65: HW-VG54-EU | D65: GE4C-7UA-RWB | E65: 1 | F65: =IFERROR(IF(LEN(_xlfn.XLOOKUP(D65, 'Parc Samsara'!B:B, 'Parc Samsara'!A:A)) >9, "Non équipé", _xlfn.XLOOKUP(D65, 'Parc Samsara'!B:B, 'Parc Samsara'!A:A)), "Non équipé") -> GJ-641-DD | G65: oui
A66: 45320 | B66: S-1477736 | C66: HW-VG54-EU | D66: GMNU-ESH-T6G | E66: 1 | F66: =IFERROR(IF(LEN(_xlfn.XLOOKUP(D66, 'Parc Samsara'!B:B, 'Parc Samsara'!A:A)) >9, "Non équipé", _xlfn.XLOOKUP(D66, 'Parc Samsara'!B:B, 'Parc Samsara'!A:A)), "Non équipé") -> FZ-496-XT | G66: oui
A67: 45320 | B67: S-1477736 | C67: HW-VG54-EU | D67: GSPC-SD9-7ER | E67: 1 | F67: =IFERROR(IF(LEN(_xlfn.XLOOKUP(D67, 'Parc Samsara'!B:B, 'Parc Samsara'!A:A)) >9, "Non équipé", _xlfn.XLOOKUP(D67, 'Parc Samsara'!B:B, 'Parc Samsara'!A:A)), "Non équipé") -> GZ-564-RA | G67: oui
... A883: 46064 | B883: S-2778373 | C883: HW-VG55-EU | D883: GYUU-SCM-F2D | E883: 1 | F883: =IFERROR(IF(LEN(_xlfn.XLOOKUP(D883, 'Parc Samsara'!B:B, 'Parc Samsara'!A:A)) >9, "Non équipé", _xlfn.XLOOKUP(D883, 'Parc Samsara'!B:B, 'Parc Samsara'!A:A)), "Non équipé") -> Non équipé | G883: oui
G884: oui
G885: oui
G886: oui
G887: oui
G888: oui
G889: oui
G890: oui
G891: oui
G892: oui
G893: oui
G894: oui
G895: oui
... G1090: oui

Sheet Parc Samsara
A1: Name | B1: Gateway Serial | C1: Location | D1: Last Connected | E1: Last Trip | F1: Status | G1: Current Fuel Level (%) | H1: Current Driver | I1: License Plate | J1: Tags | K1: Installed | L1: Make | M1: Model | N1: Year | O1: Vin | P1: Vehicle Type | Q1: présents | R1: Différents | S1: TRANSGOURMET
A2: EA-257-ZK | C2: Monnaie, Centre-Val de Loire, 37380 | D2: 11 oct. 2024 09:00 | E2: 11 oct. 2024 08:19 | F2: off | G2: 75 | I2: EA-257-ZK | J2: TG CENTRE OUEST | K2: true | L2: RENAULT | M2: D WIDE | N2: 2024 | O2: VF620J868RB013905 | P2: Automatic | Q2: =IFERROR(_xlfn.XLOOKUP(B2,'boitiers actifs'!C:C,'boitiers actifs'!A:A),"Pas installé") -> Pas installé | R2: =IF(Q2 = "Pas installé", "Pas installé", IF( Q2<>A2, "Différent du véhicule assigné", "Identique")) -> Pas installé | S2: =IF(B2 = "", "", VLOOKUP(B2, Commandes!D:G, 4, FALSE))
A3: CM-970-SV | C3: Sancerre, Centre-Val de Loire, 18300 | D3: 19 juin 2024 07:14 | E3: 19 juin 2024 06:33 | F3: off | G3: - | I3: CM-970-SV | J3: TG CENTRE EST | K3: true | L3: RENAULT | M3: MIDLUM | N3: 2012 | O3: VF644AGL000006703 | Q3: =IFERROR(_xlfn.XLOOKUP(B3,'boitiers actifs'!C:C,'boitiers actifs'!A:A),"Pas installé") -> Pas installé | R3: =IF(Q3 = "Pas installé", "Pas installé", IF( Q3<>A3, "Différent du véhicule assigné", "Identique")) -> Pas installé | S3: =IF(B3 = "", "", VLOOKUP(B3, Commandes!D:G, 4, FALSE))
A4: FR-281-MN | B4: GGMW-NMZ-NT6 | C4: La Roche-sur-Yon, Pays de la Loire, 85000 | D4: 14 avr. 2026 10:08 | E4: 13 avr. 2026 13:04 | F4: off | G4: 88 | I4: FR-281-MN | J4: TG La Roche sur Yon (PF) | K4: true | L4: RENAULT | M4: D WIDE | N4: 2020 | O4: VF620J86XLB007983 | P4: Truck | Q4: =IFERROR(_xlfn.XLOOKUP(B4,'boitiers actifs'!C:C,'boitiers actifs'!A:A),"Pas installé") -> FR-281-MN | R4: =IF(Q4 = "Pas installé", "Pas installé", IF( Q4<>A4, "Différent du véhicule assigné", "Identique")) -> Identique | S4: =IF(B4 = "", "", VLOOKUP(B4, Commandes!D:G, 4, FALSE)) -> #N/A
A5: FT-601-CN | B5: G4YX-EK6-Z7R | C5: Le Grand Cornet, Nouvelle-Aquitaine, 79330 | D5: 14 avr. 2026 10:08 | E5: On trip | F5: on | G5: 70 | H5: GUILLET Christian | I5: FT-601-CN | J5: TG La Roche sur Yon (PF) | K5: true | L5: RENAULT | M5: D WIDE | N5: 2020 | O5: VF620J861LB007967 | P5: Truck | Q5: =IFERROR(_xlfn.XLOOKUP(B5,'boitiers actifs'!C:C,'boitiers actifs'!A:A),"Pas installé") -> FT-601-CN | R5: =IF(Q5 = "Pas installé", "Pas installé", IF( Q5<>A5, "Différent du véhicule assigné", "Identique")) -> Identique | S5: =IF(B5 = "", "", VLOOKUP(B5, Commandes!D:G, 4, FALSE)) -> #N/A
A6: Boitier téléchargement tachys CARQUEFOU | B6: GR2A-VPG-46X | C6: Carquefou, Pays de la Loire, 44470 | D6: 14 avr. 2026 10:08 | F6: off | G6: - | I6: Z boitier téléchgt | J6: TG OUEST | K6: true | N6: 0 | P6: Automatic | Q6: =IFERROR(_xlfn.XLOOKUP(B6,'boitiers actifs'!C:C,'boitiers actifs'!A:A),"Pas installé") -> Boitier téléchargement tachys CARQUEFOU | R6: =IF(Q6 = "Pas installé", "Pas installé", IF( Q6<>A6, "Différent du véhicule assigné", "Identique")) -> Identique | S6: =IF(B6 = "", "", VLOOKUP(B6, Commandes!D:G, 4, FALSE)) -> #N/A
A7: GM-743-ST | B7: GR58-DA4-PVN | C7: Paris, Île-de-France, 75004 | D7: 14 avr. 2026 10:08 | E7: 14 avr. 2026 09:01 | F7: on | G7: 74 | H7: TRAORE SALLI | I7: GM-743-ST | J7: TG IDF VALENTON | K7: true | L7: RENAULT | M7: D | N7: 2022 | O7: VF640J565NB019779 | P7: Truck | Q7: =IFERROR(_xlfn.XLOOKUP(B7,'boitiers actifs'!C:C,'boitiers actifs'!A:A),"Pas installé") -> GM-743-ST | R7: =IF(Q7 = "Pas installé", "Pas installé", IF( Q7<>A7, "Différent du véhicule assigné", "Identique")) -> Identique | S7: =IF(B7 = "", "", VLOOKUP(B7, Commandes!D:G, 4, FALSE)) -> #N/A
A8: GM-757-SV | B8: GWKS-B4Z-AV2 | C8: Valenton, Île-de-France, 94460 | D8: 14 avr. 2026 10:08 | E8: 14 avr. 2026 10:02 | F8: idle | G8: 55 | H8: LEBERRE PATRICK | I8: GM-757-SV | J8: TG IDF VALENTON | K8: true | L8: RENAULT | M8: D WIDE | N8: 2022 | O8: VF620J961NB000566 | P8: Truck | Q8: =IFERROR(_xlfn.XLOOKUP(B8,'boitiers actifs'!C:C,'boitiers actifs'!A:A),"Pas installé") -> GM-757-SV | R8: =IF(Q8 = "Pas installé", "Pas installé", IF( Q8<>A8, "Différent du véhicule assigné", "Identique")) -> Identique | S8: =IF(B8 = "", "", VLOOKUP(B8, Commandes!D:G, 4, FALSE)) -> #N/A
A9: FT-966-XF | B9: GECZ-HHA-E3F | C9: Valenton, Île-de-France, 94460 | D9: 14 avr. 2026 10:08 | E9: 14 avr. 2026 09:23 | F9: off | G9: 69 | H9: KHAZRI Hamed | I9: FT-966-XF | J9: TG IDF VALENTON | K9: true | L9: RENAULT | M9: D WIDE | N9: 2020 | O9: VF620J861LB008231 | P9: Truck | Q9: =IFERROR(_xlfn.XLOOKUP(B9,'boitiers actifs'!C:C,'boitiers actifs'!A:A),"Pas installé") -> FT-966-XF | R9: =IF(Q9 = "Pas installé", "Pas installé", IF( Q9<>A9, "Différent du véhicule assigné", "Identique")) -> Identique | S9: =IF(B9 = "", "", VLOOKUP(B9, Commandes!D:G, 4, FALSE)) -> #N/A
A10: EJ-847-PS | B10: GZAK-5WG-488 | C10: Paris, Île-de-France, 75013 | D10: 14 avr. 2026 10:08 | E10: On trip | F10: on | G10: 48 | I10: EJ-847-PS | J10: TG IDF VALENTON | K10: true | L10: IVECO | M10: DAILY | N10: 2017 | O10: ZCFCD35A40D578513 | P10: Truck | Q10: =IFERROR(_xlfn.XLOOKUP(B10,'boitiers actifs'!C:C,'boitiers actifs'!A:A),"Pas installé") -> EJ-847-PS | R10: =IF(Q10 = "Pas installé", "Pas installé", IF( Q10<>A10, "Différent du véhicule assigné", "Identique")) -> Identique | S10: =IF(B10 = "", "", VLOOKUP(B10, Commandes!D:G, 4, FALSE)) -> #N/A
A11: CP-304-AD | C11: Carquefou, Pays de la Loire, 44470 | D11: 6 nov. 2024 16:22 | E11: 31 oct. 2024 14:27 | F11: off | G11: - | I11: CP-304-AD | J11: TG Ouest | K11: true | L11: VOLVO | M11: FE | N11: 2013 | O11: YV2VH40A3DB637947 | Q11: =IFERROR(_xlfn.XLOOKUP(B11,'boitiers actifs'!C:C,'boitiers actifs'!A:A),"Pas installé") -> Pas installé | R11: =IF(Q11 = "Pas installé", "Pas installé", IF( Q11<>A11, "Différent du véhicule assigné", "Identique")) -> Pas installé | S11: =IF(B11 = "", "", VLOOKUP(B11, Commandes!D:G, 4, FALSE))
A12: DV-089-QD | C12: Carquefou, Pays de la Loire, 44470 | D12: 24 févr. 2025 16:31 | E12: 24 févr. 2025 16:12 | F12: off | G12: 100 | I12: DV-089-QD | J12: TG Caen (PF) | K12: true | L12: VOLVO | M12: FE | N12: 2015 | O12: YV2V0Y1A3FZ103192 | Q12: =IFERROR(_xlfn.XLOOKUP(B12,'boitiers actifs'!C:C,'boitiers actifs'!A:A),"Pas installé") -> Pas installé | R12: =IF(Q12 = "Pas installé", "Pas installé", IF( Q12<>A12, "Différent du véhicule assigné", "Identique")) -> Pas installé | S12: =IF(B12 = "", "", VLOOKUP(B12, Commandes!D:G, 4, FALSE))
A13: EA-206-DW | B13: GDSE-UXJ-C7X | C13: Caulnes, Bretagne, 22350 | D13: 14 avr. 2026 10:08 | E13: 14 avr. 2026 10:01 | F13: off | G13: - | H13: KASSOURI Drissa | I13: EA-206-DW | J13: TG Rennes (PF) | K13: true | L13: RENAULT | M13: D | N13: 2016 | O13: VF640J562GB003610 | P13: Truck | Q13: =IFERROR(_xlfn.XLOOKUP(B13,'boitiers actifs'!C:C,'boitiers actifs'!A:A),"Pas installé") -> EA-206-DW | R13: =IF(Q13 = "Pas installé", "Pas installé", IF( Q13<>A13, "Différent du véhicule assigné", "Identique")) -> Identique | S13: =IF(B13 = "", "", VLOOKUP(B13, Commandes!D:G, 4, FALSE)) -> oui
A14: FC-613-XX | B14: GMK3-VUC-3E4 | C14: Angers, Pays de la Loire, 49100 | D14: 14 avr. 2026 10:08 | E14: 14 avr. 2026 09:30 | F14: off | G14: 79 | H14: CISSE Mamadou | I14: FC-613-XX | J14: TG Ouest | K14: true | L14: RENAULT | M14: D WIDE | N14: 2019 | O14: VF620J860KB005786 | P14: Truck | Q14: =IFERROR(_xlfn.XLOOKUP(B14,'boitiers actifs'!C:C,'boitiers actifs'!A:A),"Pas installé") -> FC-613-XX | R14: =IF(Q14 = "Pas installé", "Pas installé", IF( Q14<>A14, "Différent du véhicule assigné", "Identique")) -> Identique | S14: =IF(B14 = "", "", VLOOKUP(B14, Commandes!D:G, 4, FALSE)) -> oui
A15: GH-033-QX | B15: GYFP-PJJ-FJF | C15: Carquefou, Pays de la Loire, 44470 | D15: 14 avr. 2026 10:08 | E15: 14 avr. 2026 09:17 | F15: off | G15: 100 | I15: GH-033-QX | J15: TG Ouest | K15: true | L15: RENAULT | M15: T | N15: 2022 | O15: VF611A367ND038308 | P15: Truck | Q15: =IFERROR(_xlfn.XLOOKUP(B15,'boitiers actifs'!C:C,'boitiers actifs'!A:A),"Pas installé") -> GH-033-QX | R15: =IF(Q15 = "Pas installé", "Pas installé", IF( Q15<>A15, "Différent du véhicule assigné", "Identique")) -> Identique | S15: =IF(B15 = "", "", VLOOKUP(B15, Commandes!D:G, 4, FALSE)) -> oui
A16: FA-902-XZ | B16: GMCU-T8J-A9U | C16: Angers, Pays de la Loire, 49051 | D16: 14 avr. 2026 10:08 | E16: On trip | F16: on | G16: 55 | H16: BALDE DIAO Samba | I16: FA-902-XZ | J16: TG Ouest | K16: true | L16: DAF | M16: LF | N16: 2018 | O16: XLRAEL2700L475280 | P16: Truck | Q16: =IFERROR(_xlfn.XLOOKUP(B16,'boitiers actifs'!C:C,'boitiers actifs'!A:A),"Pas installé") -> FA-902-XZ | R16: =IF(Q16 = "Pas installé", "Pas installé", IF( Q16<>A16, "Différent du véhicule assigné", "Identique")) -> Identique | S16: =IF(B16 = "", "", VLOOKUP(B16, Commandes!D:G, 4, FALSE)) -> oui
A17: GH-931-QW | B17: GYHU-FUP-SY9 | C17: Carquefou, Pays de la Loire, 44470 | D17: 14 avr. 2026 10:08 | E17: 14 avr. 2026 08:21 | F17: off | G17: 100 | I17: GH-931-QW | J17: TG Ouest | K17: true | L17: RENAULT | M17: T | N17: 2022 | O17: VF611A365ND038307 | P17: Truck | Q17: =IFERROR(_xlfn.XLOOKUP(B17,'boitiers actifs'!C:C,'boitiers actifs'!A:A),"Pas installé") -> GH-931-QW | R17: =IF(Q17 = "Pas installé", "Pas installé", IF( Q17<>A17, "Différent du véhicule assigné", "Identique")) -> Identique | S17: =IF(B17 = "", "", VLOOKUP(B17, Commandes!D:G, 4, FALSE)) -> oui
A18: ER-911-TW | B18: GGWD-5M4-6UZ | C18: Rennes, Bretagne, 35000 | D18: 14 avr. 2026 10:08 | E18: 14 avr. 2026 09:58 | F18: off | G18: 97 | H18: SANGAND Didier | I18: ER-911-TW | J18: TG Rennes (PF) | K18: true | L18: RENAULT | M18: D | N18: 2017 | O18: VF640J566HB007659 | P18: Truck | Q18: =IFERROR(_xlfn.XLOOKUP(B18,'boitiers actifs'!C:C,'boitiers actifs'!A:A),"Pas installé") -> ER-911-TW | R18: =IF(Q18 = "Pas installé", "Pas installé", IF( Q18<>A18, "Différent du véhicule assigné", "Identique")) -> Identique | S18: =IF(B18 = "", "", VLOOKUP(B18, Commandes!D:G, 4, FALSE)) -> oui
A19: DT-147-VG | C19: Bruguières, Occitanie, 31150 | D19: 30 sept. 2025 17:27 | E19: 30 sept. 2025 16:37 | F19: off | G19: 36 | I19: DT-147-VG | J19: TG MIDI PYRENEES | K19: true | L19: VOLVO | M19: FE | N19: 2015 | O19: YV2V0Y1A5FZ103193 | P19: Truck | Q19: =IFERROR(_xlfn.XLOOKUP(B19,'boitiers actifs'!C:C,'boitiers actifs'!A:A),"Pas installé") -> Pas installé | R19: =IF(Q19 = "Pas installé", "Pas installé", IF( Q19<>A19, "Différent du véhicule assigné", "Identique")) -> Pas installé | S19: =IF(B19 = "", "", VLOOKUP(B19, Commandes!D:G, 4, FALSE))
A20: DX-992-LX | B20: GA6Y-ACC-ZGN | C20: Ploërmel, Bretagne, 56800 | D20: 14 avr. 2026 10:08 | E20: 14 avr. 2026 09:44 | F20: off | G20: 68 | H20: TAANE Sebastien | I20: DX-992-LX | J20: TG St Brieuc (PF) | K20: true | L20: VOLVO | M20: FL | N20: 2015 | O20: YV2T0X1A2FZ103749 | P20: Truck | Q20: =IFERROR(_xlfn.XLOOKUP(B20,'boitiers actifs'!C:C,'boitiers actifs'!A:A),"Pas installé") -> DX-992-LX | R20: =IF(Q20 = "Pas installé", "Pas installé", IF( Q20<>A20, "Différent du véhicule assigné", "Identique")) -> Identique | S20: =IF(B20 = "", "", VLOOKUP(B20, Commandes!D:G, 4, FALSE)) -> oui
A21: DY-586-AV | C21: Carquefou, Pays de la Loire, 44470 | D21: 14 nov. 2025 09:32 | E21: 14 nov. 2025 08:09 | F21: off | G21: 97 | I21: DY-586-AV | J21: TG Ouest | K21: true | L21: RENAULT | M21: D WIDE | N21: 2016 | O21: VF620J868GB001573 | P21: Truck | Q21: =IFERROR(_xlfn.XLOOKUP(B21,'boitiers actifs'!C:C,'boitiers actifs'!A:A),"Pas installé") -> Pas installé | R21: =IF(Q21 = "Pas installé", "Pas installé", IF( Q21<>A21, "Différent du véhicule assigné", "Identique")) -> Pas installé | S21: =IF(B21 = "", "", VLOOKUP(B21, Commandes!D:G, 4, FALSE))
A22: GS-381-DM | B22: GVEY-USU-EYR | C22: Vezin-le-Coquet, Bretagne, 35132 | D22: 14 avr. 2026 10:08 | E22: On trip | F22: on | G22: 81 | H22: DABO GARREAU Melvyn | I22: GS-381-DM | J22: B100, TG Ouest | K22: true | L22: RENAULT | M22: D WIDE | N22: 2023 | O22: VF620J868PB012198 | P22: Truck | Q22: =IFERROR(_xlfn.XLOOKUP(B22,'boitiers actifs'!C:C,'boitiers actifs'!A:A),"Pas installé") -> GS-381-DM | R22: =IF(Q22 = "Pas installé", "Pas installé", IF( Q22<>A22, "Différent du véhicule assigné", "Identique")) -> Identique | S22: =IF(B22 = "", "", VLOOKUP(B22, Commandes!D:G, 4, FALSE)) -> oui
A23: FC-143-XX | B23: GMHZ-WUD-VBH | C23: Asnières-sur-Vègre, Pays de la Loire, 72430 | D23: 14 avr. 2026 10:08 | E23: On trip | F23: on | G23: 64 | H23: DIAWARA Mody | I23: FC-143-XX | J23: TG Ouest | K23: true | L23: RENAULT | M23: D WIDE | N23: 2019 | O23: VF620J861KB005750 | P23: Truck | Q23: =IFERROR(_xlfn.XLOOKUP(B23,'boitiers actifs'!C:C,'boitiers actifs'!A:A),"Pas installé") -> FC-143-XX | R23: =IF(Q23 = "Pas installé", "Pas installé", IF( Q23<>A23, "Différent du véhicule assigné", "Identique")) -> Identique | S23: =IF(B23 = "", "", VLOOKUP(B23, Commandes!D:G, 4, FALSE)) -> oui
A24: ES-540-QB | B24: GHDV-EV2-3N5 | C24: Cherbourg-en-Cotentin, Normandie, 50100 | D24: 14 avr. 2026 10:08 | E24: On trip | F24: on | G24: 46 | H24: SAUDRAIS Jerome | I24: ES-540-QB | J24: TG Caen (PF) | K24: true | L24: RENAULT | M24: D WIDE | N24: 2017 | O24: VF620J864HB004049 | P24: Truck | Q24: =IFERROR(_xlfn.XLOOKUP(B24,'boitiers actifs'!C:C,'boitiers actifs'!A:A),"Pas installé") -> ES-540-QB | R24: =IF(Q24 = "Pas installé", "Pas installé", IF( Q24<>A24, "Différent du véhicule assigné", "Identique")) -> Identique | S24: =IF(B24 = "", "", VLOOKUP(B24, Commandes!D:G, 4, FALSE)) -> oui
A25: EE-387-AM | C25: Carquefou, Pays de la Loire, 44470 | D25: 13 nov. 2025 18:29 | E25: 13 nov. 2025 18:02 | F25: off | G25: 92 | I25: EE-387-AM | J25: TG Ouest | K25: true | L25: RENAULT | M25: D WIDE | N25: 2016 | O25: VF620J864GB002171 | P25: Truck | Q25: =IFERROR(_xlfn.XLOOKUP(B25,'boitiers actifs'!C:C,'boitiers actifs'!A:A),"Pas installé") -> Pas installé | R25: =IF(Q25 = "Pas installé", "Pas installé", IF( Q25<>A25, "Différent du véhicule assigné", "Identique")) -> Pas installé | S25: =IF(B25 = "", "", VLOOKUP(B25, Commandes!D:G, 4, FALSE))
A26: GM-405-VD | B26: GT8Y-ZBH-Y4E | C26: Theix-Noyalo, Bretagne, 56450 | D26: 14 avr. 2026 10:08 | E26: On trip | F26: on | G26: 65 | H26: BAHOLET David | I26: GM-405-VD | J26: TG Ouest | K26: true | L26: RENAULT | M26: D WIDE | N26: 2023 | O26: VF620M863PB006164 | P26: Truck | Q26: =IFERROR(_xlfn.XLOOKUP(B26,'boitiers actifs'!C:C,'boitiers actifs'!A:A),"Pas installé") -> GM-405-VD | R26: =IF(Q26 = "Pas installé", "Pas installé", IF( Q26<>A26, "Différent du véhicule assigné", "Identique")) -> Identique | S26: =IF(B26 = "", "", VLOOKUP(B26, Commandes!D:G, 4, FALSE)) -> oui
A27: EQ-199-DT | B27: GGED-D56-N7K | C27: Villaines-la-Juhel, Pays de la Loire, 53700 | D27: 14 avr. 2026 10:08 | E27: On trip | F27: on | G27: - | H27: OUAHIM Driss | I27: EQ-199-DT | J27: TG Laval (PF) | K27: true | L27: RENAULT | M27: D | N27: 2017 | O27: VF640J567HB007251 | P27: Truck | Q27: =IFERROR(_xlfn.XLOOKUP(B27,'boitiers actifs'!C:C,'boitiers actifs'!A:A),"Pas installé") -> EQ-199-DT | R27: =IF(Q27 = "Pas installé", "Pas installé", IF( Q27<>A27, "Différent du véhicule assigné", "Identique")) -> Identique | S27: =IF(B27 = "", "", VLOOKUP(B27, Commandes!D:G, 4, FALSE)) -> oui
A28: EZ-411-LJ | B28: GKYW-FP2-N2G | C28: Givrand, Pays de la Loire, 85800 | D28: 14 avr. 2026 10:08 | E28: On trip | F28: off | G28: 56 | H28: BAH Mamadou Sadio | I28: EZ-411-LJ | J28: TG Ouest | K28: true | L28: VOLVO | M28: FE | N28: 2018 | O28: YV2V0Y1A4JZ120155 | P28: Truck | Q28: =IFERROR(_xlfn.XLOOKUP(B28,'boitiers actifs'!C:C,'boitiers actifs'!A:A),"Pas installé") -> EZ-411-LJ | R28: =IF(Q28 = "Pas installé", "Pas installé", IF( Q28<>A28, "Différent du véhicule assigné", "Identique")) -> Identique | S28: =IF(B28 = "", "", VLOOKUP(B28, Commandes!D:G, 4, FALSE)) -> oui
A29: FZ-365-XF | B29: GZD9-V8G-WMG | C29: Carquefou, Pays de la Loire, 44470 | D29: 14 avr. 2026 10:08 | E29: 10 avr. 2026 21:11 | F29: off | G29: 26 | I29: FZ-365-XF | J29: TG Ouest | K29: true | L29: IVECO | M29: DAILY | N29: 2021 | O29: ZCFCH35A20D682907 | P29: Truck | Q29: =IFERROR(_xlfn.XLOOKUP(B29,'boitiers actifs'!C:C,'boitiers actifs'!A:A),"Pas installé") -> FZ-365-XF | R29: =IF(Q29 = "Pas installé", "Pas installé", IF( Q29<>A29, "Différent du véhicule assigné", "Identique")) -> Identique | S29: =IF(B29 = "", "", VLOOKUP(B29, Commandes!D:G, 4, FALSE)) -> oui
A30: FQ-538-ZT | B30: GMXY-V8C-68J | C30: Vannes, Bretagne, 56000 | D30: 14 avr. 2026 10:08 | E30: On trip | F30: on | G30: 57 | H30: DA ROCHA Fernando | I30: FQ-538-ZT | J30: TG Quimper (PF) | K30: true | L30: RENAULT | M30: D WIDE | N30: 2020 | O30: VF620J860LB007975 | P30: Truck | Q30: =IFERROR(_xlfn.XLOOKUP(B30,'boitiers actifs'!C:C,'boitiers actifs'!A:A),"Pas installé") -> FQ-538-ZT | R30: =IF(Q30 = "Pas installé", "Pas installé", IF( Q30<>A30, "Différent du véhicule assigné", "Identique")) -> Identique | S30: =IF(B30 = "", "", VLOOKUP(B30, Commandes!D:G, 4, FALSE)) -> oui
A31: DL-782-CT | C31: Carquefou, Pays de la Loire, 44470 | D31: 29 déc. 2025 12:01 | E31: 29 déc. 2025 11:32 | F31: off | G31: 60 | I31: DL-782-CT | J31: TG Ouest | K31: true | L31: RENAULT | M31: D | N31: 2015 | O31: VF640J862FB000488 | P31: Truck | Q31: =IFERROR(_xlfn.XLOOKUP(B31,'boitiers actifs'!C:C,'boitiers actifs'!A:A),"Pas installé") -> Pas installé | R31: =IF(Q31 = "Pas installé", "Pas installé", IF( Q31<>A31, "Différent du véhicule assigné", "Identique")) -> Pas installé | S31: =IF(B31 = "", "", VLOOKUP(B31, Commandes!D:G, 4, FALSE))
A32: FR-723-EP | B32: GR9P-FB6-XWY | C32: Carquefou, Pays de la Loire, 44470 | D32: 14 avr. 2026 10:08 | E32: 14 avr. 2026 10:01 | F32: off | G32: 47 | H32: HEDOUIN Laurent | I32: FR-723-EP | J32: TG Ouest | K32: true | L32: RENAULT | M32: D | N32: 2020 | O32: VF640J563LB014805 | P32: Truck | Q32: =IFERROR(_xlfn.XLOOKUP(B32,'boitiers actifs'!C:C,'boitiers actifs'!A:A),"Pas installé") -> FR-723-EP | R32: =IF(Q32 = "Pas installé", "Pas installé", IF( Q32<>A32, "Différent du véhicule assigné", "Identique")) -> Identique | S32: =IF(B32 = "", "", VLOOKUP(B32, Commandes!D:G, 4, FALSE)) -> oui
A33: DX-219-JR | C33: Carquefou, Pays de la Loire, 44470 | D33: 14 nov. 2025 09:24 | E33: 14 nov. 2025 08:03 | F33: off | G33: 48 | I33: DX-219-JR | J33: TG Rennes (PF) | K33: true | L33: RENAULT | M33: D WIDE | N33: 2015 | O33: VF620J866FB001411 | P33: Truck | Q33: =IFERROR(_xlfn.XLOOKUP(B33,'boitiers actifs'!C:C,'boitiers actifs'!A:A),"Pas installé") -> Pas installé | R33: =IF(Q33 = "Pas installé", "Pas installé", IF( Q33<>A33, "Différent du véhicule assigné", "Identique")) -> Pas installé | S33: =IF(B33 = "", "", VLOOKUP(B33, Commandes!D:G, 4, FALSE))
A34: EZ-361-HN | B34: GJWC-92S-7EH | C34: Pacé, Bretagne, 35740 | D34: 14 avr. 2026 10:08 | E34: On trip | F34: on | G34: 76 | H34: TILLY Frederic | I34: EZ-361-HN | J34: TG St Brieuc (PF) | K34: true | L34: VOLVO | M34: FE | N34: 2018 | O34: YV2V0Y1A2JZ120185 | P34: Truck | Q34: =IFERROR(_xlfn.XLOOKUP(B34,'boitiers actifs'!C:C,'boitiers actifs'!A:A),"Pas installé") -> EZ-361-HN | R34: =IF(Q34 = "Pas installé", "Pas installé", IF( Q34<>A34, "Différent du véhicule assigné", "Identique")) -> Identique | S34: =IF(B34 = "", "", VLOOKUP(B34, Commandes!D:G, 4, FALSE)) -> oui
A35: ER-129-QA | B35: GGJW-7C9-U2X | C35: Rennes, Bretagne, 35000 | D35: 14 avr. 2026 10:08 | E35: On trip | F35: on | G35: 93 | H35: CHEVALIER Christophe | I35: ER-129-QA | J35: TG Rennes (PF) | K35: true | L35: RENAULT | M35: D | N35: 2018 | O35: VF640J562JB007759 | P35: Truck | Q35: =IFERROR(_xlfn.XLOOKUP(B35,'boitiers actifs'!C:C,'boitiers actifs'!A:A),"Pas installé") -> ER-129-QA | R35: =IF(Q35 = "Pas installé", "Pas installé", IF( Q35<>A35, "Différent du véhicule assigné", "Identique")) -> Identique | S35: =IF(B35 = "", "", VLOOKUP(B35, Commandes!D:G, 4, FALSE)) -> oui
A36: GR-728-QJ | B36: GVCB-JXY-JTK | C36: Vertou, Pays de la Loire, 44120 | D36: 14 avr. 2026 10:08 | E36: 14 avr. 2026 09:59 | F36: off | G36: 94 | H36: RIMAJOU Arnaud | I36: GR-728-QJ | J36: B100, TG Ouest | K36: true | L36: RENAULT | M36: D WIDE | N36: 2023 | O36: VF620J862PB012214 | P36: Truck | Q36: =IFERROR(_xlfn.XLOOKUP(B36,'boitiers actifs'!C:C,'boitiers actifs'!A:A),"Pas installé") -> GR-728-QJ | R36: =IF(Q36 = "Pas installé", "Pas installé", IF( Q36<>A36, "Différent du véhicule assigné", "Identique")) -> Identique | S36: =IF(B36 = "", "", VLOOKUP(B36, Commandes!D:G, 4, FALSE)) -> oui
A37: FQ-217-ZT | B37: GMVJ-F7H-EBY | C37: Quimperlé, Bretagne, 29300 | D37: 14 avr. 2026 10:08 | E37: 14 avr. 2026 10:02 | F37: on | G37: 85 | H37: HERRI Denis | I37: FQ-217-ZT | J37: TG Quimper (PF) | K37: true | L37: RENAULT | M37: D WIDE | N37: 2020 | O37: VF620J869LB007974 | P37: Truck | Q37: =IFERROR(_xlfn.XLOOKUP(B37,'boitiers actifs'!C:C,'boitiers actifs'!A:A),"Pas installé") -> FQ-217-ZT | R37: =IF(Q37 = "Pas installé", "Pas installé", IF( Q37<>A37, "Différent du véhicule assigné", "Identique")) -> Identique | S37: =IF(B37 = "", "", VLOOKUP(B37, Commandes!D:G, 4, FALSE)) -> oui
A38: GH-097-QX | B38: GYG6-GW2-PXF | C38: Carquefou, Pays de la Loire, 44470 | D38: 14 avr. 2026 10:08 | E38: 14 avr. 2026 08:48 | F38: off | G38: 100 | I38: GH-097-QX | J38: TG Ouest | K38: true | L38: RENAULT | M38: T | N38: 2022 | O38: VF611A364ND038914 | P38: Truck | Q38: =IFERROR(_xlfn.XLOOKUP(B38,'boitiers actifs'!C:C,'boitiers actifs'!A:A),"Pas installé") -> GH-097-QX | R38: =IF(Q38 = "Pas installé", "Pas installé", IF( Q38<>A38, "Différent du véhicule assigné", "Identique")) -> Identique | S38: =IF(B38 = "", "", VLOOKUP(B38, Commandes!D:G, 4, FALSE)) -> oui
A39: FP-060-JA | C39: Carquefou, Pays de la Loire, 44470 | D39: 29 déc. 2025 11:03 | E39: 29 déc. 2025 10:32 | F39: off | G39: 96 | I39: FP-060-JA | J39: TG Ouest | K39: true | L39: RENAULT | M39: D WIDE | N39: 2020 | O39: VF620M862LB003945 | P39: Truck | Q39: =IFERROR(_xlfn.XLOOKUP(B39,'boitiers actifs'!C:C,'boitiers actifs'!A:A),"Pas installé") -> Pas installé | R39: =IF(Q39 = "Pas installé", "Pas installé", IF( Q39<>A39, "Différent du véhicule assigné", "Identique")) -> Pas installé | S39: =IF(B39 = "", "", VLOOKUP(B39, Commandes!D:G, 4, FALSE))
A40: CN-390-WD | C40: Couffé, Pays de la Loire, 44521 | D40: 3 oct. 2024 12:38 | E40: 3 oct. 2024 12:34 | F40: off | G40: 75 | I40: CN-390-WD | J40: TG Ouest | K40: true | L40: RENAULT | M40: D WIDE | N40: 2024 | O40: VF620J868RB013709 | P40: Automatic | Q40: =IFERROR(_xlfn.XLOOKUP(B40,'boitiers actifs'!C:C,'boitiers actifs'!A:A),"Pas installé") -> Pas installé | R40: =IF(Q40 = "Pas installé", "Pas installé", IF( Q40<>A40, "Différent du véhicule assigné", "Identique")) -> Pas installé | S40: =IF(B40 = "", "", VLOOKUP(B40, Commandes!D:G, 4, FALSE))
A41: DX-027-CH | C41: Carquefou, Pays de la Loire, 44470 | D41: 29 janv. 2025 12:30 | E41: 27 janv. 2025 17:06 | F41: off | G41: 93 | I41: DX-027-CH | J41: TG Caen (PF) | K41: true | L41: VOLVO | M41: FL | N41: 2015 | O41: YV2T0X1A6FZ103379 | Q41: =IFERROR(_xlfn.XLOOKUP(B41,'boitiers actifs'!C:C,'boitiers actifs'!A:A),"Pas installé") -> Pas installé | R41: =IF(Q41 = "Pas installé", "Pas installé", IF( Q41<>A41, "Différent du véhicule assigné", "Identique")) -> Pas installé | S41: =IF(B41 = "", "", VLOOKUP(B41, Commandes!D:G, 4, FALSE))
A42: DX-954-JT | C42: Carquefou, Pays de la Loire, 44470 | D42: 28 nov. 2024 11:55 | E42: 27 nov. 2024 15:00 | F42: off | G42: 100 | I42: DX-954-JT | J42: TG Ouest | K42: true | L42: VOLVO | M42: FL | N42: 2015 | O42: YV2T0X1A7FZ103746 | Q42: =IFERROR(_xlfn.XLOOKUP(B42,'boitiers actifs'!C:C,'boitiers actifs'!A:A),"Pas installé") -> Pas installé | R42: =IF(Q42 = "Pas installé", "Pas installé", IF( Q42<>A42, "Différent du véhicule assigné", "Identique")) -> Pas installé | S42: =IF(B42 = "", "", VLOOKUP(B42, Commandes!D:G, 4, FALSE))
A43: EF-011-JE | B43: GEMY-89R-F2V | C43: Bédée, Bretagne, 35137 | D43: 14 avr. 2026 10:08 | E43: 13 avr. 2026 13:59 | F43: off | G43: 96 | I43: EF-011-JE | J43: TG Rennes (PF) | K43: true | L43: RENAULT | M43: D | N43: 2016 | O43: VF640J566GB004775 | P43: Truck | Q43: =IFERROR(_xlfn.XLOOKUP(B43,'boitiers actifs'!C:C,'boitiers actifs'!A:A),"Pas installé") -> EF-011-JE | R43: =IF(Q43 = "Pas installé", "Pas installé", IF( Q43<>A43, "Différent du véhicule assigné", "Identique")) -> Identique | S43: =IF(B43 = "", "", VLOOKUP(B43, Commandes!D:G, 4, FALSE)) -> oui
A44: DW-770-TH | C44: Carquefou, Pays de la Loire, 44470 | D44: 13 nov. 2025 16:07 | E44: 13 nov. 2025 13:43 | F44: off | G44: 84 | I44: DW-770-TH | J44: TG Ouest | K44: true | L44: VOLVO | M44: FL | N44: 2015 | O44: YV2T0X1AXFZ103319 | P44: Truck | Q44: =IFERROR(_xlfn.XLOOKUP(B44,'boitiers actifs'!C:C,'boitiers actifs'!A:A),"Pas installé") -> Pas installé | R44: =IF(Q44 = "Pas installé", "Pas installé", IF( Q44<>A44, "Différent du véhicule assigné", "Identique")) -> Pas installé | S44: =IF(B44 = "", "", VLOOKUP(B44, Commandes!D:G, 4, FALSE))
A45: GN-784-JD | B45: GUBX-ZR8-VD3 | C45: Le Tallud, Nouvelle-Aquitaine, 79200 | D45: 14 avr. 2026 10:08 | E45: 14 avr. 2026 09:42 | F45: on | G45: 63 | H45: GARREAU Stephane | I45: GN-784-JD | J45: TG La Roche sur Yon (PF) | K45: true | L45: RENAULT | M45: D WIDE | N45: 2023 | O45: VF620J861PB011524 | P45: Truck | Q45: =IFERROR(_xlfn.XLOOKUP(B45,'boitiers actifs'!C:C,'boitiers actifs'!A:A),"Pas installé") -> GN-784-JD | R45: =IF(Q45 = "Pas installé", "Pas installé", IF( Q45<>A45, "Différent du véhicule assigné", "Identique")) -> Identique | S45: =IF(B45 = "", "", VLOOKUP(B45, Commandes!D:G, 4, FALSE)) -> oui
A46: EZ-364-HN | B46: GK7X-VP8-S97 | C46: La Clarté, Bretagne, 22700 | D46: 14 avr. 2026 10:08 | E46: On trip | F46: on | G46: 75 | H46: LE MAT Stephane | I46: EZ-364-HN | J46: TG St Brieuc (PF) | K46: true | L46: VOLVO | M46: FE | N46: 2018 | O46: YV2V0Y1A5JZ120150 | P46: Truck | Q46: =IFERROR(_xlfn.XLOOKUP(B46,'boitiers actifs'!C:C,'boitiers actifs'!A:A),"Pas installé") -> EZ-364-HN | R46: =IF(Q46 = "Pas installé", "Pas installé", IF( Q46<>A46, "Différent du véhicule assigné", "Identique")) -> Identique | S46: =IF(B46 = "", "", VLOOKUP(B46, Commandes!D:G, 4, FALSE)) -> oui
A47: DX-696-KR | C47: Carquefou, Pays de la Loire, 44470 | D47: 3 mars 2025 16:43 | E47: 3 mars 2025 15:34 | F47: off | G47: 80 | I47: DX-696-KR | J47: TG Ouest | K47: true | L47: RENAULT | M47: D WIDE | N47: 2016 | O47: VF620J867GB001600 | P47: Truck | Q47: =IFERROR(_xlfn.XLOOKUP(B47,'boitiers actifs'!C:C,'boitiers actifs'!A:A),"Pas installé") -> Pas installé | R47: =IF(Q47 = "Pas installé", "Pas installé", IF( Q47<>A47, "Différent du véhicule assigné", "Identique")) -> Pas installé | S47: =IF(B47 = "", "", VLOOKUP(B47, Commandes!D:G, 4, FALSE))
A48: EF-792-NH | B48: GFY8-44N-FK8 | C48: Beaussais-sur-Mer, Bretagne, 22650 | D48: 14 avr. 2026 10:08 | E48: On trip | F48: on | G48: 66 | H48: MALET Rudy | I48: EF-792-NH | J48: TG St Brieuc (PF) | K48: true | L48: VOLVO | M48: FL | N48: 2016 | O48: YV2T0X1A4GZ109196 | P48: Truck | Q48: =IFERROR(_xlfn.XLOOKUP(B48,'boitiers actifs'!C:C,'boitiers actifs'!A:A),"Pas installé") -> EF-792-NH | R48: =IF(Q48 = "Pas installé", "Pas installé", IF( Q48<>A48, "Différent du véhicule assigné", "Identique")) -> Identique | S48: =IF(B48 = "", "", VLOOKUP(B48, Commandes!D:G, 4, FALSE)) -> oui
A49: DW-789-PY | B49: G6XK-TXR-FUR | C49: Plérin, Bretagne, 22190 | D49: 14 avr. 2026 10:08 | E49: 13 avr. 2026 13:59 | F49: off | G49: 100 | I49: DW-789-PY | J49: TG Ouest | K49: true | L49: VOLVO | M49: FL | N49: 2015 | O49: YV2T0X1A8FZ103481 | P49: Truck | Q49: =IFERROR(_xlfn.XLOOKUP(B49,'boitiers actifs'!C:C,'boitiers actifs'!A:A),"Pas installé") -> DW-789-PY | R49: =IF(Q49 = "Pas installé", "Pas installé", IF( Q49<>A49, "Différent du véhicule assigné", "Identique")) -> Identique | S49: =IF(B49 = "", "", VLOOKUP(B49, Commandes!D:G, 4, FALSE)) -> oui
A50: ES-117-AK | B50: GHCY-JG2-RHR | C50: Val-Couesnon, Bretagne, 35560 | D50: 14 avr. 2026 10:08 | E50: 14 avr. 2026 10:00 | F50: off | G50: 68 | H50: GIRARD Nicolas | I50: ES-117-AK | J50: TG Rennes (PF) | K50: true | L50: RENAULT | M50: D | N50: 2018 | O50: VF640J565JB007707 | P50: Truck | Q50: =IFERROR(_xlfn.XLOOKUP(B50,'boitiers actifs'!C:C,'boitiers actifs'!A:A),"Pas installé") -> ES-117-AK | R50: =IF(Q50 = "Pas installé", "Pas installé", IF( Q50<>A50, "Différent du véhicule assigné", "Identique")) -> Identique | S50: =IF(B50 = "", "", VLOOKUP(B50, Commandes!D:G, 4, FALSE)) -> oui
A51: DX-409-JR | C51: Carquefou, Pays de la Loire, 44470 | D51: 31 mars 2025 12:12 | E51: 28 mars 2025 10:32 | F51: off | G51: 63 | I51: DX-409-JR | J51: TG Ouest | K51: true | L51: RENAULT | M51: D WIDE | N51: 2015 | O51: VF620J86XFB001511 | P51: Truck | Q51: =IFERROR(_xlfn.XLOOKUP(B51,'boitiers actifs'!C:C,'boitiers actifs'!A:A),"Pas installé") -> Pas installé | R51: =IF(Q51 = "Pas installé", "Pas installé", IF( Q51<>A51, "Différent du véhicule assigné", "Identique")) -> Pas installé | S51: =IF(B51 = "", "", VLOOKUP(B51, Commandes!D:G, 4, FALSE))
A52: DX-808-BN | B52: G9J7-X7N-4S2 | C52: Chantepie, Bretagne, 35135 | D52: 14 avr. 2026 10:08 | E52: On trip | F52: idle | G52: 67 | H52: PERQUIS Corentin | I52: DX-808-BN | J52: TG Rennes (PF) | K52: true | L52: RENAULT | M52: D | N52: 2015 | O52: VF640J565FB002630 | P52: Truck | Q52: =IFERROR(_xlfn.XLOOKUP(B52,'boitiers actifs'!C:C,'boitiers actifs'!A:A),"Pas installé") -> DX-808-BN | R52: =IF(Q52 = "Pas installé", "Pas installé", IF( Q52<>A52, "Différent du véhicule assigné", "Identique")) -> Identique | S52: =IF(B52 = "", "", VLOOKUP(B52, Commandes!D:G, 4, FALSE)) -> oui
A53: GY-935-WQ | B53: G2RY-RZS-WBG | C53: Angers, Pays de la Loire, 49105 | D53: 14 avr. 2026 10:08 | E53: On trip | F53: off | G53: 75 | H53: CRESPEL Jean-Marc | I53: GY-935-WQ | J53: B100, TG Ouest | K53: true | L53: RENAULT | M53: D WIDE | N53: 2024 | O53: VF620J868RB013449 | P53: Truck | Q53: =IFERROR(_xlfn.XLOOKUP(B53,'boitiers actifs'!C:C,'boitiers actifs'!A:A),"Pas installé") -> GY-935-WQ | R53: =IF(Q53 = "Pas installé", "Pas installé", IF( Q53<>A53, "Différent du véhicule assigné", "Identique")) -> Identique | S53: =IF(B53 = "", "", VLOOKUP(B53, Commandes!D:G, 4, FALSE)) -> oui
A54: DT-924-AP | C54: Carquefou, Pays de la Loire, 44470 | D54: 10 janv. 2025 11:12 | E54: 9 janv. 2025 00:26 | F54: off | G54: 57 | I54: DT-924-AP | J54: TG Ouest | K54: true | L54: RENAULT | M54: D WIDE | N54: 2015 | O54: VF620J867FB000977 | P54: Automatic | Q54: =IFERROR(_xlfn.XLOOKUP(B54,'boitiers actifs'!C:C,'boitiers actifs'!A:A),"Pas installé") -> Pas installé | R54: =IF(Q54 = "Pas installé", "Pas installé", IF( Q54<>A54, "Différent du véhicule assigné", "Identique")) -> Pas installé | S54: =IF(B54 = "", "", VLOOKUP(B54, Commandes!D:G, 4, FALSE))
A55: GZ-282-BH | B55: G364-BWH-BHV | C55: Carquefou, Pays de la Loire, 44470 | D55: 14 avr. 2026 10:08 | E55: 13 avr. 2026 08:26 | F55: off | G55: 86 | I55: GZ-282-BH | J55: B100, TG Ouest | K55: true | L55: RENAULT | M55: D WIDE | N55: 2024 | O55: VF620J865RB013716 | P55: Truck | Q55: =IFERROR(_xlfn.XLOOKUP(B55,'boitiers actifs'!C:C,'boitiers actifs'!A:A),"Pas installé") -> GZ-282-BH | R55: =IF(Q55 = "Pas installé", "Pas installé", IF( Q55<>A55, "Différent du véhicule assigné", "Identique")) -> Identique | S55: =IF(B55 = "", "", VLOOKUP(B55, Commandes!D:G, 4, FALSE)) -> oui
A56: EP-450-YV | B56: GG3U-84Z-FDR | C56: Le Ribay, Pays de la Loire, 53640 | D56: 14 avr. 2026 10:08 | E56: On trip | F56: on | G56: 89 | H56: RIVET Gwenael | I56: EP-450-YV | J56: TG Laval (PF) | K56: true | L56: RENAULT | M56: D | N56: 2017 | O56: VF640J564HB007286 | P56: Truck | Q56: =IFERROR(_xlfn.XLOOKUP(B56,'boitiers actifs'!C:C,'boitiers actifs'!A:A),"Pas installé") -> EP-450-YV | R56: =IF(Q56 = "Pas installé", "Pas installé", IF( Q56<>A56, "Différent du véhicule assigné", "Identique")) -> Identique | S56: =IF(B56 = "", "", VLOOKUP(B56, Commandes!D:G, 4, FALSE)) -> oui
A57: CV-018-DH | B57: GXWW-YBB-FJF | C57: Carquefou, Pays de la Loire, 44470 | D57: 14 avr. 2026 10:08 | E57: 14 avr. 2026 02:56 | F57: off | G57: - | I57: CV-018-DH | J57: TG Ouest | K57: true | L57: RENAULT | M57: PREMIUM | N57: 2013 | O57: VF624GPA000068657 | P57: Truck | Q57: =IFERROR(_xlfn.XLOOKUP(B57,'boitiers actifs'!C:C,'boitiers actifs'!A:A),"Pas installé") -> CV-018-DH | R57: =IF(Q57 = "Pas installé", "Pas installé", IF( Q57<>A57, "Différent du véhicule assigné", "Identique")) -> Identique | S57: =IF(B57 = "", "", VLOOKUP(B57, Commandes!D:G, 4, FALSE)) -> oui
A58: ER-455-QA | B58: GGNC-7Z5-T4W | C58: Coësmes, Bretagne, 35134 | D58: 14 avr. 2026 10:08 | E58: 14 avr. 2026 09:48 | F58: off | G58: 82 | H58: BROHAN Brian | I58: ER-455-QA | J58: TG Rennes (PF) | K58: true | L58: RENAULT | M58: D | N58: 2017 | O58: VF640J566HB007645 | P58: Truck | Q58: =IFERROR(_xlfn.XLOOKUP(B58,'boitiers actifs'!C:C,'boitiers actifs'!A:A),"Pas installé") -> ER-455-QA | R58: =IF(Q58 = "Pas installé", "Pas installé", IF( Q58<>A58, "Différent du véhicule assigné", "Identique")) -> Identique | S58: =IF(B58 = "", "", VLOOKUP(B58, Commandes!D:G, 4, FALSE)) -> oui
A59: FT-973-PK | B59: GSAF-YJ4-UKN | C59: Carquefou, Pays de la Loire, 44470 | D59: 14 avr. 2026 10:08 | E59: 13 avr. 2026 14:41 | F59: off | G59: 96 | I59: FT-973-PK | J59: TG Ouest | K59: true | L59: RENAULT | M59: D | N59: 2020 | O59: VF640J56XLB015109 | P59: Truck | Q59: =IFERROR(_xlfn.XLOOKUP(B59,'boitiers actifs'!C:C,'boitiers actifs'!A:A),"Pas installé") -> FT-973-PK | R59: =IF(Q59 = "Pas installé", "Pas installé", IF( Q59<>A59, "Différent du véhicule assigné", "Identique")) -> Identique | S59: =IF(B59 = "", "", VLOOKUP(B59, Commandes!D:G, 4, FALSE)) -> oui
A60: EF-147-MY | B60: GFMK-CWM-XF8 | C60: Plérin, Bretagne, 22190 | D60: 14 avr. 2026 10:08 | E60: 14 avr. 2026 09:51 | F60: off | G60: 79 | H60: MARCECA Renaud | I60: EF-147-MY | J60: TG St Brieuc (PF) | K60: true | L60: VOLVO | M60: FL | N60: 2016 | O60: YV2T0X1A7GZ109368 | P60: Truck | Q60: =IFERROR(_xlfn.XLOOKUP(B60,'boitiers actifs'!C:C,'boitiers actifs'!A:A),"Pas installé") -> EF-147-MY | R60: =IF(Q60 = "Pas installé", "Pas installé", IF( Q60<>A60, "Différent du véhicule assigné", "Identique")) -> Identique | S60: =IF(B60 = "", "", VLOOKUP(B60, Commandes!D:G, 4, FALSE)) -> oui
A61: DK-420-MY | C61: Carquefou, Pays de la Loire, 44470 | D61: 19 févr. 2025 12:35 | E61: 12 févr. 2025 16:40 | F61: off | G61: 96 | I61: DK-420-MY | J61: TG Quimper (PF) | K61: true | L61: RENAULT | M61: D | N61: 2014 | O61: VF640J560EB000752 | P61: Automatic | Q61: =IFERROR(_xlfn.XLOOKUP(B61,'boitiers actifs'!C:C,'boitiers actifs'!A:A),"Pas installé") -> Pas installé | R61: =IF(Q61 = "Pas installé", "Pas installé", IF( Q61<>A61, "Différent du véhicule assigné", "Identique")) -> Pas installé | S61: =IF(B61 = "", "", VLOOKUP(B61, Commandes!D:G, 4, FALSE))
A62: DT-291-BG | B62: GYNC-9U8-FU6 | C62: Carquefou, Pays de la Loire, 44470 | D62: 14 avr. 2026 10:08 | E62: 13 avr. 2026 12:41 | F62: off | G62: 100 | I62: DT-291-BG | J62: TG Ouest | K62: true | L62: RENAULT | M62: MASTER | N62: 2015 | O62: VF6VFE4S652921537 | P62: Truck | Q62: =IFERROR(_xlfn.XLOOKUP(B62,'boitiers actifs'!C:C,'boitiers actifs'!A:A),"Pas installé") -> DT-291-BG | R62: =IF(Q62 = "Pas installé", "Pas installé", IF( Q62<>A62, "Différent du véhicule assigné", "Identique")) -> Identique | S62: =IF(B62 = "", "", VLOOKUP(B62, Commandes!D:G, 4, FALSE)) -> oui
A63: DX-293-KR | C63: Carquefou, Pays de la Loire, 44470 | D63: 26 mars 2025 17:45 | E63: 26 mars 2025 10:42 | F63: off | G63: 48 | I63: DX-293-KR | J63: TG Ouest | K63: true | L63: RENAULT | M63: D WIDE | N63: 2016 | O63: VF620J868GB001556 | P63: Truck | Q63: =IFERROR(_xlfn.XLOOKUP(B63,'boitiers actifs'!C:C,'boitiers actifs'!A:A),"Pas installé") -> Pas installé | R63: =IF(Q63 = "Pas installé", "Pas installé", IF( Q63<>A63, "Différent du véhicule assigné", "Identique")) -> Pas installé | S63: =IF(B63 = "", "", VLOOKUP(B63, Commandes!D:G, 4, FALSE))
A64: EP-959-YT | B64: GG4K-EUG-4SC | C64: Saint-Berthevin, Pays de la Loire, 53940 | D64: 14 avr. 2026 10:08 | E64: 1 avr. 2026 18:53 | F64: off | G64: 83 | I64: EP-959-YT | J64: TG Laval (PF) | K64: true | L64: RENAULT | M64: D | N64: 2017 | O64: VF640J567HB007329 | P64: Truck | Q64: =IFERROR(_xlfn.XLOOKUP(B64,'boitiers actifs'!C:C,'boitiers actifs'!A:A),"Pas installé") -> EP-959-YT | R64: =IF(Q64 = "Pas installé", "Pas installé", IF( Q64<>A64, "Différent du véhicule assigné", "Identique")) -> Identique | S64: =IF(B64 = "", "", VLOOKUP(B64, Commandes!D:G, 4, FALSE)) -> oui
A65: FR-072-MN | B65: GPG9-4TA-RNF | C65: Vannes, Bretagne, 56000 | D65: 14 avr. 2026 10:08 | E65: On trip | F65: on | G65: 66 | H65: DUFRIEN Ludovic | I65: FR-072-MN | J65: TG Quimper (PF) | K65: true | L65: RENAULT | M65: D WIDE | N65: 2020 | O65: VF620J868LB007982 | P65: Truck | Q65: =IFERROR(_xlfn.XLOOKUP(B65,'boitiers actifs'!C:C,'boitiers actifs'!A:A),"Pas installé") -> FR-072-MN | R65: =IF(Q65 = "Pas installé", "Pas installé", IF( Q65<>A65, "Différent du véhicule assigné", "Identique")) -> Identique | S65: =IF(B65 = "", "", VLOOKUP(B65, Commandes!D:G, 4, FALSE)) -> oui
A66: FF-656-NP | C66: Carquefou, Pays de la Loire, 44470 | D66: 29 déc. 2025 16:51 | E66: 29 déc. 2025 16:33 | F66: off | G66: 97 | I66: FF-656-NP | J66: TG Ouest | K66: true | L66: RENAULT | M66: D | N66: 2019 | O66: VF640J56XKB012192 | P66: Truck | Q66: =IFERROR(_xlfn.XLOOKUP(B66,'boitiers actifs'!C:C,'boitiers actifs'!A:A),"Pas installé") -> Pas installé | R66: =IF(Q66 = "Pas installé", "Pas installé", IF( Q66<>A66, "Différent du véhicule assigné", "Identique")) -> Pas installé | S66: =IF(B66 = "", "", VLOOKUP(B66, Commandes!D:G, 4, FALSE))
A67: DT-401-LA | C67: Carquefou, Pays de la Loire, 44470 | D67: 7 janv. 2025 17:08 | E67: 7 janv. 2025 11:40 | F67: off | G67: 92 | I67: DT-401-LA | J67: TG Ouest | K67: true | L67: RENAULT | M67: D WIDE | N67: 2015 | O67: VF620J864FB001004 | P67: Automatic | Q67: =IFERROR(_xlfn.XLOOKUP(B67,'boitiers actifs'!C:C,'boitiers actifs'!A:A),"Pas installé") -> Pas installé | R67: =IF(Q67 = "Pas installé", "Pas installé", IF( Q67<>A67, "Différent du véhicule assigné", "Identique")) -> Pas installé | S67: =IF(B67 = "", "", VLOOKUP(B67, Commandes!D:G, 4, FALSE))
A68: DV-086-QD | C68: Carquefou, Pays de la Loire, 44470 | D68: 27 févr. 2025 11:43 | E68: 26 févr. 2025 17:26 | F68: off | G68: 30 | I68: DV-086-QD | J68: TG Quimper (PF) | K68: true | L68: VOLVO | M68: FL | N68: 2015 | O68: YV2T0X1A8FZ103447 | P68: Truck | Q68: =IFERROR(_xlfn.XLOOKUP(B68,'boitiers actifs'!C:C,'boitiers actifs'!A:A),"Pas installé") -> Pas installé | R68: =IF(Q68 = "Pas installé", "Pas installé", IF( Q68<>A68, "Différent du véhicule assigné", "Identique")) -> Pas installé | S68: =IF(B68 = "", "", VLOOKUP(B68, Commandes!D:G, 4, FALSE))
A69: GR-621-RJ | B69: GUHP-HUN-9S8 | C69: Rezé, Pays de la Loire, 44400 | D69: 14 avr. 2026 10:08 | E69: On trip | F69: on | G69: 80 | H69: BRUGERE Patrice | I69: GR-621-RJ | J69: B100, TG Ouest | K69: true | L69: RENAULT | M69: D WIDE | N69: 2023 | O69: VF620J86XPB012221 | P69: Truck | Q69: =IFERROR(_xlfn.XLOOKUP(B69,'boitiers actifs'!C:C,'boitiers actifs'!A:A),"Pas installé") -> GR-621-RJ | R69: =IF(Q69 = "Pas installé", "Pas installé", IF( Q69<>A69, "Différent du véhicule assigné", "Identique")) -> Identique | S69: =IF(B69 = "", "", VLOOKUP(B69, Commandes!D:G, 4, FALSE)) -> oui
A70: DX-027-KR | C70: Carquefou, Pays de la Loire, 44470 | D70: 20 mars 2025 12:33 | E70: 20 mars 2025 11:29 | F70: off | G70: 100 | I70: DX-027-KR | J70: TG Laval (PF) | K70: true | L70: RENAULT | M70: D WIDE | N70: 2024 | O70: VF620J860RB014272 | P70: Truck | Q70: =IFERROR(_xlfn.XLOOKUP(B70,'boitiers actifs'!C:C,'boitiers actifs'!A:A),"Pas installé") -> Pas installé | R70: =IF(Q70 = "Pas installé", "Pas installé", IF( Q70<>A70, "Différent du véhicule assigné", "Identique")) -> Pas installé | S70: =IF(B70 = "", "", VLOOKUP(B70, Commandes!D:G, 4, FALSE))
A71: DT-151-VG | C71: Bruguières, Occitanie, 31150 | D71: 24 oct. 2025 09:13 | E71: 22 oct. 2025 10:30 | F71: off | G71: 62 | I71: DT-151-VG | J71: TG MIDI PYRENEES | K71: true | L71: VOLVO | M71: FE | N71: 2015 | O71: YV2V0Y1A1FZ103191 | P71: Truck | Q71: =IFERROR(_xlfn.XLOOKUP(B71,'boitiers actifs'!C:C,'boitiers actifs'!A:A),"Pas installé") -> Pas installé | R71: =IF(Q71 = "Pas installé", "Pas installé", IF( Q71<>A71, "Différent du véhicule assigné", "Identique")) -> Pas installé | S71: =IF(B71 = "", "", VLOOKUP(B71, Commandes!D:G, 4, FALSE))
A72: GW-638-LM | B72: GYSV-ZEG-W5R | C72: Frossay, Pays de la Loire, 44320 | D72: 14 avr. 2026 10:08 | E72: On trip | F72: on | G72: 45 | H72: DIOP Abdoul Aziz | I72: GW-638-LM | J72: B100, TG Ouest | K72: true | L72: RENAULT | M72: D WIDE | N72: 2024 | O72: VF620J868RB012978 | P72: Truck | Q72: =IFERROR(_xlfn.XLOOKUP(B72,'boitiers actifs'!C:C,'boitiers actifs'!A:A),"Pas installé") -> GW-638-LM | R72: =IF(Q72 = "Pas installé", "Pas installé", IF( Q72<>A72, "Différent du véhicule assigné", "Identique")) -> Identique | S72: =IF(B72 = "", "", VLOOKUP(B72, Commandes!D:G, 4, FALSE)) -> oui
A73: DW-793-PY | C73: Bruguières, Occitanie, 31150 | D73: 24 oct. 2025 08:56 | E73: 30 sept. 2025 11:49 | F73: off | G73: 50 | I73: DW-793-PY | J73: TG MIDI PYRENEES | K73: true | L73: VOLVO | M73: FE | N73: 2015 | O73: YV2V0Y1A1FZ103837 | P73: Truck | Q73: =IFERROR(_xlfn.XLOOKUP(B73,'boitiers actifs'!C:C,'boitiers actifs'!A:A),"Pas installé") -> Pas installé | R73: =IF(Q73 = "Pas installé", "Pas installé", IF( Q73<>A73, "Différent du véhicule assigné", "Identique")) -> Pas installé | S73: =IF(B73 = "", "", VLOOKUP(B73, Commandes!D:G, 4, FALSE))
A74: EF-177-HN | B74: GFP8-J4M-HA7 | C74: Le Mont-Saint-Michel, Normandie, 50170 | D74: 14 avr. 2026 10:08 | E74: 14 avr. 2026 09:42 | F74: off | G74: 72 | H74: MAIZI Hicham | I74: EF-177-HN | J74: TG Caen (PF) | K74: true | L74: RENAULT | M74: D WIDE | N74: 2016 | O74: VF620J860GB002510 | P74: Truck | Q74: =IFERROR(_xlfn.XLOOKUP(B74,'boitiers actifs'!C:C,'boitiers actifs'!A:A),"Pas installé") -> EF-177-HN | R74: =IF(Q74 = "Pas installé", "Pas installé", IF( Q74<>A74, "Différent du véhicule assigné", "Identique")) -> Identique | S74: =IF(B74 = "", "", VLOOKUP(B74, Commandes!D:G, 4, FALSE)) -> oui
A75: FQ-835-ZT | B75: GNC5-SDR-VK3 | C75: Châteaulin, Bretagne, 29150 | D75: 14 avr. 2026 10:08 | E75: 14 avr. 2026 09:50 | F75: off | G75: 83 | H75: CARIOU Ronan | I75: FQ-835-ZT | J75: TG Quimper (PF) | K75: true | L75: RENAULT | M75: D WIDE | N75: 2020 | O75: VF620J868LB007934 | P75: Truck | Q75: =IFERROR(_xlfn.XLOOKUP(B75,'boitiers actifs'!C:C,'boitiers actifs'!A:A),"Pas installé") -> FQ-835-ZT | R75: =IF(Q75 = "Pas installé", "Pas installé", IF( Q75<>A75, "Différent du véhicule assigné", "Identique")) -> Identique | S75: =IF(B75 = "", "", VLOOKUP(B75, Commandes!D:G, 4, FALSE)) -> oui
A76: DY-491-DR | B76: GAAJ-496-PBU | C76: Noirmoutier-en-l'Île, Pays de la Loire, 85330 | D76: 14 avr. 2026 10:08 | E76: On trip | F76: off | G76: 85 | H76: OULD AHMED Ismael | I76: DY-491-DR | J76: TG Ouest | K76: true | L76: VOLVO | M76: FL | N76: 2015 | O76: YV2T0X1A0FZ103748 | P76: Truck | Q76: =IFERROR(_xlfn.XLOOKUP(B76,'boitiers actifs'!C:C,'boitiers actifs'!A:A),"Pas installé") -> DY-491-DR | R76: =IF(Q76 = "Pas installé", "Pas installé", IF( Q76<>A76, "Différent du véhicule assigné", "Identique")) -> Identique | S76: =IF(B76 = "", "", VLOOKUP(B76, Commandes!D:G, 4, FALSE)) -> oui
A77: CR-711-TY | C77: Carquefou, Pays de la Loire, 44470 | D77: 6 nov. 2024 16:13 | E77: 31 oct. 2024 12:56 | F77: off | G77: - | I77: CR-711-TY | J77: TG Ouest | K77: true | L77: RENAULT | M77: MIDLUM | N77: 2013 | O77: VF644AGE000012004 | P77: Automatic | Q77: =IFERROR(_xlfn.XLOOKUP(B77,'boitiers actifs'!C:C,'boitiers actifs'!A:A),"Pas installé") -> Pas installé | R77: =IF(Q77 = "Pas installé", "Pas installé", IF( Q77<>A77, "Différent du véhicule assigné", "Identique")) -> Pas installé | S77: =IF(B77 = "", "", VLOOKUP(B77, Commandes!D:G, 4, FALSE))
A78: EW-511-SC | B78: GJHX-XX8-7V2 | C78: Carquefou, Pays de la Loire, 44470 | D78: 13 avr. 2026 21:51 | E78: 13 avr. 2026 21:46 | F78: off | G78: 35 | I78: EW-511-SC | J78: TG Ouest | K78: true | L78: DAF | M78: LF | N78: 2018 | O78: XLRAEL3700L470599 | P78: Truck | Q78: =IFERROR(_xlfn.XLOOKUP(B78,'boitiers actifs'!C:C,'boitiers actifs'!A:A),"Pas installé") -> EW-511-SC | R78: =IF(Q78 = "Pas installé", "Pas installé", IF( Q78<>A78, "Différent du véhicule assigné", "Identique")) -> Identique | S78: =IF(B78 = "", "", VLOOKUP(B78, Commandes!D:G, 4, FALSE)) -> oui
A79: FR-193-MW | B79: GPHX-KJB-6V9 | C79: Saint-Berthevin, Pays de la Loire, 53940 | D79: 14 avr. 2026 10:08 | E79: 14 avr. 2026 00:11 | F79: off | G79: 56 | I79: FR-193-MW | J79: TG Ouest | K79: true | L79: RENAULT | M79: D | N79: 2020 | O79: VF640J568LB014864 | P79: Truck | Q79: =IFERROR(_xlfn.XLOOKUP(B79,'boitiers actifs'!C:C,'boitiers actifs'!A:A),"Pas installé") -> FR-193-MW | R79: =IF(Q79 = "Pas installé", "Pas installé", IF( Q79<>A79, "Différent du véhicule assigné", "Identique")) -> Identique | S79: =IF(B79 = "", "", VLOOKUP(B79, Commandes!D:G, 4, FALSE)) -> oui
A80: GY-797-WQ | B80: GXEJ-VWX-9NP | C80: Carquefou, Pays de la Loire, 44470 | D80: 14 avr. 2026 10:08 | E80: 10 avr. 2026 14:02 | F80: off | G80: 100 | I80: GY-797-WQ | J80: B100, TG Ouest | K80: true | L80: RENAULT | M80: D WIDE | N80: 2024 | O80: VF620J868RB013466 | P80: Truck | Q80: =IFERROR(_xlfn.XLOOKUP(B80,'boitiers actifs'!C:C,'boitiers actifs'!A:A),"Pas installé") -> GY-797-WQ | R80: =IF(Q80 = "Pas installé", "Pas installé", IF( Q80<>A80, "Différent du véhicule assigné", "Identique")) -> Identique | S80: =IF(B80 = "", "", VLOOKUP(B80, Commandes!D:G, 4, FALSE)) -> oui
A81: FA-049-YA | B81: GM36-EYR-4TP | C81: Nantes, Pays de la Loire, 44000 | D81: 14 avr. 2026 10:08 | E81: 14 avr. 2026 09:17 | F81: idle | G81: 55 | H81: DIALLO Ibrahima Sory | I81: FA-049-YA | J81: TG Ouest | K81: true | L81: DAF | M81: LF | N81: 2018 | O81: XLRAEL2700L475281 | P81: Truck | Q81: =IFERROR(_xlfn.XLOOKUP(B81,'boitiers actifs'!C:C,'boitiers actifs'!A:A),"Pas installé") -> FA-049-YA | R81: =IF(Q81 = "Pas installé", "Pas installé", IF( Q81<>A81, "Différent du véhicule assigné", "Identique")) -> Identique | S81: =IF(B81 = "", "", VLOOKUP(B81, Commandes!D:G, 4, FALSE)) -> oui
A82: DT-918-FY | C82: Carquefou, Pays de la Loire, 44470 | D82: 28 févr. 2025 14:31 | E82: 27 févr. 2025 12:26 | F82: off | G82: 52 | I82: DT-918-FY | J82: TG Ouest | K82: true | L82: RENAULT | M82: D WIDE | N82: 2015 | O82: VF620J860FB001159 | P82: Truck | Q82: =IFERROR(_xlfn.XLOOKUP(B82,'boitiers actifs'!C:C,'boitiers actifs'!A:A),"Pas installé") -> Pas installé | R82: =IF(Q82 = "Pas installé", "Pas installé", IF( Q82<>A82, "Différent du véhicule assigné", "Identique")) -> Pas installé | S82: =IF(B82 = "", "", VLOOKUP(B82, Commandes!D:G, 4, FALSE))
A83: EZ-367-HN | B83: GKE7-H89-U3V | C83: Carquefou, Pays de la Loire, 44470 | D83: 14 avr. 2026 10:08 | E83: 13 avr. 2026 17:34 | F83: off | G83: - | I83: EZ-367-HN | J83: TG Ouest | K83: true | L83: VOLVO | M83: FE | N83: 2018 | O83: YV2V0Y1A5JZ120178 | P83: Truck | Q83: =IFERROR(_xlfn.XLOOKUP(B83,'boitiers actifs'!C:C,'boitiers actifs'!A:A),"Pas installé") -> EZ-367-HN | R83: =IF(Q83 = "Pas installé", "Pas installé", IF( Q83<>A83, "Différent du véhicule assigné", "Identique")) -> Identique | S83: =IF(B83 = "", "", VLOOKUP(B83, Commandes!D:G, 4, FALSE)) -> oui
A84: EZ-040-GR | B84: GJSA-A8G-R3N | C84: Pouancé, Pays de la Loire, 49420 | D84: 14 avr. 2026 10:08 | E84: 14 avr. 2026 09:51 | F84: off | G84: 58 | H84: FERRE Pascal | I84: EZ-040-GR | J84: TG Ouest | K84: true | L84: DAF | M84: LF | N84: 2018 | O84: XLRAEL3700L475365 | P84: Truck | Q84: =IFERROR(_xlfn.XLOOKUP(B84,'boitiers actifs'!C:C,'boitiers actifs'!A:A),"Pas installé") -> EZ-040-GR | R84: =IF(Q84 = "Pas installé", "Pas installé", IF( Q84<>A84, "Différent du véhicule assigné", "Identique")) -> Identique | S84: =IF(B84 = "", "", VLOOKUP(B84, Commandes!D:G, 4, FALSE)) -> oui
A85: DS-830-NB | C85: Préfailles, Pays de la Loire, 44770 | D85: 31 janv. 2025 08:32 | E85: 31 janv. 2025 08:28 | F85: off | G85: 81 | I85: DS-830-NB | J85: TG Quimper (PF) | K85: true | L85: RENAULT | M85: D WIDE | N85: 2025 | O85: VF620J862SB014358 | Q85: =IFERROR(_xlfn.XLOOKUP(B85,'boitiers actifs'!C:C,'boitiers actifs'!A:A),"Pas installé") -> Pas installé | R85: =IF(Q85 = "Pas installé", "Pas installé", IF( Q85<>A85, "Différent du véhicule assigné", "Identique")) -> Pas installé | S85: =IF(B85 = "", "", VLOOKUP(B85, Commandes!D:G, 4, FALSE))
A86: FS-384-GQ | B86: GS3A-833-V5A | C86: Le Chefresne, Normandie, 50410 | D86: 14 avr. 2026 10:08 | E86: 14 avr. 2026 10:03 | F86: off | G86: 48 | I86: FS-384-GQ | J86: TG Caen (PF) | K86: true | L86: RENAULT | M86: D WIDE | N86: 2020 | O86: VF620J861LB008018 | P86: Truck | Q86: =IFERROR(_xlfn.XLOOKUP(B86,'boitiers actifs'!C:C,'boitiers actifs'!A:A),"Pas installé") -> FS-384-GQ | R86: =IF(Q86 = "Pas installé", "Pas installé", IF( Q86<>A86, "Différent du véhicule assigné", "Identique")) -> Identique | S86: =IF(B86 = "", "", VLOOKUP(B86, Commandes!D:G, 4, FALSE)) -> oui
A87: FS-992-GP | B87: GS3V-JSE-AMW | C87: Carquefou, Pays de la Loire, 44470 | D87: 14 avr. 2026 10:08 | E87: 13 avr. 2026 18:44 | F87: off | G87: 44 | I87: FS-992-GP | J87: TG Caen (PF) | K87: true | L87: RENAULT | M87: D WIDE | N87: 2020 | O87: VF620J865LB007938 | P87: Truck | Q87: =IFERROR(_xlfn.XLOOKUP(B87,'boitiers actifs'!C:C,'boitiers actifs'!A:A),"Pas installé") -> FS-992-GP | R87: =IF(Q87 = "Pas installé", "Pas installé", IF( Q87<>A87, "Différent du véhicule assigné", "Identique")) -> Identique | S87: =IF(B87 = "", "", VLOOKUP(B87, Commandes!D:G, 4, FALSE)) -> oui
A88: DX-317-XE | C88: Loudéac, Bretagne, 22600 | D88: 6 févr. 2025 17:25 | E88: 21 janv. 2025 18:05 | F88: off | G88: 46 | I88: DX-317-XE | J88: TG Ouest | K88: true | L88: VOLVO | M88: FL | N88: 2015 | O88: YV2T0X1A5FZ103762 | Q88: =IFERROR(_xlfn.XLOOKUP(B88,'boitiers actifs'!C:C,'boitiers actifs'!A:A),"Pas installé") -> Pas installé | R88: =IF(Q88 = "Pas installé", "Pas installé", IF( Q88<>A88, "Différent du véhicule assigné", "Identique")) -> Pas installé | S88: =IF(B88 = "", "", VLOOKUP(B88, Commandes!D:G, 4, FALSE))
A89: DX-100-GY | C89: Carquefou, Pays de la Loire, 44470 | D89: 7 févr. 2025 15:36 | E89: 6 févr. 2025 16:43 | F89: off | G89: 100 | I89: DX-100-GY | J89: TG Caen (PF) | K89: true | L89: VOLVO | M89: FL | N89: 2015 | O89: YV2T0X1A1FZ103872 | Q89: =IFERROR(_xlfn.XLOOKUP(B89,'boitiers actifs'!C:C,'boitiers actifs'!A:A),"Pas installé") -> Pas installé | R89: =IF(Q89 = "Pas installé", "Pas installé", IF( Q89<>A89, "Différent du véhicule assigné", "Identique")) -> Pas installé | S89: =IF(B89 = "", "", VLOOKUP(B89, Commandes!D:G, 4, FALSE))
A90: GN-775-AJ | B90: GTR5-J2B-8E3 | C90: L'Aigle, Normandie, 61300 | D90: 14 avr. 2026 10:08 | E90: On trip | F90: on | G90: 65 | H90: LEVAVASSEUR Marc | I90: GN-775-AJ | J90: TG Caen (PF) | K90: true | L90: RENAULT | M90: D WIDE | N90: 2023 | O90: VF620J863PB011511 | P90: Truck | Q90: =IFERROR(_xlfn.XLOOKUP(B90,'boitiers actifs'!C:C,'boitiers actifs'!A:A),"Pas installé") -> GN-775-AJ | R90: =IF(Q90 = "Pas installé", "Pas installé", IF( Q90<>A90, "Différent du véhicule assigné", "Identique")) -> Identique | S90: =IF(B90 = "", "", VLOOKUP(B90, Commandes!D:G, 4, FALSE)) -> oui
A91: EF-550-HR | B91: GFRV-R8F-84D | C91: Rennes, Bretagne, 3500 | D91: 14 avr. 2026 10:08 | E91: 14 avr. 2026 10:00 | F91: off | G91: 65 | I91: EF-550-HR | J91: TG Rennes (PF) | K91: true | L91: RENAULT | M91: D | N91: 2016 | O91: VF640J568GB004776 | P91: Truck | Q91: =IFERROR(_xlfn.XLOOKUP(B91,'boitiers actifs'!C:C,'boitiers actifs'!A:A),"Pas installé") -> EF-550-HR | R91: =IF(Q91 = "Pas installé", "Pas installé", IF( Q91<>A91, "Différent du véhicule assigné", "Identique")) -> Identique | S91: =IF(B91 = "", "", VLOOKUP(B91, Commandes!D:G, 4, FALSE)) -> oui
A92: ES-665-HN | B92: GJ9X-GVD-F9Z | C92: Pacé, Bretagne, 35740 | D92: 14 avr. 2026 10:08 | E92: 10 avr. 2026 12:04 | F92: off | G92: - | I92: ES-665-HN | J92: TG Ouest | K92: true | L92: RENAULT | M92: D | N92: 2018 | O92: VF640J565JB007836 | P92: Truck | Q92: =IFERROR(_xlfn.XLOOKUP(B92,'boitiers actifs'!C:C,'boitiers actifs'!A:A),"Pas installé") -> ES-665-HN | R92: =IF(Q92 = "Pas installé", "Pas installé", IF( Q92<>A92, "Différent du véhicule assigné", "Identique")) -> Identique | S92: =IF(B92 = "", "", VLOOKUP(B92, Commandes!D:G, 4, FALSE)) -> oui
A93: CD-674-AR | B93: GWCA-WAZ-AT2 | C93: Carquefou, Pays de la Loire, 44470 | D93: 14 avr. 2026 10:08 | E93: 14 avr. 2026 09:49 | F93: off | G93: - | I93: CD-674-AR | J93: TG Ouest | K93: true | L93: RENAULT | M93: PREMIUM | N93: 2012 | O93: VF624GPA000057318 | P93: Truck | Q93: =IFERROR(_xlfn.XLOOKUP(B93,'boitiers actifs'!C:C,'boitiers actifs'!A:A),"Pas installé") -> CD-674-AR | R93: =IF(Q93 = "Pas installé", "Pas installé", IF( Q93<>A93, "Différent du véhicule assigné", "Identique")) -> Identique | S93: =IF(B93 = "", "", VLOOKUP(B93, Commandes!D:G, 4, FALSE)) -> oui
A94: DX-818-HY | C94: Carquefou, Pays de la Loire, 44470 | D94: 23 sept. 2025 16:21 | E94: 17 sept. 2025 08:15 | F94: off | G94: 86 | I94: DX-818-HY | J94: TG Ouest | K94: true | L94: VOLVO | M94: FL | N94: 2015 | O94: YV2T0X1A9FZ103750 | P94: Truck | Q94: =IFERROR(_xlfn.XLOOKUP(B94,'boitiers actifs'!C:C,'boitiers actifs'!A:A),"Pas installé") -> Pas installé | R94: =IF(Q94 = "Pas installé", "Pas installé", IF( Q94<>A94, "Différent du véhicule assigné", "Identique")) -> Pas installé | S94: =IF(B94 = "", "", VLOOKUP(B94, Commandes!D:G, 4, FALSE))
A95: CR-717-GD | C95: Valenton, Île-de-France, 94460 | D95: 12 nov. 2024 14:33 | E95: 8 nov. 2024 17:15 | F95: off | G95: - | I95: CR-717-GD | J95: TG IDF VALENTON | K95: true | L95: RENAULT | M95: MIDLUM | N95: 2013 | O95: VF644AGL000006841 | Q95: =IFERROR(_xlfn.XLOOKUP(B95,'boitiers actifs'!C:C,'boitiers actifs'!A:A),"Pas installé") -> Pas installé | R95: =IF(Q95 = "Pas installé", "Pas installé", IF( Q95<>A95, "Différent du véhicule assigné", "Identique")) -> Pas installé | S95: =IF(B95 = "", "", VLOOKUP(B95, Commandes!D:G, 4, FALSE))
A96: DT-858-QB | B96: GK5F-XFB-WJE | C96: Villeneuve-sur-Lot, Nouvelle-Aquitaine, 47300 | D96: 14 avr. 2026 10:08 | E96: 1 avr. 2026 04:24 | F96: off | G96: 93 | I96: DT-858-QB | J96: TG Villeneuve sur Lot (PF) | K96: true | L96: RENAULT | M96: D WIDE | N96: 2015 | O96: VF620J866FB001196 | P96: Truck | Q96: =IFERROR(_xlfn.XLOOKUP(B96,'boitiers actifs'!C:C,'boitiers actifs'!A:A),"Pas installé") -> DT-858-QB | R96: =IF(Q96 = "Pas installé", "Pas installé", IF( Q96<>A96, "Différent du véhicule assigné", "Identique")) -> Identique | S96: =IF(B96 = "", "", VLOOKUP(B96, Commandes!D:G, 4, FALSE)) -> oui
A97: GK-174-SZ | B97: GD2A-ZR3-UW4 | C97: Artigues-près-Bordeaux, Nouvelle-Aquitaine, 33370 | D97: 14 avr. 2026 10:08 | E97: 9 avr. 2026 15:04 | F97: off | G97: 37 | I97: GK-174-SZ | J97: Site St Loubes, TG AQUITAINE | K97: true | L97: RENAULT | M97: D WIDE | N97: 2022 | O97: VF620J960NB000543 | P97: Truck | Q97: =IFERROR(_xlfn.XLOOKUP(B97,'boitiers actifs'!C:C,'boitiers actifs'!A:A),"Pas installé") -> GK-174-SZ | R97: =IF(Q97 = "Pas installé", "Pas installé", IF( Q97<>A97, "Différent du véhicule assigné", "Identique")) -> Identique | S97: =IF(B97 = "", "", VLOOKUP(B97, Commandes!D:G, 4, FALSE)) -> oui
A98: FT-777-DD | B98: GNFG-6M6-H67 | C98: Villecresnes, Île-de-France, 94440 | D98: 14 avr. 2026 10:08 | E98: 13 avr. 2026 14:14 | F98: off | G98: 63 | I98: FT-777-DD | J98: TG IDF VALENTON | K98: true | L98: RENAULT | M98: D WIDE | N98: 2020 | O98: VF620J867LB008170 | P98: Truck | Q98: =IFERROR(_xlfn.XLOOKUP(B98,'boitiers actifs'!C:C,'boitiers actifs'!A:A),"Pas installé") -> FT-777-DD | R98: =IF(Q98 = "Pas installé", "Pas installé", IF( Q98<>A98, "Différent du véhicule assigné", "Identique")) -> Identique | S98: =IF(B98 = "", "", VLOOKUP(B98, Commandes!D:G, 4, FALSE)) -> oui
A99: FT-906-HJ | B99: GRRX-9GK-W4S | C99: Créteil, Île-de-France, 94000 | D99: 14 avr. 2026 10:08 | E99: 14 avr. 2026 09:34 | F99: off | G99: 64 | H99: CISSE DJIBRIL | I99: FT-906-HJ | J99: TG IDF VALENTON | K99: true | L99: RENAULT | M99: D WIDE | N99: 2020 | O99: VF620J869LB008154 | P99: Truck | Q99: =IFERROR(_xlfn.XLOOKUP(B99,'boitiers actifs'!C:C,'boitiers actifs'!A:A),"Pas installé") -> FT-906-HJ | R99: =IF(Q99 = "Pas installé", "Pas installé", IF( Q99<>A99, "Différent du véhicule assigné", "Identique")) -> Identique | S99: =IF(B99 = "", "", VLOOKUP(B99, Commandes!D:G, 4, FALSE)) -> oui
A100: FT-035-HK | B100: G9W2-A82-5RB | C100: Saint-Denis, Île-de-France, 93210 | D100: 14 avr. 2026 10:08 | E100: On trip | F100: on | G100: 74 | H100: AFONSO Jessy | I100: FT-035-HK | J100: TG IDF VALENTON | K100: true | L100: RENAULT | M100: D WIDE | N100: 2020 | O100: VF620J865LB008121 | P100: Truck | Q100: =IFERROR(_xlfn.XLOOKUP(B100,'boitiers actifs'!C:C,'boitiers actifs'!A:A),"Pas installé") -> FT-035-HK | R100: =IF(Q100 = "Pas installé", "Pas installé", IF( Q100<>A100, "Différent du véhicule assigné", "Identique")) -> Identique | S100: =IF(B100 = "", "", VLOOKUP(B100, Commandes!D:G, 4, FALSE)) -> oui
...

Sheet Véhicules Samsara non équipés
A1: Last Connected | B1: (Plusieurs éléments)
A2: Différents | B2: Pas installé
A4: Site | B4: Nombre de véhicules non équipé
A5: EUR Schiltigheim LIV
A6: ED-783-HE | B6: 1
A7: Site Bonneville
A8: EZ-838-EL | B8: 1
A9: Site St Loubes, TEST TEMPERATURE , TG AQUITAINE
A10: GL-338-WD | B10: 1
A11: GX-879-NT | B11: 1
A12: HA-458-ZM | B12: 1
A13: HA-582-GC | B13: 1
A14: Site St Loubes, TG AQUITAINE
A15: FD-972-ZS | B15: 1
A16: TG Arques, TG NORD
A17: EV-563-PW | B17: 1
A18: EV-575-PW | B18: 1
A19: FQ-575-KG | B19: 1
A20: TG BOURGOGNE
A21: EF-734-XN | B21: 1
A22: EQ-229-KN | B22: 1
A23: TG CENTRE EST
A24: DW-773-YG | B24: 1
A25: TG CENTRE OUEST
A26: DX-801-EY | B26: 1
A27: DX-836-BJ | B27: 1
A28: TG COULOMMIERS
A29: HH-714-FQ | B29: 1
A30: TG IDF VALENTON
A31: DV-919-PS | B31: 1
A32: EE-280-ZV | B32: 1
A33: FB-980-TY | B33: 1
A34: FF-956-RQ | B34: 1
A35: FG-129-HR | B35: 1
A36: FG-725-GA | B36: 1
A37: TG Le Muy (PF)
A38: DH-914-WC | B38: 1
A39: EF-068-CH | B39: 1
A40: FN-765-KB | B40: 1
A41: GW-007-FJ | B41: 1
A42: TG MEDITERRANEE
A43: DX-379-MX | B43: 1
A44: DX-383-MX | B44: 1
A45: DY-245-TB | B45: 1
A46: EA-696-LD | B46: 1
A47: GY-826-PE | B47: 1
A48: GZ-701-SV | B48: 1
A49: TG RHONE
A50: GN-061-RE | B50: 1
A51: GP-188-ZF | B51: 1
A52: TGFL-DELTA LOGISTIQUE
A53: ER-722-WS | B53: 1
A54: ES-780-LG | B54: 1
A55: Total général | B55: 36

Sheet Parc Avril
A1: Etablissement opérationnel | B1: Famille | C1: Parc | D1: Code parc interne | E1: Immatriculation | F1: Sous-famille | G1: Segment | H1: Marque | I1: Modèle | J1: Version | K1: Date de mise en service | L1: Date d'entrée | M1: Date de retrait | N1: Mode d'acquisition | O1: Fournisseur | P1: Conducteur | Q1: Dernier index compteur connu | R1: Date dernier index connu | S1: Libellé statut | T1: N° de série | U1: P.T.A.C | V1: Energie | W1: CO2 | X1: Puissance fiscale | Y1: Catégorie du véhicule (CE) | Z1: Boitier
A2: COFIDA I4 | B2: VP | C2: SITE RUNGIS I4 | D2: GR108DK | E2: GR-108-DK | F2: Berline | G2: 2 | H2: RENAULT | I2: CLIO 5 EVOLUTION | J2: TCE 90 | K2: 12/09/2023 | L2: 21/09/2023 17:30 | N2: Achat neuf | O2: TRANSGOURMET | P2: LOUYEBO THEMARK | Q2: 50461 | R2: 11/12/2025 12:41 | S2: En exploitation | T2: VF1RJA00371030784 | U2: 1595 | V2: Essence | W2: 120 | X2: 5 | Y2: M1 | Z2: =_xlfn.XLOOKUP(E2, Commandes!F:F, Commandes!D:D) -> #N/A
A3: COFIDA I4 | B3: VP | C3: SITE RUNGIS I4 | D3: GR783XM | E3: GR-783-XM | F3: Berline | G3: 4 | H3: CITROEN | I3: C4 | J3: PureTech 130 S&S EAT8 Shine | K3: 19/10/2023 | L3: 25/10/2023 10:30 | N3: Achat neuf | O3: TRANSGOURMET | P3: DUHAMEL ELISE | Q3: 40129 | R3: 23/02/2026 11:58 | S3: En exploitation | T3: VR7BAHNSBPE067192 | U3: 1755 | V3: Essence | W3: 130 | X3: 7 | Y3: M1 | Z3: =_xlfn.XLOOKUP(E3, Commandes!F:F, Commandes!D:D) -> #N/A
A4: COFIDA I4 | B4: VP | C4: SITE RUNGIS I4 | D4: GW494NK | E4: GW-494-NK | F4: SUV | G4: 3 | H4: RENAULT | I4: CAPTUR | J4: EVO E-Tech Full hybride 145ch non rechargeable | K4: 23/04/2024 | L4: 29/05/2024 09:40 | N4: Achat neuf | O4: TRANSGOURMET | P4: BENAMARI DRISS | Q4: 35330 | R4: 04/03/2026 05:56 | S4: En exploitation | T4: VF1RJB00472787340 | U4: 1896 | V4: Electricité + essence | W4: 110 | X4: 5 | Y4: M1 | Z4: =_xlfn.XLOOKUP(E4, Commandes!F:F, Commandes!D:D) -> #N/A
A5: COFIDA I4 | B5: VUL | C5: SITE RUNGIS I4 | D5: GN240VQ | E5: GN-240-VQ | F5: 3T5 | G5: 3T5 | H5: RENAULT TRUCKS | I5: MASTER ZE | K5: 09/05/2023 | L5: 02/06/2023 00:00 | N5: Location longue durée | O5: PETIT FORESTIER | Q5: 0 | R5: 08/05/2023 00:00 | S5: En exploitation | T5: VF1VAE0D269573310 | U5: 3500 | V5: Electricité | W5: 0 | X5: 7 | Y5: N1 | Z5: =_xlfn.XLOOKUP(E5, Commandes!F:F, Commandes!D:D) -> GFPW-3PW-5YA
A6: COFIDA I4 | B6: VUL | C6: SITE RUNGIS I4 | D6: GN362SL | E6: GN-362-SL | F6: 3T5 | G6: 3T5 | H6: IVECO | I6: 35C14 | K6: 03/05/2023 | L6: 23/05/2023 00:00 | N6: Location Moyenne Durée | O6: PETIT FORESTIER | P6: GUEMERT JULIE | Q6: 80667 | R6: 13/03/2026 07:57 | S6: En exploitation | T6: ZCFCP35A00D731752 | U6: 3500 | V6: Gazole | W6: 0 | X6: 8 | Y6: N1 | Z6: =_xlfn.XLOOKUP(E6, Commandes!F:F, Commandes!D:D) -> G3HK-3TK-ZVW
A7: COFIDA I4 | B7: VUL | C7: SITE RUNGIS I4 | D7: GP228DA | E7: GP-228-DA | F7: 3T5 | G7: 3T5 | H7: IVECO | I7: 35C14 | K7: 26/05/2023 | L7: 19/06/2023 00:00 | N7: Location Moyenne Durée | O7: PETIT FORESTIER | P7: FERIAUX WILLY ANGELO | Q7: 57220 | R7: 09/03/2026 06:30 | S7: En exploitation | T7: ZCFCP35A90D731751 | U7: 3500 | V7: Gazole | W7: 0 | X7: 8 | Y7: N1 | Z7: =_xlfn.XLOOKUP(E7, Commandes!F:F, Commandes!D:D) -> GXNC-PUY-8M5
A8: COFIDA I4 | B8: VUL | C8: SITE RUNGIS I4 | D8: GP454SE | E8: GP-454-SE | F8: 3T5 | G8: 3T5 | H8: IVECO | I8: 35C14 | K8: 22/06/2023 | L8: 03/11/2023 00:00 | N8: Location Moyenne Durée | O8: PETIT FORESTIER | P8: FERNANDES DE ANDRADE NELSON | Q8: 145894 | R8: 13/03/2026 16:17 | S8: En exploitation | T8: ZCFCP35A70D731750 | U8: 3500 | V8: Gazole | W8: 0 | X8: 8 | Y8: N1 | Z8: =_xlfn.XLOOKUP(E8, Commandes!F:F, Commandes!D:D) -> G9J6-69Z-4JA
A9: COFIDA I4 | B9: VUL | C9: SITE RUNGIS I4 | D9: GR790RH | E9: GR-790-RH | F9: 3T5 | G9: 3T5 | H9: IVECO | I9: 35C14 | K9: 06/10/2023 | L9: 13/10/2023 00:00 | N9: Location Moyenne Durée | O9: PETIT FORESTIER | P9: LOUYEBO THEMARK | Q9: 34742 | R9: 10/03/2026 06:28 | S9: En exploitation | T9: ZCFCP35A40D731429 | U9: 3500 | V9: Gazole | W9: 0 | X9: 8 | Y9: N1 | Z9: =_xlfn.XLOOKUP(E9, Commandes!F:F, Commandes!D:D) -> GZF5-DXA-C5R
A10: DELTA | B10: PL | C10: SITE RUNGIS DELTA | D10: ER615WS | E10: ER-615-WS | F10: 16T | G10: 16T | H10: DAF | I10: LF | J10: LF260FA | K10: 07/11/2017 | L10: 13/11/2017 00:00 | N10: Achat neuf | O10: TRANSGOURMET | P10: OUTALHA ADIL | Q10: 220000 | R10: 27/01/2026 11:28 | S10: En exploitation | T10: XLRAEL2700L467300 | U10: 15500 | V10: Gazole | W10: 0 | X10: 18 | Z10: =_xlfn.XLOOKUP(E10, Commandes!F:F, Commandes!D:D) -> GKNK-STC-P6N
A11: DELTA | B11: PL | C11: SITE RUNGIS DELTA | D11: ES187AG | E11: ES-187-AG | F11: 16T | G11: 16T | H11: DAF | I11: LF | J11: LF260FA | K11: 15/11/2017 | L11: 22/11/2017 00:00 | N11: Achat neuf | O11: TRANSGOURMET | P11: NIAKATE CHEICKNA | Q11: 207127 | R11: 13/01/2026 10:23 | S11: En exploitation | T11: XLRAEL2700L467407 | U11: 15500 | V11: Gazole | W11: 0 | X11: 18 | Y11: N3 | Z11: =_xlfn.XLOOKUP(E11, Commandes!F:F, Commandes!D:D) -> GBDU-JEZ-4UX
A12: DELTA | B12: PL | C12: SITE RUNGIS DELTA | D12: ES885LG | E12: ES-885-LG | F12: 16T | G12: 16T | H12: DAF | I12: LF | J12: LF260FA | K12: 28/11/2017 | L12: 08/12/2017 00:00 | N12: Achat neuf | O12: TRANSGOURMET | P12: BELHOUAS AMAR | Q12: 96700 | R12: 22/12/2025 11:08 | S12: En exploitation | T12: XLRAEL2700L468485 | U12: 15500 | V12: Gazole | W12: 0 | X12: 18 | Z12: =_xlfn.XLOOKUP(E12, Commandes!F:F, Commandes!D:D) -> GM7A-K79-JR3
A13: DELTA | B13: PL | C13: SITE RUNGIS DELTA | D13: HH154WC | E13: HH-154-WC | F13: 16T | G13: 16T | H13: RENAULT TRUCKS | I13: D16WIDE | J13: 320 E6 DTI 8 B 100 FLEXIBLE | K13: 25/01/2026 | L13: 25/01/2026 11:30 | N13: Achat neuf | O13: TRANSGOURMET | Q13: 0 | R13: 24/01/2026 11:30 | S13: En exploitation | T13: VF620J865TB016042 | U13: 16000 | V13: Gazole | W13: 0 | X13: 21 | Y13: N3 | Z13: =_xlfn.XLOOKUP(E13, Commandes!F:F, Commandes!D:D) -> GWCD-4VB-NCB
A14: DELTA | B14: PL | C14: SITE RUNGIS DELTA | D14: HH360WP | E14: HH-360-WP | F14: 16T | G14: 16T | H14: RENAULT TRUCKS | I14: D16WIDE | J14: 320 E6 DTI 8 B 100 FLEXIBLE | K14: 27/01/2026 | L14: 25/01/2026 11:30 | N14: Achat neuf | O14: TRANSGOURMET | Q14: 4742 | R14: 11/03/2026 08:41 | S14: En exploitation | T14: VF620J861TB016068 | U14: 16000 | V14: Gazole | W14: 0 | X14: 21 | Y14: N3 | Z14: =_xlfn.XLOOKUP(E14, Commandes!F:F, Commandes!D:D) -> GP47-ZJJ-AV2
A15: DELTA | B15: PL | C15: SITE RUNGIS DELTA | D15: HH409TF | E15: HH-409-TF | F15: 16T | G15: 16T | H15: RENAULT TRUCKS | I15: D16WIDE | J15: 320 E6 DTI 8 B 100 FLEXIBLE | K15: 20/01/2026 | L15: 23/01/2026 11:00 | N15: Achat neuf | O15: TRANSGOURMET | Q15: 0 | R15: 19/01/2026 00:00 | S15: En exploitation | T15: VF620J862TB015978 | U15: 16000 | V15: Gazole | W15: 0 | X15: 21 | Y15: N3 | Z15: =_xlfn.XLOOKUP(E15, Commandes!F:F, Commandes!D:D) -> GN3M-WG9-6UR
A16: DELTA | B16: PL | C16: SITE RUNGIS DELTA | D16: HH487TF | E16: HH-487-TF | F16: 16T | G16: 16T | H16: RENAULT TRUCKS | I16: D16WIDE | J16: 320 E6 DTI 8 B 100 FLEXIBLE | K16: 20/01/2026 | L16: 23/01/2026 11:00 | N16: Achat neuf | O16: TRANSGOURMET | Q16: 0 | R16: 19/01/2026 00:00 | S16: En exploitation | T16: VF620J867TB016043 | U16: 16000 | V16: Gazole | W16: 0 | X16: 21 | Y16: N3 | Z16: =_xlfn.XLOOKUP(E16, Commandes!F:F, Commandes!D:D) -> GS8F-X9W-YA7
A17: DELTA | B17: PL | C17: SITE RUNGIS DELTA | D17: HH602PG | E17: HH-602-PG | F17: 16T | G17: 16T | H17: RENAULT TRUCKS | I17: D16WIDE | J17: 320 E6 DTI 8 B 100 FLEXIBLE | K17: 06/01/2026 | L17: 12/01/2026 11:40 | N17: Achat neuf | O17: TRANSGOURMET | Q17: 0 | R17: 05/01/2026 00:00 | S17: En exploitation | T17: VF620J868TB016021 | U17: 16000 | V17: Gazole | W17: 0 | X17: 21 | Y17: N3 | Z17: =_xlfn.XLOOKUP(E17, Commandes!F:F, Commandes!D:D) -> GKBH-EG3-4FY
A18: DELTA | B18: PL | C18: SITE RUNGIS DELTA | D18: HH750PG | E18: HH-750-PG | F18: 16T | G18: 16T | H18: RENAULT TRUCKS | I18: D16WIDE | J18: 320 E6 DTI 8 B 100 FLEXIBLE | K18: 06/01/2026 | L18: 12/01/2026 11:40 | N18: Achat neuf | O18: TRANSGOURMET | Q18: 0 | R18: 05/01/2026 00:00 | S18: En exploitation | T18: VF620J866TB016020 | U18: 16000 | V18: Gazole | W18: 0 | X18: 21 | Y18: N3 | Z18: =_xlfn.XLOOKUP(E18, Commandes!F:F, Commandes!D:D) -> GJZR-G8U-YTB
A19: DELTA | B19: PL | C19: SITE RUNGIS DELTA | D19: HJ129GS | E19: HJ-129-GS | F19: 16T | G19: 16T | H19: RENAULT TRUCKS | I19: D16WIDE | J19: 320 E6 DTI 8 B 100 FLEXIBLE | K19: 23/02/2026 | L19: 27/02/2026 15:30 | N19: Achat neuf | O19: TRANSGOURMET | Q19: 0 | R19: 27/02/2026 15:30 | S19: En exploitation | T19: VF620J865TB016039 | U19: 16000 | V19: Gazole | W19: 0 | X19: 21 | Y19: N3 | Z19: =_xlfn.XLOOKUP(E19, Commandes!F:F, Commandes!D:D) -> GWJM-UC2-CPC
A20: DELTA | B20: PL | C20: SITE RUNGIS DELTA | D20: HJ749AY | E20: HJ-749-AY | F20: 16T | G20: 16T | H20: RENAULT TRUCKS | I20: D16WIDE | J20: 320 E6 DTI 8 B 100 FLEXIBLE | K20: 05/02/2026 | L20: 11/02/2026 12:03 | N20: Achat neuf | O20: TRANSGOURMET | Q20: 0 | R20: 04/02/2026 00:00 | S20: En exploitation | T20: VF620J863TB016038 | U20: 16000 | V20: Gazole | W20: 0 | X20: 21 | Y20: N3 | Z20: =_xlfn.XLOOKUP(E20, Commandes!F:F, Commandes!D:D) -> GVX2-ASW-XPS
A21: DELTA | B21: SREM | C21: SITE RUNGIS DELTA | D21: EF736XP | E21: EF-736-XP | F21: S38T | G21: S38T | H21: LAMBERET | K21: 08/02/2024 | L21: 27/09/2024 08:00 | N21: Location Moyenne Durée | O21: FRAIKIN | Q21: 0 | R21: 17/10/2019 00:00 | S21: En exploitation | T21: VM3LVFS3FG1R31689 | U21: 38000 | W21: 0 | X21: 0 | Y21: O4 | Z21: =_xlfn.XLOOKUP(E21, Commandes!F:F, Commandes!D:D) -> #N/A
A22: DELTA | B22: SREM | C22: SITE RUNGIS DELTA | D22: GV246AT | E22: GV-246-AT | F22: S38T | G22: S38T | H22: FRAPPA | K22: 08/02/2024 | L22: 27/09/2024 08:00 | N22: Location longue durée | O22: FRAIKIN | Q22: 0 | R22: 17/10/2019 00:00 | S22: En exploitation | T22: VPRS43KBFPF001009 | U22: 38000 | W22: 0 | X22: 0 | Y22: O4 | Z22: =_xlfn.XLOOKUP(E22, Commandes!F:F, Commandes!D:D) -> #N/A
A23: DELTA | B23: TRR | C23: SITE RUNGIS DELTA | D23: HG567EE | E23: HG-567-EE | F23: 44T | G23: 44T | H23: RENAULT TRUCKS | I23: T | K23: 21/10/2025 | L23: 01/12/2025 08:00 | N23: Location longue durée | O23: FRAIKIN | Q23: 2563 | R23: 30/01/2026 19:12 | S23: En exploitation | T23: VF611A369TD059108 | U23: 19000 | V23: Gazole | W23: 0 | X23: 34 | Y23: N3 | Z23: =_xlfn.XLOOKUP(E23, Commandes!F:F, Commandes!D:D) -> GMB9-GFK-RYY
A24: DELTA | B24: VP | C24: SITE RUNGIS DELTA | D24: FP874PX | E24: FP-874-PX | F24: Monospace | G24: 4 | H24: RENAULT | I24: SCENIC | J24: Business Blue Dci 120 EDC | K24: 23/04/2020 | L24: 01/12/2020 10:40 | N24: Achat neuf | O24: TRANSGOURMET | P24: SIMOES HELENE | Q24: 110215 | R24: 17/02/2026 00:00 | S24: En exploitation | T24: VF1RFA00464246609 | U24: 2199 | V24: Gazole | W24: 157 | X24: 6 | Y24: M1 | Z24: =_xlfn.XLOOKUP(E24, Commandes!F:F, Commandes!D:D) -> #N/A
A25: DELTA | B25: VP | C25: SITE RUNGIS DELTA | D25: GN414RH | E25: GN-414-RH | F25: SUV | G25: 5 | H25: PEUGEOT | I25: 3008 | J25: ALLURE PACK HYBRID 225 e-EAT8 | K25: 28/07/2023 | L25: 24/10/2023 10:58 | N25: Achat neuf | O25: TRANSGOURMET | P25: ERRAHAB NADIA | Q25: 29156 | R25: 02/03/2026 16:53 | S25: En exploitation | T25: VF3M4DGZUPS045538 | U25: 2290 | V25: Electricité + essence rechargeable | W25: 28 | X25: 10 | Y25: M1 | Z25: =_xlfn.XLOOKUP(E25, Commandes!F:F, Commandes!D:D) -> #N/A
A26: DELTA | B26: VP | C26: SITE RUNGIS DELTA | D26: GP094CP | E26: GP-094-CP | F26: Berline | G26: 4 | H26: CITROEN | I26: C4 | J26: PureTech 130 S&S EAT8 Shine | K26: 25/05/2023 | L26: 02/06/2023 09:35 | N26: Achat neuf | O26: TRANSGOURMET | Q26: 39580 | R26: 24/03/2026 00:00 | S26: En exploitation | T26: VR7BAHNSBPE010767 | U26: 1755 | V26: Essence | W26: 130 | X26: 7 | Y26: M1 | Z26: =_xlfn.XLOOKUP(E26, Commandes!F:F, Commandes!D:D) -> #N/A
A27: DELTA | B27: VP | C27: SITE RUNGIS DELTA | D27: GQ318SE | E27: GQ-318-SE | F27: Berline | G27: 2 | H27: RENAULT | I27: CLIO 5 EVOLUTION | J27: TCE 90 | K27: 14/08/2023 | L27: 29/08/2023 14:20 | N27: Achat neuf | O27: TRANSGOURMET | P27: FARRUGIA PAUL MICHEL | Q27: 60700 | R27: 11/03/2026 18:21 | S27: En exploitation | T27: VF1RJA00971030742 | U27: 1595 | V27: Essence | W27: 120 | X27: 5 | Y27: M1 | Z27: =_xlfn.XLOOKUP(E27, Commandes!F:F, Commandes!D:D) -> #N/A
A28: DELTA | B28: VP | C28: SITE RUNGIS DELTA | D28: GQ324SE | E28: GQ-324-SE | F28: Berline | G28: 2 | H28: RENAULT | I28: CLIO 5 EVOLUTION | J28: TCE 90 | K28: 14/08/2023 | L28: 29/08/2023 14:20 | N28: Achat neuf | O28: TRANSGOURMET | P28: HADJAZ HAMID | Q28: 105949 | R28: 14/03/2026 10:50 | S28: En exploitation | T28: VF1RJA00171030766 | U28: 1595 | V28: Essence | W28: 120 | X28: 5 | Y28: M1 | Z28: =_xlfn.XLOOKUP(E28, Commandes!F:F, Commandes!D:D) -> #N/A
A29: DELTA | B29: VP | C29: SITE RUNGIS DELTA | D29: GQ332SE | E29: GQ-332-SE | F29: Berline | G29: 2 | H29: RENAULT | I29: CLIO 5 EVOLUTION | J29: TCE 90 | K29: 14/08/2023 | L29: 29/08/2023 14:20 | N29: Achat neuf | O29: TRANSGOURMET | P29: BERTIN SEBASTIEN | Q29: 49242 | R29: 12/03/2026 14:20 | S29: En exploitation | T29: VF1RJA00671030651 | U29: 1595 | V29: Essence | W29: 120 | X29: 5 | Y29: M1 | Z29: =_xlfn.XLOOKUP(E29, Commandes!F:F, Commandes!D:D) -> #N/A
A30: DELTA | B30: VP | C30: SITE RUNGIS DELTA | D30: GQ335SE | E30: GQ-335-SE | F30: Berline | G30: 2 | H30: RENAULT | I30: CLIO 5 EVOLUTION | J30: TCE 90 | K30: 14/08/2023 | L30: 29/08/2023 14:20 | N30: Achat neuf | O30: TRANSGOURMET | P30: JOUIN AXELLE | Q30: 55460 | R30: 07/03/2026 11:52 | S30: En exploitation | T30: VF1RJA00971030790 | U30: 1595 | V30: Essence | W30: 120 | X30: 5 | Y30: M1 | Z30: =_xlfn.XLOOKUP(E30, Commandes!F:F, Commandes!D:D) -> #N/A
A31: DELTA | B31: VP | C31: SITE RUNGIS DELTA | D31: GQ339SE | E31: GQ-339-SE | F31: Berline | G31: 2 | H31: RENAULT | I31: CLIO 5 EVOLUTION | J31: TCE 90 | K31: 14/08/2023 | L31: 29/08/2023 14:20 | N31: Achat neuf | O31: TRANSGOURMET | P31: WANCAUWENBERGHE CECILE | Q31: 23827 | R31: 07/03/2026 08:19 | S31: En exploitation | T31: VF1RJA0047130714 | U31: 1595 | V31: Essence | W31: 120 | X31: 5 | Y31: M1 | Z31: =_xlfn.XLOOKUP(E31, Commandes!F:F, Commandes!D:D) -> #N/A
A32: DELTA | B32: VP | C32: SITE RUNGIS DELTA | D32: GR036XL | E32: GR-036-XL | F32: SUV | G32: 5 | H32: PEUGEOT | I32: 3008 | J32: ALLURE PACK HYBRID 225 e-EAT8 | K32: 19/10/2023 | L32: 26/10/2023 10:42 | N32: Achat neuf | O32: TRANSGOURMET | Q32: 55800 | R32: 27/10/2025 16:16 | S32: En exploitation | T32: VF3M4DGZUPS126043 | U32: 2290 | V32: Electricité + essence rechargeable | W32: 28 | X32: 10 | Y32: M1 | Z32: =_xlfn.XLOOKUP(E32, Commandes!F:F, Commandes!D:D) -> #N/A
A33: DELTA | B33: VP | C33: SITE RUNGIS DELTA | D33: GR179DK | E33: GR-179-DK | F33: Berline | G33: 2 | H33: RENAULT | I33: CLIO 5 EVOLUTION | J33: TCE 90 | K33: 12/09/2023 | L33: 21/09/2023 17:30 | N33: Achat neuf | O33: TRANSGOURMET | P33: RENOUARD NICOLAS | Q33: 42520 | R33: 04/03/2026 08:23 | S33: En exploitation | T33: VF1RJA00X71030796 | U33: 1595 | V33: Essence | W33: 120 | X33: 5 | Y33: M1 | Z33: =_xlfn.XLOOKUP(E33, Commandes!F:F, Commandes!D:D) -> #N/A
A34: DELTA | B34: VP | C34: SITE RUNGIS DELTA | D34: GR516NZ | E34: GR-516-NZ | F34: Break | G34: 4 | H34: PEUGEOT | I34: 308 SW | J34: ACTIVE PACK Pure tech 130 EAT8 | K34: 29/09/2023 | L34: 06/11/2023 10:25 | N34: Achat neuf | O34: TRANSGOURMET | P34: LEFRERE SEBASTIEN | Q34: 41865 | R34: 09/03/2026 10:50 | S34: En exploitation | T34: VR3FRHNSTPY620142 | U34: 1860 | V34: Essence | W34: 128 | X34: 7 | Y34: M1 | Z34: =_xlfn.XLOOKUP(E34, Commandes!F:F, Commandes!D:D) -> #N/A
A35: DELTA | B35: VP | C35: SITE RUNGIS DELTA | D35: GR532SW | E35: GR-532-SW | F35: Berline | G35: 2 | H35: RENAULT | I35: CLIO 5 EVOLUTION | J35: TCE 90 | K35: 10/10/2023 | L35: 19/10/2023 08:30 | N35: Achat neuf | O35: TRANSGOURMET | P35: AUBERT CELINE | Q35: 76961 | R35: 13/03/2026 20:23 | S35: En exploitation | T35: VF1RJA00671030704 | U35: 1595 | V35: Essence | W35: 120 | X35: 5 | Y35: M1 | Z35: =_xlfn.XLOOKUP(E35, Commandes!F:F, Commandes!D:D) -> #N/A
A36: DELTA | B36: VP | C36: SITE RUNGIS DELTA | D36: GR696TB | E36: GR-696-TB | F36: Berline | G36: 2 | H36: RENAULT | I36: CLIO 5 EVOLUTION | J36: TCE 90 | K36: 11/10/2023 | L36: 19/10/2023 08:30 | N36: Achat neuf | O36: TRANSGOURMET | P36: KARROUCHI KARIM | Q36: 34588 | R36: 13/03/2026 13:01 | S36: En exploitation | T36: VF1RJA00471030809 | U36: 1595 | V36: Essence | W36: 120 | X36: 5 | Y36: M1 | Z36: =_xlfn.XLOOKUP(E36, Commandes!F:F, Commandes!D:D) -> #N/A
A37: DELTA | B37: VP | C37: SITE RUNGIS DELTA | D37: GR840TB | E37: GR-840-TB | F37: Berline | G37: 2 | H37: RENAULT | I37: CLIO 5 EVOLUTION | J37: TCE 90 | K37: 11/10/2023 | L37: 19/10/2023 08:30 | N37: Achat neuf | O37: TRANSGOURMET | P37: BOUDJEMA ENZO | Q37: 70345 | R37: 11/03/2026 19:38 | S37: En exploitation | T37: VF1RJA00071030659 | U37: 1595 | V37: Essence | W37: 120 | X37: 5 | Y37: M1 | Z37: =_xlfn.XLOOKUP(E37, Commandes!F:F, Commandes!D:D) -> #N/A
A38: DELTA | B38: VP | C38: SITE RUNGIS DELTA | D38: GR877DK | E38: GR-877-DK | F38: Berline | G38: 2 | H38: RENAULT | I38: CLIO 5 EVOLUTION | J38: TCE 90 | K38: 12/09/2023 | L38: 21/09/2023 17:30 | N38: Achat neuf | O38: TRANSGOURMET | P38: BERTIN SEBASTIEN | Q38: 32892 | R38: 05/03/2026 13:47 | S38: En exploitation | T38: VF1RJA00171030637 | U38: 1595 | V38: Essence | W38: 120 | X38: 5 | Y38: M1 | Z38: =_xlfn.XLOOKUP(E38, Commandes!F:F, Commandes!D:D) -> #N/A
A39: DELTA | B39: VP | C39: SITE RUNGIS DELTA | D39: GT137YN | E39: GT-137-YN | F39: SUV | G39: Cat 6 (DR) | H39: VOLVO | I39: XC60 | J39: T8 AWD | K39: 01/02/2024 | L39: 02/02/2024 00:00 | N39: Achat neuf | O39: TRANSGOURMET | P39: WAGNER BENJAMIN | Q39: 2890 | R39: 12/03/2024 14:39 | S39: En exploitation | T39: YV1UZH7VOR1884269 | U39: 2660 | V39: Electricité + essence rechargeable | W39: 25 | X39: 20 | Y39: M1G | Z39: =_xlfn.XLOOKUP(E39, Commandes!F:F, Commandes!D:D) -> #N/A
A40: DELTA | B40: VP | C40: SITE RUNGIS DELTA | D40: GV505LQ | E40: GV-505-LQ | F40: SUV | G40: 5 | H40: PEUGEOT | I40: 3008 | J40: ACTIVE PACK hybride 136e-DCs6 | K40: 29/02/2024 | L40: 18/03/2024 00:00 | N40: Achat neuf | O40: TRANSGOURMET | P40: COHEN SCALI LAURENT | Q40: 11300 | R40: 02/03/2026 10:12 | S40: En exploitation | T40: VF3MRHPYEPS172792 | U40: 2050 | V40: Electricité + essence | W40: 126 | X40: 7 | Y40: M1 | Z40: =_xlfn.XLOOKUP(E40, Commandes!F:F, Commandes!D:D) -> #N/A
A41: DELTA | B41: VP | C41: SITE RUNGIS DELTA | D41: GV920PZ | E41: GV-920-PZ | F41: SUV | G41: 3 | H41: RENAULT | I41: CAPTUR | J41: EVO E-Tech Full hybride 145ch non rechargeable | K41: 08/03/2024 | L41: 29/03/2024 09:20 | N41: Achat neuf | O41: TRANSGOURMET | Q41: 37800 | R41: 11/03/2026 00:00 | S41: Immobilisé | T41: VF1RJB00972488345 | U41: 1896 | V41: Electricité + essence | W41: 110 | X41: 5 | Y41: M1 | Z41: =_xlfn.XLOOKUP(E41, Commandes!F:F, Commandes!D:D) -> #N/A
A42: DELTA | B42: VU | C42: SITE RUNGIS DELTA | D42: GX438YG | E42: GX-438-YG | G42: 1 | H42: RENAULT | I42: EXPRESS VAN | J42: CONFORT Tce 100-22 | K42: 28/06/2024 | L42: 08/07/2024 09:35 | N42: Achat neuf | O42: TRANSGOURMET | P42: CHAUDERON JEAN PHILIPPE | Q42: 9998 | R42: 23/02/2026 09:25 | S42: En exploitation | T42: VF1RJK00772558537 | U42: 1871 | V42: Essence | W42: 150 | X42: 8 | Y42: N1 | Z42: =_xlfn.XLOOKUP(E42, Commandes!F:F, Commandes!D:D) -> #N/A
A43: DELTA | B43: VUL | C43: SITE RUNGIS DELTA | D43: GN778QW | E43: GN-778-QW | F43: 3T5 | G43: 3T5 | H43: FIAT PROFESSIONAL | I43: DUCATO | K43: 28/04/2023 | L43: 21/06/2023 00:00 | N43: Location Moyenne Durée | O43: PETIT FORESTIER | Q43: 400000 | R43: 25/07/2025 12:34 | S43: En exploitation | T43: ZFA25000002W57876 | U43: 3500 | V43: Gazole | W43: 294 | X43: 7 | Y43: N1 | Z43: =_xlfn.XLOOKUP(E43, Commandes!F:F, Commandes!D:D) -> GHN6-ZSM-MTN
A44: DELTA | B44: VUL | C44: SITE RUNGIS DELTA | D44: GN898DP | E44: GN-898-DP | F44: 3T5 | G44: 3T5 | H44: FIAT PROFESSIONAL | I44: DUCATO | K44: 03/04/2023 | L44: 25/04/2023 00:00 | N44: Location Moyenne Durée | O44: PETIT FORESTIER | Q44: 39525 | R44: 11/02/2026 10:22 | S44: En exploitation | T44: ZFA25000002W57547 | U44: 3500 | V44: Gazole | W44: 293 | X44: 7 | Y44: N1 | Z44: =_xlfn.XLOOKUP(E44, Commandes!F:F, Commandes!D:D) -> GWPY-WD9-G35
A45: DELTA | B45: VUL | C45: SITE RUNGIS DELTA | D45: GR194XM | E45: GR-194-XM | F45: 3T5 | G45: 3T5 | H45: IVECO | I45: 35C14 | K45: 19/10/2023 | L45: 27/10/2023 00:00 | N45: Location longue durée | O45: PETIT FORESTIER | Q45: 120000 | R45: 28/02/2026 09:45 | S45: En exploitation | T45: ZCFCP35A00D731427 | U45: 3500 | V45: Gazole | W45: 0 | X45: 8 | Y45: N1 | Z45: =_xlfn.XLOOKUP(E45, Commandes!F:F, Commandes!D:D) -> GZFU-AK8-MGC
A46: DELTA | B46: VUL | C46: SITE RUNGIS DELTA | D46: GS180PT | E46: GS-180-PT | F46: 3T5 | G46: 3T5 | H46: IVECO | I46: 35C14 | K46: 24/11/2023 | L46: 18/12/2023 00:00 | N46: Location Moyenne Durée | O46: PETIT FORESTIER | P46: DJADJA ABDERRAHMANE | Q46: 72250 | R46: 10/03/2026 10:43 | S46: En exploitation | T46: ZCFCP35A70D731747 | U46: 35000 | V46: Gazole | W46: 0 | X46: 8 | Y46: N1 | Z46: =_xlfn.XLOOKUP(E46, Commandes!F:F, Commandes!D:D) -> GJ7F-MK2-MT7
A47: DELTA | B47: VUL | C47: SITE RUNGIS DELTA | D47: GS363GY | E47: GS-363-GY | F47: 3T5 | G47: 3T5 | H47: IVECO | I47: 35C14 | K47: 09/11/2023 | L47: 23/11/2023 00:00 | N47: Location Moyenne Durée | O47: PETIT FORESTIER | P47: CELINI RUDDY | Q47: 92000 | R47: 11/03/2026 08:36 | S47: En exploitation | T47: ZCFCP35A00D731749 | U47: 3500 | V47: Gazole | W47: 0 | X47: 8 | Y47: N1 | Z47: =_xlfn.XLOOKUP(E47, Commandes!F:F, Commandes!D:D) -> G77G-86T-937
A48: DELTA | B48: VUL | C48: SITE RUNGIS DELTA | D48: GS750JC | E48: GS-750-JC | F48: 3T5 | G48: 3T5 | H48: IVECO | I48: 35C14 | K48: 13/11/2023 | L48: 13/11/2023 00:00 | N48: Location longue durée | O48: PETIT FORESTIER | P48: MAHIOU HAMID | Q48: 88651 | R48: 30/01/2026 07:27 | S48: En exploitation | T48: ZCFCP35A30D731745 | U48: 3500 | V48: Gazole | W48: 0 | X48: 8 | Y48: N1 | Z48: =_xlfn.XLOOKUP(E48, Commandes!F:F, Commandes!D:D) -> GUSM-H9P-NA2
A49: DELTA | B49: VUL | C49: SITE RUNGIS DELTA | D49: GS917TE | E49: GS-917-TE | F49: 3T5 | G49: 3T5 | H49: IVECO | I49: 40C14N | K49: 18/07/2023 | L49: 17/01/2024 00:00 | N49: Location Moyenne Durée | O49: PETIT FORESTIER | Q49: 50000 | R49: 11/12/2025 10:09 | S49: En exploitation | T49: ZCFCS42A705539571 | U49: 3500 | V49: GNV | W49: 0 | X49: 8 | Y49: N2 | Z49: =_xlfn.XLOOKUP(E49, Commandes!F:F, Commandes!D:D) -> GTT9-XJ2-7K7
A50: DELTA | B50: VUL | C50: SITE RUNGIS DELTA | D50: GS921FW | E50: GS-921-FW | F50: 3T5 | G50: 3T5 | H50: IVECO | I50: 35C14 | K50: 07/11/2023 | L50: 14/11/2023 00:00 | N50: Location longue durée | O50: PETIT FORESTIER | P50: KACIMI SAMIR | Q50: 58160 | R50: 07/01/2026 05:38 | S50: En exploitation | T50: ZCFCP35A50D731746 | U50: 3500 | V50: Gazole | W50: 0 | X50: 8 | Y50: N1 | Z50: =_xlfn.XLOOKUP(E50, Commandes!F:F, Commandes!D:D) -> G3M8-RJN-VU3
A51: DELTA | B51: VUL | C51: SITE RUNGIS DELTA | D51: GT411DN | E51: GT-411-DN | F51: 3T5 | G51: 3T5 | H51: IVECO | I51: 35C14 | K51: 20/12/2023 | L51: 02/01/2024 00:00 | N51: Location Moyenne Durée | O51: PETIT FORESTIER | P51: GRES PATRICK | Q51: 112144 | R51: 11/02/2026 03:47 | S51: En exploitation | T51: ZCFCP35A20D731428 | U51: 3500 | V51: Gazole | W51: 0 | X51: 8 | Y51: N1 | Z51: =_xlfn.XLOOKUP(E51, Commandes!F:F, Commandes!D:D) -> G5ZW-AH7-7MN
A52: DELTA | B52: VUL | C52: SITE RUNGIS DELTA | D52: GT494NY | E52: GT-494-NY | F52: 3T5 | G52: 3T5 | H52: RENAULT TRUCKS | I52: MASTER ZE | K52: 12/01/2024 | L52: 27/02/2024 08:00 | N52: Location longue durée | O52: PETIT FORESTIER | Q52: 411 | R52: 27/02/2024 08:00 | S52: En exploitation | T52: VF1VAE00070169427 | U52: 3500 | V52: Electricité | W52: 0 | X52: 7 | Y52: N1 | Z52: =_xlfn.XLOOKUP(E52, Commandes!F:F, Commandes!D:D) -> GGMF-GRK-ZUG
A53: DELTA | B53: VUL | C53: SITE RUNGIS DELTA | D53: GT619BM | E53: GT-619-BM | F53: 3T5 | G53: 3T5 | H53: IVECO | I53: 35C14 | K53: 15/12/2023 | L53: 29/12/2023 00:00 | N53: Location Moyenne Durée | O53: PETIT FORESTIER | P53: RIEGEL REMI | Q53: 83359 | R53: 04/03/2026 08:32 | S53: En exploitation | T53: ZCFCP35A90D731748 | U53: 3500 | V53: Gazole | W53: 0 | X53: 8 | Y53: N1 | Z53: =_xlfn.XLOOKUP(E53, Commandes!F:F, Commandes!D:D) -> G4Y2-JDD-6R8
A54: SEAFOOD | B54: VP | C54: SITE SEAFOOD RUNGIS MIN C5 | D54: FJ486RQ | E54: FJ-486-RQ | F54: SUV | G54: 3 | H54: RENAULT | I54: CAPTUR | J54: Business Dci 90 | K54: 27/08/2019 | L54: 11/09/2019 00:00 | N54: Achat neuf | O54: TRANSGOURMET | Q54: 108233 | R54: 26/11/2025 10:59 | S54: En exploitation | T54: VF1R8700643788697 | U54: 0 | V54: Gazole | W54: 111 | X54: 5 | Z54: =_xlfn.XLOOKUP(E54, Commandes!F:F, Commandes!D:D) -> #N/A
A55: SEAFOOD | B55: VP | C55: SITE SEAFOOD RUNGIS MIN C5 | D55: FJ577RQ | E55: FJ-577-RQ | F55: SUV | G55: 3 | H55: RENAULT | I55: CAPTUR | J55: Business Dci 90 | K55: 27/08/2019 | L55: 11/09/2019 00:00 | N55: Achat neuf | O55: TRANSGOURMET | Q55: 103896 | R55: 30/03/2026 11:50 | S55: En exploitation | T55: VF1R8700863788685 | U55: 0 | V55: Gazole | W55: 111 | X55: 5 | Z55: =_xlfn.XLOOKUP(E55, Commandes!F:F, Commandes!D:D) -> #N/A
A56: SEAFOOD | B56: VP | C56: SITE SEAFOOD RUNGIS MIN C5 | D56: GQ184MS | E56: GQ-184-MS | F56: SUV | G56: 3 | H56: PEUGEOT | I56: 2008 | J56: ACTIVE PACK Pure tech 100 BVM6 | K56: 31/07/2023 | L56: 02/10/2023 15:35 | N56: Achat neuf | O56: TRANSGOURMET | P56: DHEILLY NICOLAS | Q56: 67254 | R56: 24/03/2026 08:36 | S56: En Bourse Inter Site | T56: VR3USSHNKKPJ682900 | U56: 1710 | V56: Essence | W56: 123 | X56: 5 | Y56: M1 | Z56: =_xlfn.XLOOKUP(E56, Commandes!F:F, Commandes!D:D) -> #N/A
A57: SEAFOOD | B57: VP | C57: SITE SEAFOOD RUNGIS MIN C5 | D57: GQ294LT | E57: GQ-294-LT | F57: SUV | G57: Cat 6 | H57: DS | I57: DS 7 | J57: E-TENSE 225 OPERA | K57: 28/07/2023 | L57: 23/08/2023 10:10 | N57: Achat neuf | O57: TRANSGOURMET | P57: SCHIANO LOMORIELLO CHRISTOPHE | Q57: 41837 | R57: 22/03/2026 15:45 | S57: En exploitation | T57: VR1J4DGZUPY576819 | U57: 2325 | V57: Electricité + essence rechargeable | W57: 28 | X57: 10 | Y57: M1 | Z57: =_xlfn.XLOOKUP(E57, Commandes!F:F, Commandes!D:D) -> #N/A
A58: SEAFOOD | B58: VP | C58: SITE SEAFOOD RUNGIS MIN C5 | D58: GQ922MX | E58: GQ-922-MX | F58: SUV | G58: 3 | H58: PEUGEOT | I58: 2008 | J58: ACTIVE PACK Pure tech 100 BVM6 | K58: 31/07/2023 | L58: 06/10/2023 10:00 | N58: Achat neuf | O58: TRANSGOURMET | P58: CARLIER AMELIE | Q58: 45156 | R58: 30/03/2026 12:05 | S58: En exploitation | T58: VR3USHNKKPJ682896 | U58: 1710 | V58: Essence | W58: 123 | X58: 5 | Y58: M1 | Z58: =_xlfn.XLOOKUP(E58, Commandes!F:F, Commandes!D:D) -> #N/A
A59: SEAFOOD | B59: VP | C59: SITE SEAFOOD RUNGIS MIN C5 | D59: GR267SZ | E59: GR-267-SZ | F59: SUV | G59: 3 | H59: PEUGEOT | I59: 2008 | J59: ACTIVE PACK Pure tech 100 BVM6 | K59: 11/10/2023 | L59: 17/10/2023 11:10 | N59: Achat neuf | O59: TRANSGOURMET | P59: THIERRY JEREMY | Q59: 155000 | R59: 18/03/2026 12:17 | S59: En exploitation | T59: VR3USHNKKPJ799478 | U59: 1710 | V59: Essence | W59: 123 | X59: 5 | Y59: M1 | Z59: =_xlfn.XLOOKUP(E59, Commandes!F:F, Commandes!D:D) -> #N/A
A60: SEAFOOD | B60: VP | C60: SITE SEAFOOD RUNGIS MIN C5 | D60: GR971JS | E60: GR-971-JS | F60: SUV | G60: 3 | H60: PEUGEOT | I60: 2008 | J60: ACTIVE PACK Pure tech 100 BVM6 | K60: 25/09/2023 | L60: 06/10/2023 09:35 | N60: Achat neuf | O60: TRANSGOURMET | P60: DEBREE VINCENT | Q60: 68725 | R60: 12/02/2026 15:37 | S60: En exploitation | T60: VR3USHNKKPJ799477 | U60: 1710 | V60: Essence | W60: 123 | X60: 5 | Y60: M1 | Z60: =_xlfn.XLOOKUP(E60, Commandes!F:F, Commandes!D:D) -> #N/A
A61: SEAFOOD | B61: VP | C61: SITE SEAFOOD RUNGIS MIN C5 | D61: GR973JS | E61: GR-973-JS | F61: SUV | G61: 3 | H61: PEUGEOT | I61: 2008 | J61: ACTIVE PACK Pure tech 100 BVM6 | K61: 25/09/2023 | L61: 18/10/2023 00:00 | N61: Achat neuf | O61: TRANSGOURMET | P61: TARNAC JULIEN | Q61: 132073 | R61: 26/03/2026 12:44 | S61: En exploitation | T61: VR3USHNKKPJ799476 | U61: 1710 | V61: Essence | W61: 123 | X61: 5 | Y61: M1 | Z61: =_xlfn.XLOOKUP(E61, Commandes!F:F, Commandes!D:D) -> #N/A
A62: SEAFOOD | B62: VP | C62: SITE SEAFOOD RUNGIS MIN C5 | D62: GR974JS | E62: GR-974-JS | F62: SUV | G62: 3 | H62: PEUGEOT | I62: 2008 | J62: ACTIVE PACK Pure tech 100 BVM6 | K62: 25/09/2023 | L62: 05/10/2023 10:25 | N62: Achat neuf | O62: TRANSGOURMET | P62: RAYNAUD LUCIE LAURE | Q62: 47255 | R62: 24/03/2026 08:54 | S62: En exploitation | T62: VR3USHNKKPJ795790 | U62: 17410 | V62: Essence | W62: 123 | X62: 5 | Y62: M1 | Z62: =_xlfn.XLOOKUP(E62, Commandes!F:F, Commandes!D:D) -> #N/A
A63: SEAFOOD | B63: VP | C63: SITE SEAFOOD RUNGIS MIN C5 | D63: GV237PZ | E63: GV-237-PZ | F63: Break | G63: 3 | H63: RENAULT | I63: MEGANE4 ESTATE | J63: EVOLUTION TCe 140 EDC-23 | K63: 08/03/2024 | L63: 29/03/2024 13:25 | N63: Achat neuf | O63: TRANSGOURMET | P63: LE BIHAN THIERRY | Q63: 50573 | R63: 27/03/2026 16:14 | S63: En exploitation | T63: VF1RFB00572400828 | U63: 1888 | V63: Essence | W63: 138 | X63: 7 | Y63: M1 | Z63: =_xlfn.XLOOKUP(E63, Commandes!F:F, Commandes!D:D) -> #N/A
A64: SEAFOOD | B64: VP | C64: SITE SEAFOOD RUNGIS MIN C5 | D64: GV413LQ | E64: GV-413-LQ | F64: SUV | G64: 5 | H64: PEUGEOT | I64: 3008 | J64: ACTIVE PACK hybride 136e-DCs6 | K64: 29/02/2024 | L64: 18/03/2024 11:00 | N64: Achat neuf | O64: TRANSGOURMET | P64: LAMARRE LAURENT | Q64: 75480 | R64: 31/03/2026 12:35 | S64: En exploitation | T64: VF3MRHPYERS014725 | U64: 2050 | V64: Electricité + essence | W64: 0 | X64: 7 | Y64: M1 | Z64: =_xlfn.XLOOKUP(E64, Commandes!F:F, Commandes!D:D) -> #N/A
A65: SEAFOOD | B65: VP | C65: SITE SEAFOOD RUNGIS MIN C5 | D65: GW201SV | E65: GW-201-SV | F65: Break | G65: 4 | H65: PEUGEOT | I65: 308 SW | J65: ACTIVE PACK Pure tech 130 EAT8 | K65: 30/04/2024 | L65: 11/07/2024 09:00 | N65: Achat neuf | O65: TRANSGOURMET | P65: LEPLOMB ALEXANDRE | Q65: 30786 | R65: 20/03/2026 13:48 | S65: En exploitation | T65: VR3FRHNS8RY543845 | U65: 1860 | V65: Essence | W65: 128 | X65: 7 | Y65: M1 | Z65: =_xlfn.XLOOKUP(E65, Commandes!F:F, Commandes!D:D) -> #N/A
A66: SEAFOOD | B66: VP | C66: SITE SEAFOOD RUNGIS MIN C5 | D66: GW243NK | E66: GW-243-NK | F66: SUV | G66: 3 | H66: RENAULT | I66: CAPTUR | J66: EVO E-Tech Full hybride 145ch non rechargeable | K66: 23/04/2024 | L66: 29/05/2024 09:40 | N66: Achat neuf | O66: TRANSGOURMET | P66: LAZARD MELANIE | Q66: 22271 | R66: 06/03/2026 12:35 | S66: En exploitation | T66: VF1RJB00972787351 | U66: 1896 | V66: Electricité + essence | W66: 110 | X66: 5 | Y66: M1 | Z66: =_xlfn.XLOOKUP(E66, Commandes!F:F, Commandes!D:D) -> #N/A
A67: SEAFOOD | B67: VP | C67: SITE SEAFOOD RUNGIS MIN C5 | D67: GW339NK | E67: GW-339-NK | F67: SUV | G67: 3 | H67: RENAULT | I67: CAPTUR | J67: EVO E-Tech Full hybride 145ch non rechargeable | K67: 23/04/2024 | L67: 23/05/2024 16:00 | N67: Achat neuf | O67: TRANSGOURMET | P67: DUVAL CORALIE | Q67: 52600 | R67: 13/03/2026 07:26 | S67: En exploitation | T67: VF1RJB00X72836511 | U67: 1896 | V67: Electricité + essence | W67: 110 | X67: 5 | Y67: M1 | Z67: =_xlfn.XLOOKUP(E67, Commandes!F:F, Commandes!D:D) -> #N/A
A68: SEAFOOD | B68: VP | C68: SITE SEAFOOD RUNGIS MIN C5 | D68: GW375NK | E68: GW-375-NK | F68: SUV | G68: 3 | H68: RENAULT | I68: CAPTUR | J68: EVO E-Tech Full hybride 145ch non rechargeable | K68: 23/04/2024 | L68: 29/05/2024 09:40 | N68: Achat neuf | O68: TRANSGOURMET | P68: DAHMANE HAMZA | Q68: 22900 | R68: 26/03/2026 20:15 | S68: En exploitation | T68: VF1RJB00772836515 | U68: 1896 | V68: Electricité + essence | W68: 110 | X68: 5 | Y68: M1 | Z68: =_xlfn.XLOOKUP(E68, Commandes!F:F, Commandes!D:D) -> #N/A
A69: SEAFOOD | B69: VP | C69: SITE SEAFOOD RUNGIS MIN C5 | D69: GY730CR | E69: GY-730-CR | F69: Berline | G69: 4 | H69: RENAULT | I69: ARKANA | J69: EVOLUTION E-Tech Hybride 145 | K69: 08/07/2024 | L69: 24/07/2024 10:25 | N69: Achat neuf | O69: TRANSGOURMET | P69: BRASSAS FABRICE | Q69: 54091 | R69: 26/03/2026 16:05 | S69: En exploitation | T69: VF1RJL005UC489648 | U69: 0 | V69: Electricité + essence | W69: 108 | X69: 5 | Z69: =_xlfn.XLOOKUP(E69, Commandes!F:F, Commandes!D:D) -> #N/A
A70: SEAFOOD | B70: VU | C70: SITE SEAFOOD RUNGIS MIN C5 | D70: FN896HX | E70: FN-896-HX | G70: 2 | H70: RENAULT | I70: CLIO 5 | J70: STE AIR NAV Blue dCi 85 | K70: 29/01/2020 | L70: 01/12/2020 00:00 | N70: Achat neuf | O70: TRANSGOURMET | P70: ANDHUM BACAR | Q70: 221125 | R70: 25/03/2026 10:45 | S70: En exploitation | T70: VF1RJA00X64368941 | U70: 1702 | V70: Gazole | W70: 95 | X70: 4 | Y70: M1 | Z70: =_xlfn.XLOOKUP(E70, Commandes!F:F, Commandes!D:D) -> #N/A
A71: SEAFOOD | B71: VUL | C71: SITE SEAFOOD RUNGIS MIN C5 | D71: EP901AB | E71: EP-901-AB | F71: 3T5 | G71: 3T5 | H71: FIAT PROFESSIONAL | I71: DOBLO | K71: 06/07/2017 | L71: 01/04/2025 00:00 | N71: Location longue durée | O71: PETIT FORESTIER | P71: JODON OLIVIER | Q71: 194070 | R71: 14/11/2025 12:22 | S71: En exploitation | T71: ZFA26300006D64638 | U71: 2510 | V71: Gazole | W71: 149 | X71: 5 | Z71: =_xlfn.XLOOKUP(E71, Commandes!F:F, Commandes!D:D) -> #N/A
A72: SEAFOOD | B72: VUL | C72: SITE SEAFOOD RUNGIS MIN C5 | D72: FF431CN | E72: FF-431-CN | F72: 3T5 | G72: 3T5 | H72: IVECO | I72: 35S14 | K72: 01/04/2019 | L72: 22/08/2024 08:00 | N72: Location Moyenne Durée | O72: PETIT FORESTIER | P72: SAKHO YAHAYE | Q72: 299600 | R72: 16/07/2025 14:55 | S72: En exploitation | T72: ZCFC135800D632914 | U72: 3500 | V72: Gazole | W72: 0 | X72: 8 | Y72: N2 | Z72: =_xlfn.XLOOKUP(E72, Commandes!F:F, Commandes!D:D) -> #N/A
A73: SEAFOOD | B73: VUL | C73: SITE SEAFOOD RUNGIS MIN C5 | D73: FH692PD | E73: FH-692-PD | F73: 3T5 | G73: 3T5 | H73: FIAT PROFESSIONAL | I73: DUCATO | K73: 03/07/2019 | L73: 05/01/2026 04:00 | N73: Location longue durée | O73: PETIT FORESTIER | P73: KAMASSOKHO OUSMANE | Q73: 45000 | R73: 06/03/2026 11:49 | S73: Immobilisé | T73: ZFA25000002L34860 | U73: 3500 | V73: Gazole | W73: 177 | X73: 8 | Y73: N1 | Z73: =_xlfn.XLOOKUP(E73, Commandes!F:F, Commandes!D:D) -> #N/A
A74: SEAFOOD | B74: VUL | C74: SITE SEAFOOD RUNGIS MIN C5 | D74: GF420DW | E74: GF-420-DW | F74: 3T5 | G74: 3T5 | H74: IVECO | I74: 35C14 | K74: 14/03/2022 | L74: 01/03/2025 00:00 | N74: Location Moyenne Durée | O74: PETIT FORESTIER | P74: AZZABI MOHAMED | Q74: 225699 | R74: 28/06/2025 10:31 | S74: En exploitation | T74: ZCFCP35A20D703032 | U74: 3500 | V74: Gazole | W74: 0 | X74: 8 | Y74: N1 | Z74: =_xlfn.XLOOKUP(E74, Commandes!F:F, Commandes!D:D) -> #N/A
A75: SEAFOOD | B75: VUL | C75: SITE SEAFOOD RUNGIS MIN C5 | D75: GN118TT | E75: GN-118-TT | F75: 3T5 | G75: 3T5 | H75: FIAT PROFESSIONAL | K75: 05/05/2023 | L75: 01/06/2023 00:00 | N75: Location longue durée | O75: PETIT FORESTIER | P75: TAVARES CRISTO JOAO MENDES LUCAS | Q75: 145898 | R75: 18/02/2026 06:44 | S75: En exploitation | T75: ZFA25000002W22980 | U75: 3500 | V75: Gazole | W75: 300 | X75: 7 | Y75: N1 | Z75: =_xlfn.XLOOKUP(E75, Commandes!F:F, Commandes!D:D) -> #N/A
A76: SEAFOOD | B76: VUL | C76: SITE SEAFOOD RUNGIS MIN C5 | D76: GN786WA | E76: GN-786-WA | F76: 3T5 | G76: 3T5 | H76: IVECO | I76: 35C14 | K76: 10/05/2023 | L76: 01/06/2023 00:00 | N76: Location longue durée | O76: PETIT FORESTIER | P76: MENNANE M HAND | Q76: 75185 | R76: 29/03/2026 15:13 | S76: En exploitation | T76: ZCFCP35A90D731426 | U76: 3500 | V76: Gazole | W76: 0 | X76: 8 | Y76: N1 | Z76: =_xlfn.XLOOKUP(E76, Commandes!F:F, Commandes!D:D) -> #N/A
A77: SEAFOOD | B77: VUL | C77: SITE SEAFOOD RUNGIS MIN C5 | D77: GN940KC | E77: GN-940-KC | F77: 3T5 | G77: 3T5 | H77: FIAT PROFESSIONAL | I77: DUCATO | K77: 18/04/2023 | L77: 12/05/2023 00:00 | N77: Location longue durée | O77: PETIT FORESTIER | P77: BONALDI GILLES | Q77: 82528 | R77: 28/03/2026 12:09 | S77: En exploitation | T77: ZFA25000002W25389 | U77: 3500 | V77: Gazole | W77: 300 | X77: 7 | Y77: N1 | Z77: =_xlfn.XLOOKUP(E77, Commandes!F:F, Commandes!D:D) -> #N/A
A78: SEAFOOD | B78: VUL | C78: SITE SEAFOOD RUNGIS MIN C5 | D78: GP329TN | E78: GP-329-TN | F78: 3T5 | G78: 3T5 | H78: FIAT PROFESSIONAL | I78: DUCATO | K78: 26/06/2023 | L78: 07/07/2023 00:00 | N78: Location longue durée | O78: PETIT FORESTIER | P78: ABBASSI MOHAMED | Q78: 400001 | R78: 18/11/2024 10:07 | S78: En exploitation | T78: ZFA25000002W25577 | U78: 3500 | V78: Gazole | W78: 300 | X78: 7 | Y78: N1 | Z78: =_xlfn.XLOOKUP(E78, Commandes!F:F, Commandes!D:D) -> #N/A
A79: SEAFOOD | B79: VUL | C79: SITE SEAFOOD RUNGIS MIN C5 | D79: GP986HG | E79: GP-986-HG | F79: 3T5 | G79: 3T5 | H79: FIAT PROFESSIONAL | I79: DUCATO | K79: 05/06/2023 | L79: 01/11/2023 00:00 | N79: Location longue durée | O79: PETIT FORESTIER | P79: LEVAIN BRUNO | Q79: 230548 | R79: 08/07/2025 13:37 | S79: En exploitation | T79: ZFA25000002W55351 | U79: 3500 | V79: Gazole | W79: 299 | X79: 7 | Y79: N1 | Z79: =_xlfn.XLOOKUP(E79, Commandes!F:F, Commandes!D:D) -> #N/A
A80: SEAFOOD | B80: VUL | C80: SITE SEAFOOD RUNGIS MIN C5 | D80: GV216WL | E80: GV-216-WL | F80: 3T5 | G80: 3T5 | H80: RENAULT TRUCKS | I80: MASTER ZE | K80: 21/03/2024 | L80: 01/04/2024 08:00 | N80: Location longue durée | O80: PETIT FORESTIER | P80: BERRAHOU SOFIANE | Q80: 10 | R80: 01/04/2024 08:00 | S80: En exploitation | T80: VF1VAE00970169426 | U80: 3500 | V80: Electricité | W80: 0 | X80: 7 | Y80: N1 | Z80: =_xlfn.XLOOKUP(E80, Commandes!F:F, Commandes!D:D) -> #N/A
A81: SEAFOOD | B81: VUL | C81: SITE SEAFOOD RUNGIS MIN C5 | D81: GW059EN | E81: GW-059-EN | F81: 3T5 | G81: 3T5 | H81: RENAULT TRUCKS | I81: MASTER ZE | K81: 04/04/2024 | L81: 01/04/2024 08:00 | N81: Location longue durée | O81: PETIT FORESTIER | P81: DIAW IBRAHIMA | Q81: 10 | R81: 01/04/2024 08:00 | S81: En exploitation | T81: VF1VAE00570169441 | U81: 3500 | V81: Electricité | W81: 0 | X81: 7 | Y81: N1 | Z81: =_xlfn.XLOOKUP(E81, Commandes!F:F, Commandes!D:D) -> #N/A
A82: SEAFOOD | B82: VUL | C82: SITE SEAFOOD RUNGIS MIN C5 | D82: GW621BK | E82: GW-621-BK | F82: 3T5 | G82: 3T5 | H82: RENAULT TRUCKS | I82: MASTER ZE | K82: 28/03/2024 | L82: 01/04/2024 08:00 | N82: Location longue durée | O82: PETIT FORESTIER | P82: ZROUR ADEL | Q82: 10 | R82: 01/04/2024 08:00 | S82: En exploitation | T82: VF1VAE00770169425 | U82: 3500 | V82: Electricité | W82: 0 | X82: 7 | Y82: N1 | Z82: =_xlfn.XLOOKUP(E82, Commandes!F:F, Commandes!D:D) -> #N/A
A83: SEAFOOD | B83: VUL | C83: SITE SEAFOOD RUNGIS MIN C5 | D83: HF080AN | E83: HF-080-AN | F83: 3T | G83: 3T | H83: RENAULT | I83: KANGOO | K83: 05/08/2025 | L83: 07/10/2025 00:00 | N83: Location longue durée | O83: FRAIKIN | P83: CHOUIKHA EZZEDDINE | Q83: 75127 | R83: 30/03/2026 06:36 | S83: En exploitation | T83: VF1RFK00X72399711 | U83: 2230 | V83: Gazole | W83: 197 | X83: 5 | Y83: N1 | Z83: =_xlfn.XLOOKUP(E83, Commandes!F:F, Commandes!D:D) -> #N/A
A84: SEAFOOD | B84: VUL | C84: SITE SEAFOOD STRASBOURG | D84: FA540VQ | E84: FA-540-VQ | F84: 3T5 | G84: 3T5 | H84: FIAT PROFESSIONAL | I84: DUCATO | K84: 02/10/2018 | L84: 28/07/2025 07:30 | N84: Location Moyenne Durée | O84: PETIT FORESTIER | P84: SINTEFF ARNAUD | Q84: 242305 | R84: 30/03/2026 11:06 | S84: En exploitation | T84: ZFA35000002H67452 | U84: 3500 | V84: Gazole | W84: 177 | X84: 8 | Y84: N1 | Z84: =_xlfn.XLOOKUP(E84, Commandes!F:F, Commandes!D:D) -> #N/A
A85: SEAFOOD | B85: VUL | C85: SITE SEAFOOD STRASBOURG | D85: FY869KY | E85: FY-869-KY | F85: 3T5 | G85: 3T5 | H85: FIAT PROFESSIONAL | I85: DUCATO | K85: 08/04/2021 | L85: 17/12/2025 07:30 | N85: Location longue durée | O85: PETIT FORESTIER | P85: LAMOOT NICOLAS | Q85: 216233 | R85: 13/02/2026 09:56 | S85: En exploitation | T85: ZFA25000002S11461 | U85: 3500 | V85: Gazole | W85: 0 | X85: 8 | Y85: N1 | Z85: =_xlfn.XLOOKUP(E85, Commandes!F:F, Commandes!D:D) -> #N/A
A86: SEAFOOD | B86: VUL | C86: SITE SEAFOOD STRASBOURG | D86: GS750AQ | E86: GS-750-AQ | F86: 3T5 | G86: 3T5 | H86: RENAULT TRUCKS | I86: MASTER ZE | K86: 18/09/2023 | L86: 06/05/2025 14:00 | N86: Location Moyenne Durée | O86: PETIT FORESTIER | Q86: 205795 | R86: 24/07/2025 08:07 | S86: En exploitation | T86: VF1VAE00870169434 | U86: 3500 | V86: Electricité | W86: 0 | X86: 7 | Y86: N1 | Z86: =_xlfn.XLOOKUP(E86, Commandes!F:F, Commandes!D:D) -> #N/A
A87: SIEGE VALENTON | B87: VP | C87: SIEGE CASTELNAU D ESTRETEFONDS | D87: GS074KC | E87: GS-074-KC | F87: SUV | G87: Cat 6 | H87: DS | I87: DS 7 CROSSBACK | J87: E-TENSE 2x4 225 PERF LINE | K87: 15/11/2023 | L87: 29/12/2023 00:00 | N87: Achat neuf | O87: TRANSGOURMET | P87: PIE NICOLAS | Q87: 62881 | R87: 30/03/2026 08:51 | S87: En exploitation | T87: VR1J4DGZUPY626010 | U87: 2325 | V87: Electricité + essence rechargeable | W87: 28 | X87: 10 | Y87: M1 | Z87: =_xlfn.XLOOKUP(E87, Commandes!F:F, Commandes!D:D) -> #N/A
A88: SIEGE VALENTON | B88: VP | C88: SIEGE GUEMAR | D88: GK341XB | E88: GK-341-XB | F88: Berline | G88: Cat 5 | H88: RENAULT | I88: ARKANA | J88: Business E-Tech Hybride 145 | K88: 30/11/2022 | L88: 23/12/2022 11:30 | N88: Achat neuf | O88: TRANSGOURMET | P88: COUCHOT CYNTHIA | Q88: 84012 | R88: 16/03/2026 08:16 | S88: En exploitation | T88: VF1RJL008UC378625 | U88: 1961 | V88: Electricité + essence | W88: 106 | X88: 5 | Y88: M1 | Z88: =_xlfn.XLOOKUP(E88, Commandes!F:F, Commandes!D:D) -> #N/A
A89: SIEGE VALENTON | B89: VP | C89: SIEGE SAINT LOUBES | D89: EZ336MD | E89: EZ-336-MD | F89: SUV | G89: 5 | H89: RENAULT | I89: KADJAR | J89: BUSINESS 110 cv EDC | K89: 31/07/2018 | L89: 27/09/2018 00:00 | N89: Achat neuf | O89: TRANSGOURMET | P89: BERIOL CHRISTOPHE | Q89: 239763 | R89: 31/03/2026 18:27 | S89: En exploitation | T89: VF1RFE00061094661 | U89: 0 | V89: Gazole | W89: 99 | X89: 5 | Z89: =_xlfn.XLOOKUP(E89, Commandes!F:F, Commandes!D:D) -> #N/A
A90: SIEGE VALENTON | B90: VP | C90: SIEGE SAINT LOUBES | D90: GK559RR | E90: GK-559-RR | F90: SUV | G90: 5 | H90: PEUGEOT | I90: 3008 | J90: ALLURE PACK HYBRID 225 e-EAT8 | K90: 23/11/2022 | L90: 21/03/2023 15:00 | N90: Achat neuf | O90: TRANSGOURMET | P90: FRETIER GHISLAIN | Q90: 97562 | R90: 30/03/2026 10:31 | S90: En exploitation | T90: VF3M4DGZUNS128667 | U90: 2290 | V90: Electricité + essence rechargeable | W90: 31 | X90: 10 | Y90: M1 | Z90: =_xlfn.XLOOKUP(E90, Commandes!F:F, Commandes!D:D) -> #N/A
A91: SIEGE VALENTON | B91: VP | C91: SIEGE SAINT LOUBES | D91: GM521EN | E91: GM-521-EN | F91: SUV | G91: Cat 6 (DR) | H91: BMW | I91: X5 xDRIVE45e | J91: 394ch BVA8 Hybride M Sport | K91: 16/02/2023 | L91: 17/02/2023 00:00 | N91: Achat neuf | O91: TRANSGOURMET | P91: DECROIX ERIC | Q91: 68096 | R91: 30/03/2026 14:35 | S91: En exploitation | T91: WBATA61009R17206 | U91: 3150 | V91: Electricité + essence rechargeable | W91: 29 | X91: 17 | Y91: M1G | Z91: =_xlfn.XLOOKUP(E91, Commandes!F:F, Commandes!D:D) -> #N/A
A92: SIEGE VALENTON | B92: VP | C92: SIEGE SAINT LOUBES | D92: GM864LE | E92: GM-864-LE | F92: SUV | G92: 5 | H92: PEUGEOT | I92: 3008 | J92: ALLURE PACK HYBRID 225 e-EAT8 | K92: 28/02/2023 | L92: 27/04/2023 15:30 | N92: Achat neuf | O92: TRANSGOURMET | P92: DELBERGHE LAURENT | Q92: 88398 | R92: 29/03/2026 17:16 | S92: En exploitation | T92: VF3M4DGZUPS022771 | U92: 2290 | V92: Electricité + essence rechargeable | W92: 28 | X92: 10 | Y92: M1 | Z92: =_xlfn.XLOOKUP(E92, Commandes!F:F, Commandes!D:D) -> #N/A
A93: SIEGE VALENTON | B93: VP | C93: SIEGE SAINT LOUBES | D93: GQ645LV | E93: GQ-645-LV | F93: SUV | G93: Cat 6 | H93: DS | I93: DS 7 CROSSBACK | J93: E-TENSE 2x4 225 PERF LINE | K93: 28/07/2023 | L93: 10/10/2023 17:00 | N93: Achat neuf | O93: TRANSGOURMET | P93: RIDOUANI HICHAM | Q93: 107000 | R93: 10/03/2026 18:47 | S93: En exploitation | T93: VR1J4DGZUPY590800 | U93: 2325 | V93: Electricité + essence rechargeable | W93: 28 | X93: 10 | Y93: M1 | Z93: =_xlfn.XLOOKUP(E93, Commandes!F:F, Commandes!D:D) -> #N/A
A94: SIEGE VALENTON | B94: VP | C94: SIEGE SAINT LOUBES | D94: GQ701MR | E94: GQ-701-MR | F94: Berline | G94: 4 | H94: PEUGEOT | I94: 308 | J94: ACTIVE PACK PHEV 180 | K94: 31/07/2023 | L94: 13/09/2023 12:57 | N94: Achat neuf | O94: TRANSGOURMET | P94: FERNANDES FLAVIEN | Q94: 60800 | R94: 31/03/2026 08:03 | S94: En exploitation | T94: VR3F3DGXTPY590188 | U94: 2120 | V94: Electricité + essence rechargeable | W94: 23 | X94: 8 | Y94: M1 | Z94: =_xlfn.XLOOKUP(E94, Commandes!F:F, Commandes!D:D) -> #N/A
A95: SIEGE VALENTON | B95: VP | C95: SIEGE SAINT LOUBES | D95: GR257XM | E95: GR-257-XM | F95: Berline | G95: 4 | H95: CITROEN | I95: C4 | J95: PureTech 130 S&S EAT8 Shine | K95: 19/10/2023 | L95: 24/11/2023 09:00 | N95: Achat neuf | O95: TRANSGOURMET | P95: GOUDICHAUD JEROME | Q95: 70960 | R95: 28/03/2026 17:59 | S95: En exploitation | T95: VR7BAHNSBPE068793 | U95: 1755 | V95: Essence | W95: 130 | X95: 7 | Y95: M1 | Z95: =_xlfn.XLOOKUP(E95, Commandes!F:F, Commandes!D:D) -> #N/A
A96: SIEGE VALENTON | B96: VP | C96: SIEGE SAINT LOUBES | D96: GS835PR | E96: GS-835-PR | F96: Berline | G96: Cat 5 | H96: RENAULT | I96: ARKANA | J96: EVOLUTION E-Tech Hybride 145 | K96: 24/11/2023 | L96: 11/12/2023 11:00 | N96: Achat neuf | O96: TRANSGOURMET | P96: RENAUD SANDRINE | Q96: 52923 | R96: 30/03/2026 09:53 | S96: En exploitation | T96: VF1RJL009UC447810 | U96: 1961 | V96: Electricité + essence | W96: 108 | X96: 5 | Y96: M1 | Z96: =_xlfn.XLOOKUP(E96, Commandes!F:F, Commandes!D:D) -> #N/A
A97: SIEGE VALENTON | B97: VP | C97: SIEGE SAINT LOUBES | D97: GX160PJ | E97: GX-160-PJ | F97: Berline | G97: 4 | H97: RENAULT | I97: ARKANA | J97: EVOLUTION E-Tech Hybride 145 | K97: 17/06/2024 | L97: 26/06/2024 10:25 | N97: Achat neuf | O97: TRANSGOURMET | P97: BATY PASCALE | Q97: 18139 | R97: 20/03/2026 18:27 | S97: En exploitation | T97: VF1RJL007UC489702 | U97: 1961 | V97: Electricité + essence | W97: 108 | X97: 5 | Y97: M1 | Z97: =_xlfn.XLOOKUP(E97, Commandes!F:F, Commandes!D:D) -> #N/A
A98: SIEGE VALENTON | B98: VP | C98: SIEGE SAINT LOUBES | D98: GY079QD | E98: GY-079-QD | F98: SUV | G98: 5 | H98: RENAULT | I98: AUSTRAL | J98: TECHNO mild Hybrid160 AUTO | K98: 05/08/2024 | L98: 20/08/2024 10:45 | N98: Achat neuf | O98: TRANSGOURMET | P98: GALLINEAU HERVE | Q98: 25200 | R98: 12/03/2026 10:26 | S98: En exploitation | T98: VF1RHN00073429921 | U98: 2003 | V98: Electricité + essence | W98: 145 | X98: 8 | Y98: M1 | Z98: =_xlfn.XLOOKUP(E98, Commandes!F:F, Commandes!D:D) -> #N/A
A99: SIEGE VALENTON | B99: VP | C99: SIEGE SAINT LOUBES | D99: GY687CR | E99: GY-687-CR | F99: Berline | G99: 4 | H99: RENAULT | I99: ARKANA | J99: EVOLUTION E-Tech Hybride 145 | K99: 08/07/2024 | L99: 13/08/2024 09:00 | N99: Achat neuf | O99: TRANSGOURMET | P99: GALOPIN JEAN LUC | Q99: 18724 | R99: 04/03/2026 18:12 | S99: En exploitation | T99: VF1RJL006UC489707 | U99: 1961 | V99: Electricité + essence | W99: 108 | X99: 5 | Y99: M1 | Z99: =_xlfn.XLOOKUP(E99, Commandes!F:F, Commandes!D:D) -> #N/A
A100: SIEGE VALENTON | B100: VP | C100: SIEGE SAINT LOUBES | D100: GY700CR | E100: GY-700-CR | F100: Berline | G100: 4 | H100: RENAULT | I100: ARKANA | J100: EVOLUTION E-Tech Hybride 145 | K100: 08/07/2024 | L100: 19/08/2024 08:00 | N100: Achat neuf | O100: TRANSGOURMET | P100: SERIS MARION | Q100: 27630 | R100: 21/03/2026 09:57 | S100: En exploitation | T100: VF1RJL003UC489647 | U100: 1961 | V100: Electricité + essence | W100: 108 | X100: 5 | Y100: M1 | Z100: =_xlfn.XLOOKUP(E100, Commandes!F:F, Commandes!D:D) -> #N/A
...
